Workbook

Sheet tab 1 BS 2025 vs 2026
A1: Graniti Vicentia, L.L.C.
A2: Parent Company : Graniti Vicentia LLC
A3: Graniti Comparative Balance Sheet
A4: End of Dec 2025
A6: Options: Activity Only
A7: Financial Row | B7: Amount
B8: As of Jan 2025 | C8: As of Feb 2025 | D8: As of Mar 2025 | E8: As of Apr 2025 | F8: As of May 2025 | G8: As of Jun 2025 | H8: As of Jul 2025 | I8: As of Aug 2025 | J8: As of Sep 2025 | K8: As of Oct 2025 | L8: As of Nov 2025 | M8: As of Dec 2025 | X8: Next tab
X9: 46023
A10: ASSETS
A11: Current Assets
A12: Bank
A13: 10110 - GV Truist Bank - 4637 | B13: 0 | C13: 0 | D13: 0 | E13: 0 | F13: 0 | G13: 0 | H13: 13448.91 | I13: 20771.52 | J13: 567606.78 | K13: -7426.01 | L13: 184430.26 | M13: -62150.43 | X13: =_xlfn.XLOOKUP(A13,'tabhg 1a bs 2026'!A:A,'tabhg 1a bs 2026'!B:B,,) -> -62150.43
A14: 21050 - Amex GVLLC | B14: 0 | C14: 0 | D14: 0 | E14: 0 | F14: 0 | G14: 0 | H14: 0 | I14: 0 | J14: -41575 | K14: -139787.67 | L14: -220613.63 | M14: -298052.26 | X14: =_xlfn.XLOOKUP(A14,'tabhg 1a bs 2026'!A:A,'tabhg 1a bs 2026'!B:B,,) -> -325692.32
A15: A10000 - Cash (GV LLC) (New) | X15: =_xlfn.XLOOKUP(A15,'tabhg 1a bs 2026'!A:A,'tabhg 1a bs 2026'!B:B,,) -> 0
A16: A10001 - Petty Cash On Hand (New) | B16: 7986782.4 | C16: 8712214.3 | D16: 11798097 | E16: 13700989 | F16: 17109150 | G16: -6415602.5 | H16: -6415602.5 | I16: -6415602.5 | J16: -6415602.5 | K16: -6415602.5 | L16: -6415602.5 | M16: -6415602.5 | X16: =_xlfn.XLOOKUP(A16,'tabhg 1a bs 2026'!A:A,'tabhg 1a bs 2026'!B:B,,) -> -6415602.5
A17: A10002 - Allegiance Bank Texas-2243 (New) | B17: 0 | C17: 0 | D17: 0 | E17: 0 | F17: 0 | G17: 936.03 | H17: 529.52 | I17: 529.52 | J17: 529.52 | K17: 529.52 | L17: 1029.52 | M17: 1029.52 | X17: =_xlfn.XLOOKUP(A17,'tabhg 1a bs 2026'!A:A,'tabhg 1a bs 2026'!B:B,,) -> 1029.52
A18: A10003 - Truist Bank - 4637 (New) | B18: 0 | C18: 0 | D18: 0 | E18: 0 | F18: 0 | G18: 8099.13 | H18: 14223.64 | I18: 14223.64 | J18: 14223.64 | K18: -46828.34 | L18: -108571.57 | M18: -175916.84 | X18: =_xlfn.XLOOKUP(A18,'tabhg 1a bs 2026'!A:A,'tabhg 1a bs 2026'!B:B,,) -> 3696129.7
A19: A10004 - Truist - Savings - 4645 (New) | B19: 0 | C19: 0 | D19: 0 | E19: 0 | F19: 0 | G19: 1221.56 | H19: 1176.57 | I19: 1176.58 | J19: 1176.59 | K19: 1176.6 | L19: 1176.61 | M19: 1176.62 | X19: =_xlfn.XLOOKUP(A19,'tabhg 1a bs 2026'!A:A,'tabhg 1a bs 2026'!B:B,,) -> 1176.62
A20: A10005 - CC - Clearing Account (New) | B20: 0 | C20: 0 | D20: 0 | E20: 0 | F20: 0 | G20: -4091.4 | H20: -4091.4 | I20: -4091.4 | J20: -4091.4 | K20: -4091.4 | L20: -4091.4 | M20: -4091.4 | X20: =_xlfn.XLOOKUP(A20,'tabhg 1a bs 2026'!A:A,'tabhg 1a bs 2026'!B:B,,) -> -4091.4
A21: A10006 - Undeposited Funds (New) | B21: 0 | C21: 0 | D21: 0 | E21: 0 | F21: 0 | G21: 277725.74 | H21: 277725.74 | I21: 277725.74 | J21: 277725.74 | K21: 277725.74 | L21: 277725.74 | M21: 277725.74 | X21: =_xlfn.XLOOKUP(A21,'tabhg 1a bs 2026'!A:A,'tabhg 1a bs 2026'!B:B,,) -> 277725.74
A22: Total - A10000 - Cash (GV LLC) (New) | B22: =SUM(B16:B21) -> 7986782.4 | C22: =SUM(C16:C21) -> 8712214.3 | D22: =SUM(D16:D21) -> 11798097 | E22: =SUM(E16:E21) -> 13700989 | F22: =SUM(F16:F21) -> 17109150 | G22: =SUM(G16:G21) -> -6131711.4 | H22: =SUM(H16:H21) -> -6126038.4 | I22: =SUM(I16:I21) -> -6126038.4 | ... M22: =SUM(M16:M21) -> -6315678.8 | X22: =_xlfn.XLOOKUP(A22,'tabhg 1a bs 2026'!A:A,'tabhg 1a bs 2026'!B:B,,) -> -2443632.3
A23: Total Bank | B23: =SUM(B13:B14,B22) -> 7986782.4 | C23: =SUM(C13:C14,C22) -> 8712214.3 | D23: =SUM(D13:D14,D22) -> 11798097 | E23: =SUM(E13:E14,E22) -> 13700989 | F23: =SUM(F13:F14,F22) -> 17109150 | G23: =SUM(G13:G14,G22) -> -6131711.4 | H23: =SUM(H13:H14,H22) -> -6112589.5 | I23: =SUM(I13:I14,I22) -> -6105266.9 | ... M23: =SUM(M13:M14,M22) -> -6675881.5 | X23: =_xlfn.XLOOKUP(A23,'tabhg 1a bs 2026'!A:A,'tabhg 1a bs 2026'!B:B,,) -> -2831475
A24: Accounts Receivable | X24: =_xlfn.XLOOKUP(A24,'tabhg 1a bs 2026'!A:A,'tabhg 1a bs 2026'!B:B,,) -> 0
A25: 11000 - Accounts Receivable | B25: 0 | C25: 0 | D25: 0 | E25: 0 | F25: 0 | G25: 33300 | H25: 95758.88 | I25: 225911.11 | J25: 834928.26 | K25: 1049269.3 | L25: 1031006.8 | M25: 993053.75 | X25: =_xlfn.XLOOKUP(A25,'tabhg 1a bs 2026'!A:A,'tabhg 1a bs 2026'!B:B,,) -> 993053.75
A26: A11000 - Accounts Receivable (GV LLC) (New) | X26: =_xlfn.XLOOKUP(A26,'tabhg 1a bs 2026'!A:A,'tabhg 1a bs 2026'!B:B,,) -> 0
A27: A11001 - Accounts Receivable (New) | B27: 6270885.8 | C27: 6270885.8 | D27: 6270885.8 | E27: 6475450.5 | F27: 7013367.4 | G27: 12119591 | H27: 15802724 | I27: 23151709 | J27: 23162048 | K27: 23820658 | L27: 24435725 | M27: 39415246 | X27: =_xlfn.XLOOKUP(A27,'tabhg 1a bs 2026'!A:A,'tabhg 1a bs 2026'!B:B,,) -> 31840880
A28: A11002 - Accrued Accounts Receivable (New) | B28: 0 | C28: 0 | D28: 0 | E28: 0 | F28: 0 | G28: 15430 | H28: 15430 | I28: 15430 | J28: 15430 | K28: 15430 | L28: 15430 | M28: 15430 | X28: =_xlfn.XLOOKUP(A28,'tabhg 1a bs 2026'!A:A,'tabhg 1a bs 2026'!B:B,,) -> 15430
A29: A11003 - Allowance for Doubtful Accounts (New) | B29: 0 | C29: 0 | D29: 0 | E29: 0 | F29: 0 | G29: -766001.85 | H29: -766001.85 | I29: -766001.85 | J29: -766001.85 | K29: -766001.85 | L29: -766001.85 | M29: -766001.85 | X29: =_xlfn.XLOOKUP(A29,'tabhg 1a bs 2026'!A:A,'tabhg 1a bs 2026'!B:B,,) -> -766001.85
A30: Total - A11000 - Accounts Receivable (GV LLC) (New) | B30: =SUM(B27:B29) -> 6270885.8 | C30: =SUM(C27:C29) -> 6270885.8 | D30: =SUM(D27:D29) -> 6270885.8 | E30: =SUM(E27:E29) -> 6475450.5 | F30: =SUM(F27:F29) -> 7013367.4 | G30: =SUM(G27:G29) -> 11369019 | H30: =SUM(H27:H29) -> 15052152 | I30: =SUM(I27:I29) -> 22401137 | ... M30: =SUM(M27:M29) -> 38664674 | X30: =_xlfn.XLOOKUP(A30,'tabhg 1a bs 2026'!A:A,'tabhg 1a bs 2026'!B:B,,) -> 31090308
A31: Total Accounts Receivable | B31: =SUM(B25,B30) -> 6270885.8 | C31: =SUM(C25,C30) -> 6270885.8 | D31: =SUM(D25,D30) -> 6270885.8 | E31: =SUM(E25,E30) -> 6475450.5 | F31: =SUM(F25,F30) -> 7013367.4 | G31: =SUM(G25,G30) -> 11402319 | H31: =SUM(H25,H30) -> 15147911 | I31: =SUM(I25,I30) -> 22627048 | ... M31: =SUM(M25,M30) -> 39657728 | X31: =_xlfn.XLOOKUP(A31,'tabhg 1a bs 2026'!A:A,'tabhg 1a bs 2026'!B:B,,) -> 32083362
A32: Other Current Asset | X32: =_xlfn.XLOOKUP(A32,'tabhg 1a bs 2026'!A:A,'tabhg 1a bs 2026'!B:B,,) -> 0
A33: 12000 - Inventory | B33: 0 | C33: 0 | D33: 0 | E33: 1740 | F33: 1874.58 | G33: 1874.58 | H33: 249003.98 | I33: 9065776.5 | J33: 1375368.4 | K33: 1678708.7 | L33: 2074540.6 | M33: 2077812.9 | X33: =_xlfn.XLOOKUP(A33,'tabhg 1a bs 2026'!A:A,'tabhg 1a bs 2026'!B:B,,) -> 2078728.2
A34: 13000 - Prepaid Expenses | B34: 0 | C34: 0 | D34: 0 | E34: 0 | F34: 0 | G34: 86072.21 | H34: 2802057.2 | I34: 4481870.7 | J34: 6874155.9 | K34: 8820243.6 | L34: 9605309.8 | M34: 12770664 | X34: =_xlfn.XLOOKUP(A34,'tabhg 1a bs 2026'!A:A,'tabhg 1a bs 2026'!B:B,,) -> 14215715
A35: 15000 - Intercompany Receivable | B35: 0 | C35: 0 | D35: 0 | E35: 0 | F35: 0 | G35: 0 | H35: 0 | I35: 0 | J35: 0 | K35: -18301.82 | L35: -168301.82 | M35: -168301.82 | R35: Gap - accounting vs scm | X35: =_xlfn.XLOOKUP(A35,'tabhg 1a bs 2026'!A:A,'tabhg 1a bs 2026'!B:B,,) -> -168301.82
A36: A12000 - Inventory (GV LLC) (New) | H36: =G37-H37 -> 1345584.5 | N36: tab 5 receipts | O36: tab 6 receipts | P36: recalculated balance | T36: recalculated balance | X36: =_xlfn.XLOOKUP(A36,'tabhg 1a bs 2026'!A:A,'tabhg 1a bs 2026'!B:B,,) -> 0
A37: A12001 - Inventory (New) | B37: 0 | C37: 0 | D37: 0 | E37: 0 | F37: 1538.6 | G37: 14946309 | H37: 13600724 | I37: 7127740 | J37: 5912884.6 | K37: 5226855.2 | L37: 5122429.5 | M37: 4389020 | N37: ='tab12July cogs in sps'!H1235 -> 3347689.8 | O37: ='tab 13 aug cogs in sps'!H5577 -> 51431.11 | P37: =SUM(M37:O37) -> 7788140.8 | R37: =P37-T37 -> -1679930.4 | T37: =SUM(U37:X37) -> 9468071.3 | U37: . | V37: =-'tab 3 bal sheetNtsuite Jan 2026'!J10 -> 417768.92 | W37: =-'tab 3 bal sheetNtsuite Jan 2026'!J9 -> -1462939.7 | X37: =_xlfn.XLOOKUP(A37,'tabhg 1a bs 2026'!A:A,'tabhg 1a bs 2026'!B:B,,) -> 10513242
A38: A12002 - Inventory - In Transit (New) | B38: 0 | C38: 0 | D38: 0 | E38: 0 | F38: 0 | G38: 2135520.9 | H38: 2135520.9 | I38: 2135520.9 | J38: 2135520.9 | K38: 2135520.9 | L38: 2135520.9 | M38: 2135520.9 | U38: . | V38: \ | X38: =_xlfn.XLOOKUP(A38,'tabhg 1a bs 2026'!A:A,'tabhg 1a bs 2026'!B:B,,) -> 2135520.9
A39: A12003 - Obsolete Inventory (New) | B39: 0 | C39: 0 | D39: 0 | E39: 0 | F39: 0 | G39: 899003.97 | H39: 899003.97 | I39: 899003.97 | J39: 899003.97 | K39: 899003.97 | L39: 899003.97 | M39: 899003.97 | X39: =_xlfn.XLOOKUP(A39,'tabhg 1a bs 2026'!A:A,'tabhg 1a bs 2026'!B:B,,) -> 899003.97
A40: A12004 - Hotels Projects/ Tub Surrounds For Obsolete Inventory (New) | B40: 0 | C40: 0 | D40: 0 | E40: 0 | F40: 0 | G40: 1456.86 | H40: 1456.86 | I40: 1456.86 | J40: 1456.86 | K40: 1456.86 | L40: 1456.86 | M40: 1456.86 | X40: =_xlfn.XLOOKUP(A40,'tabhg 1a bs 2026'!A:A,'tabhg 1a bs 2026'!B:B,,) -> 1456.86
A41: A12005 - Inventory Adjustments (New) | B41: 0 | C41: 0 | D41: 0 | E41: 0 | F41: 0 | G41: 18722.87 | H41: 18722.87 | I41: 18722.87 | J41: 18722.87 | K41: 18722.87 | L41: 18722.87 | M41: 18722.87 | X41: =_xlfn.XLOOKUP(A41,'tabhg 1a bs 2026'!A:A,'tabhg 1a bs 2026'!B:B,,) -> 18722.87
A42: A12006 - Inventory Allowances (New) | B42: 0 | C42: 0 | D42: 0 | E42: 0 | F42: 0 | G42: -1000000 | H42: -1000000 | I42: -1000000 | J42: -1000000 | K42: -1000000 | L42: -1000000 | M42: -1000000 | X42: =_xlfn.XLOOKUP(A42,'tabhg 1a bs 2026'!A:A,'tabhg 1a bs 2026'!B:B,,) -> -1000000
A43: Total - A12000 - Inventory (GV LLC) (New) | B43: =SUM(B37:B42) -> 0 | C43: =SUM(C37:C42) -> 0 | D43: =SUM(D37:D42) -> 0 | E43: =SUM(E37:E42) -> 0 | F43: =SUM(F37:F42) -> 1538.6 | G43: =SUM(G37:G42) -> 17001014 | H43: =SUM(H37:H42) -> 15655429 | I43: =SUM(I37:I42) -> 9182444.6 | ... M43: =SUM(M37:M42) -> 6443724.6 | X43: =_xlfn.XLOOKUP(A43,'tabhg 1a bs 2026'!A:A,'tabhg 1a bs 2026'!B:B,,) -> 12567947
A44: A13000 - Prepaid Expenses (GV LLC) (New) | G44: ties to tab 4 | X44: =_xlfn.XLOOKUP(A44,'tabhg 1a bs 2026'!A:A,'tabhg 1a bs 2026'!B:B,,) -> 0
A45: A13001 - PrePaid Expenses (New) | B45: 0 | C45: 0 | D45: 0 | E45: 0 | F45: 0 | G45: 177485.31 | H45: 177485.31 | I45: 177485.31 | J45: 177485.31 | K45: 177485.31 | L45: 177485.31 | M45: 177485.31 | X45: =_xlfn.XLOOKUP(A45,'tabhg 1a bs 2026'!A:A,'tabhg 1a bs 2026'!B:B,,) -> 177485.31
A46: Total - A13000 - Prepaid Expenses (GV LLC) (New) | B46: =SUM(B45) -> 0 | C46: =SUM(C45) -> 0 | D46: =SUM(D45) -> 0 | E46: =SUM(E45) -> 0 | F46: =SUM(F45) -> 0 | G46: =SUM(G45) -> 177485.31 | H46: =SUM(H45) -> 177485.31 | I46: =SUM(I45) -> 177485.31 | ... M46: =SUM(M45) -> 177485.31 | X46: =_xlfn.XLOOKUP(A46,'tabhg 1a bs 2026'!A:A,'tabhg 1a bs 2026'!B:B,,) -> 177485.31
A47: Total Other Current Asset | B47: =SUM(B33:B35,B43,B46) -> 0 | C47: =SUM(C33:C35,C43,C46) -> 0 | D47: =SUM(D33:D35,D43,D46) -> 0 | E47: =SUM(E33:E35,E43,E46) -> 1740 | F47: =SUM(F33:F35,F43,F46) -> 3413.18 | G47: =SUM(G33:G35,G43,G46) -> 17266446 | H47: =SUM(H33:H35,H43,H46) -> 18883976 | I47: =SUM(I33:I35,I43,I46) -> 22907577 | ... M47: =SUM(M33:M35,M43,M46) -> 21301385 | X47: =_xlfn.XLOOKUP(A47,'tabhg 1a bs 2026'!A:A,'tabhg 1a bs 2026'!B:B,,) -> 29688992
A48: Total Current Assets | B48: =B23+B31+0+B47 -> 14257668 | C48: =C23+C31+0+C47 -> 14983100 | D48: =D23+D31+0+D47 -> 18068983 | E48: =E23+E31+0+E47 -> 20178180 | F48: =F23+F31+0+F47 -> 24125930 | G48: =G23+G31+0+G47 -> 22537054 | H48: =H23+H31+0+H47 -> 27919297 | I48: =I23+I31+0+I47 -> 39429359 | ... M48: =M23+M31+0+M47 -> 54283231 | X48: =_xlfn.XLOOKUP(A48,'tabhg 1a bs 2026'!A:A,'tabhg 1a bs 2026'!B:B,,) -> 58940879
A49: Fixed Assets
A50: 17000 - Fixed Asset
A51: 17320 - Leasehold Improvements | B51: 0 | C51: 0 | D51: 0 | E51: 0 | F51: 3227 | G51: 3227 | H51: 3227 | I51: 3227 | J51: 3227 | K51: 3227 | L51: 3227 | M51: 3227
A52: Total - 17000 - Fixed Asset | B52: =SUM(B51) -> 0 | C52: =SUM(C51) -> 0 | D52: =SUM(D51) -> 0 | E52: =SUM(E51) -> 0 | F52: =SUM(F51) -> 3227 | G52: =SUM(G51) -> 3227 | H52: =SUM(H51) -> 3227 | I52: =SUM(I51) -> 3227 | ... M52: =SUM(M51) -> 3227
A53: A16000 - Fixed Assets (GV LLC) (New)
A54: A16001 - Furniture & Fixture (New) | B54: 0 | C54: 0 | D54: 0 | E54: 0 | F54: 0 | G54: 41183.31 | H54: 41183.31 | I54: 41183.31 | J54: 41183.31 | K54: 41183.31 | L54: 41183.31 | M54: 41183.31
A55: A16002 - Computer & Electronics (New) | B55: 0 | C55: 0 | D55: 0 | E55: 0 | F55: 0 | G55: 449068.68 | H55: 453228.68 | I55: 453228.68 | J55: 453228.68 | K55: 453228.68 | L55: 453228.68 | M55: 453228.68
A56: A16003 - Machinery & Equipment (New) | B56: 0 | C56: 0 | D56: 0 | E56: 0 | F56: 0 | G56: 2120560.2 | H56: 2120560.2 | I56: 2120560.2 | J56: 2127630.8 | K56: 2127630.8 | L56: 2127630.8 | M56: 2127630.8
A57: A16004 - Automobile (New) | B57: 0 | C57: 0 | D57: 0 | E57: 0 | F57: 0 | G57: 437491.46 | H57: 437491.46 | I57: 437491.46 | J57: 496121.46 | K57: 496121.46 | L57: 496121.46 | M57: 496121.46
A58: A16005 - Leasehold Improvements (New) | B58: 0 | C58: 0 | D58: 0 | E58: 0 | F58: 0 | G58: 5633130.9 | H58: 5635482.9 | I58: 5635482.9 | J58: 5945372.4 | K58: 5945372.4 | L58: 5945372.4 | M58: 5945372.4
A59: A16006 - Construction In Process (New) | B59: 0 | C59: 0 | D59: 0 | E59: 0 | F59: 0 | G59: 4802 | H59: 4802 | I59: 4802 | J59: 4802 | K59: 4802 | L59: 4802 | M59: 4802
A60: Total - A16000 - Fixed Assets (GV LLC) (New) | B60: =SUM(B54:B59) -> 0 | C60: =SUM(C54:C59) -> 0 | D60: =SUM(D54:D59) -> 0 | E60: =SUM(E54:E59) -> 0 | F60: =SUM(F54:F59) -> 0 | G60: =SUM(G54:G59) -> 8686236.6 | H60: =SUM(H54:H59) -> 8692748.6 | I60: =SUM(I54:I59) -> 8692748.6 | ... M60: =SUM(M54:M59) -> 9068338.6
A61: A16021 - Accumulated Depreciation (New) | B61: 0 | C61: 0 | D61: 0 | E61: 0 | F61: 0 | G61: -2884036.8 | H61: -2884036.8 | I61: -2884036.8 | J61: -2884036.8 | K61: -2884036.8 | L61: -2884036.8 | M61: -2928443.8
A62: Total Fixed Assets | B62: =SUM(B52,B60:B61) -> 0 | C62: =SUM(C52,C60:C61) -> 0 | D62: =SUM(D52,D60:D61) -> 0 | E62: =SUM(E52,E60:E61) -> 0 | F62: =SUM(F52,F60:F61) -> 3227 | G62: =SUM(G52,G60:G61) -> 5805426.8 | H62: =SUM(H52,H60:H61) -> 5811938.8 | I62: =SUM(I52,I60:I61) -> 5811938.8 | ... M62: =SUM(M52,M60:M61) -> 6143121.8
A63: Other Assets
A64: A14000 - Investment in Subsidiaries (GV LLC) (New)
A65: A14001 - Investment in GV India (New) | B65: 0 | C65: 0 | D65: 0 | E65: 0 | F65: 0 | G65: 62000 | H65: 62000 | I65: 62000 | J65: 62000 | K65: 62000 | L65: 62000 | M65: 62000
A66: A14002 - Investment in GV Saudi (New) | B66: 0 | C66: 0 | D66: 0 | E66: 0 | F66: 0 | G66: 365000 | H66: 365000 | I66: 365000 | J66: 365000 | K66: 365000 | L66: 365000 | M66: 365000
A67: Total - A14000 - Investment in Subsidiaries (GV LLC) (New) | B67: =SUM(B65:B66) -> 0 | C67: =SUM(C65:C66) -> 0 | D67: =SUM(D65:D66) -> 0 | E67: =SUM(E65:E66) -> 0 | F67: =SUM(F65:F66) -> 0 | G67: =SUM(G65:G66) -> 427000 | H67: =SUM(H65:H66) -> 427000 | I67: =SUM(I65:I66) -> 427000 | ... M67: =SUM(M65:M66) -> 427000
A68: A15000 - Intercompany (GV LLC) (New)
A69: A15001 - Intercompany GV Realty (New) | B69: 0 | C69: 0 | D69: 0 | E69: 0 | F69: 0 | G69: 2151414.9 | H69: 2151414.9 | I69: 2151414.9 | J69: 2136414.9 | K69: 2236414.9 | L69: 2236414.9 | M69: 2236414.9
A70: A15002 - Intercompany GV Realty2 (New) | B70: 0 | C70: 0 | D70: 0 | E70: 0 | F70: 0 | G70: -821160.07 | H70: -821160.07 | I70: -821160.07 | J70: -821160.07 | K70: -421160.07 | L70: -221160.07 | M70: -221160.07
A71: A15003 - Intercompany - GV Facades (New) | B71: 0 | C71: 0 | D71: 0 | E71: 0 | F71: 0 | G71: -616602.83 | H71: 205971.12 | I71: 183278.8 | J71: 1753278.9 | K71: 1978662.3 | L71: 2039837.1 | M71: 2120112.6
A72: A15004 - Intercompany GV Canada (New) | B72: 0 | C72: 0 | D72: 0 | E72: 0 | F72: 0 | G72: 213729.44 | H72: 213729.44 | I72: 213729.44 | J72: 228729.44 | K72: 240729.44 | L72: 229293.76 | M72: 362204.25
A73: A15005 - Intercompany GV Saudi (New) | B73: 0 | C73: 0 | D73: 0 | E73: 0 | F73: 0 | G73: 0 | H73: 0 | I73: 0 | J73: 60000 | K73: 60000 | L73: 115000 | M73: 215000
A74: A15006 - Intercompany GV INDIA - 33800 (New) | B74: 0 | C74: 0 | D74: 0 | E74: 0 | F74: 0 | G74: 176239.94 | H74: 537922.94 | I74: 577922.94 | J74: 687922.94 | K74: 837922.94 | L74: 837922.94 | M74: 837922.94
A75: Total - A15000 - Intercompany (GV LLC) (New) | B75: =SUM(B69:B74) -> 0 | C75: =SUM(C69:C74) -> 0 | D75: =SUM(D69:D74) -> 0 | E75: =SUM(E69:E74) -> 0 | F75: =SUM(F69:F74) -> 0 | G75: =SUM(G69:G74) -> 1103621.4 | H75: =SUM(H69:H74) -> 2287878.4 | I75: =SUM(I69:I74) -> 2305186 | ... M75: =SUM(M69:M74) -> 5550494.6
A76: Total Other Assets | B76: =SUM(B67,B75) -> 0 | C76: =SUM(C67,C75) -> 0 | D76: =SUM(D67,D75) -> 0 | E76: =SUM(E67,E75) -> 0 | F76: =SUM(F67,F75) -> 0 | G76: =SUM(G67,G75) -> 1530621.4 | H76: =SUM(H67,H75) -> 2714878.4 | I76: =SUM(I67,I75) -> 2732186 | ... M76: =SUM(M67,M75) -> 5977494.6
A77: Total ASSETS | B77: =B48+B62+B76 -> 14257668 | C77: =C48+C62+C76 -> 14983100 | D77: =D48+D62+D76 -> 18068983 | E77: =E48+E62+E76 -> 20178180 | F77: =F48+F62+F76 -> 24129157 | G77: =G48+G62+G76 -> 29873102 | H77: =H48+H62+H76 -> 36446114 | I77: =I48+I62+I76 -> 47973483 | ... M77: =M48+M62+M76 -> 66403847
A78: Liabilities & Equity
A79: Current Liabilities
A80: Accounts Payable
A81: 20000 - Accounts Payable | B81: 39032.63 | C81: 100785.7 | D81: 275774.11 | E81: 753382.12 | F81: 1440427.7 | G81: 2341329.9 | H81: 5072422.6 | I81: 8597413.7 | J81: 8702490.3 | K81: 8272375.8 | L81: 10678368 | M81: 11781930
A82: A20000 - Accounts Payable (GV LLC) (New)
A83: A20001 - Accounts Payable Suppliers & Vendors (New) | B83: 2709775.9 | C83: 2966442.2 | D83: 3034629.2 | E83: 3407331.3 | F83: 2638686.8 | G83: 858663.1 | H83: 1408029.9 | I83: 1762222.6 | J83: 1771636.9 | K83: 1784580.1 | L83: 2001406.1 | M83: 2030696.6
A84: A20002 - Accounts Payable Vendors (New) | B84: 0 | C84: 0 | D84: 0 | E84: 0 | F84: 0 | G84: 1579078.4 | H84: 1579078.4 | I84: 1584969.3 | J84: 1584969.3 | K84: 1597733.8 | L84: 1608681.8 | M84: 1584789.3
A85: Total - A20000 - Accounts Payable (GV LLC) (New) | B85: =SUM(B83:B84) -> 2709775.9 | C85: =SUM(C83:C84) -> 2966442.2 | D85: =SUM(D83:D84) -> 3034629.2 | E85: =SUM(E83:E84) -> 3407331.3 | F85: =SUM(F83:F84) -> 2638686.8 | G85: =SUM(G83:G84) -> 2437741.5 | H85: =SUM(H83:H84) -> 2987108.3 | I85: =SUM(I83:I84) -> 3347191.9 | ... M85: =SUM(M83:M84) -> 3615485.9
A86: A20003 - Prepayment to Suppliers (New) | B86: 0 | C86: 0 | D86: 0 | E86: 0 | F86: 0 | G86: -38542.08 | H86: -38542.08 | I86: -38542.08 | J86: -38542.08 | K86: -38542.08 | L86: -38542.08 | M86: -38542.08
A87: N20000 - Accounts Payable (GV LLC)
A88: N20100 - Accounts Payable (GV USA)
A89: N20102 - Accounts Payable Vendors | B89: 0 | C89: 0 | D89: 0 | E89: 0 | F89: 0 | G89: 0 | H89: 0 | I89: 0 | J89: 0 | K89: 0 | L89: -743.23 | M89: -743.23
A90: Total - N20100 - Accounts Payable (GV USA) | B90: =SUM(B89) -> 0 | C90: =SUM(C89) -> 0 | D90: =SUM(D89) -> 0 | E90: =SUM(E89) -> 0 | F90: =SUM(F89) -> 0 | G90: =SUM(G89) -> 0 | H90: =SUM(H89) -> 0 | I90: =SUM(I89) -> 0 | ... M90: =SUM(M89) -> -743.23
A91: Total - N20000 - Accounts Payable (GV LLC) | B91: =SUM(B90) -> 0 | C91: =SUM(C90) -> 0 | D91: =SUM(D90) -> 0 | E91: =SUM(E90) -> 0 | F91: =SUM(F90) -> 0 | G91: =SUM(G90) -> 0 | H91: =SUM(H90) -> 0 | I91: =SUM(I90) -> 0 | ... M91: =SUM(M90) -> -743.23
A92: Total Accounts Payable | B92: =SUM(B81,B85:B86,B91) -> 2748808.5 | C92: =SUM(C81,C85:C86,C91) -> 3067227.9 | D92: =SUM(D81,D85:D86,D91) -> 3310403.4 | E92: =SUM(E81,E85:E86,E91) -> 4160713.4 | F92: =SUM(F81,F85:F86,F91) -> 4079114.5 | G92: =SUM(G81,G85:G86,G91) -> 4740529.3 | H92: =SUM(H81,H85:H86,H91) -> 8020988.8 | I92: =SUM(I81,I85:I86,I91) -> 11906064 | ... M92: =SUM(M81,M85:M86,M91) -> 15358130
A93: Credit Card
A94: 21030 - Truist Visa Corp Card | B94: 0 | C94: 0 | D94: 0 | E94: 0 | F94: 0 | G94: 0 | H94: 65694.7 | I94: 140922.1 | J94: 173107.46 | K94: 173107.46 | L94: 173107.46 | M94: 173107.46
A95: 21040 - Truist Visa Purchase Card | B95: 0 | C95: 0 | D95: 0 | E95: 0 | F95: 0 | G95: 54062.21 | H95: 756942.85 | I95: 1282401.3 | J95: 1897998 | K95: 2394311.4 | L95: 2823041.6 | M95: 3821611.6
A96: A23900 - Credit cards
A97: A23901 - Truist Visa -Facades -card - Visa (New) | B97: 0 | C97: 0 | D97: 0 | E97: 0 | F97: 0 | G97: 2344942.1 | H97: -1364.87 | I97: -1364.87 | J97: -1364.87 | K97: -1364.87 | L97: -1364.87 | M97: -1364.87
A98: A23902 - American Express - 31013 (New) | B98: 0 | C98: 0 | D98: 0 | E98: 0 | F98: 0 | G98: -74865.99 | H98: -162023.4 | I98: -172538.17 | J98: -179667.16 | K98: -233330.58 | L98: -394158.03 | M98: -436179.28
A99: A23903 - Truist -Visa - 6325- CORP(New) | B99: 0 | C99: 0 | D99: 0 | E99: 0 | F99: 0 | G99: 1175253.5 | H99: 606817.06 | I99: 558211.73 | J99: 513760.95 | K99: 175332.44 | L99: 175332.44 | M99: 29816.93
A100: A23904 - Truist -Visa - 4576 -PURCHASE (New) | B100: 0 | C100: 0 | D100: 0 | E100: 0 | F100: 0 | G100: 0 | H100: 0 | I100: -516108.72 | J100: -843828.24 | K100: -1550949.2 | L100: -2064941.8 | M100: -3067469.2
A101: Total - A23900 - Credit cards | B101: =SUM(B97:B100) -> 0 | C101: =SUM(C97:C100) -> 0 | D101: =SUM(D97:D100) -> 0 | E101: =SUM(E97:E100) -> 0 | F101: =SUM(F97:F100) -> 0 | G101: =SUM(G97:G100) -> 3445329.6 | H101: =SUM(H97:H100) -> 443428.79 | I101: =SUM(I97:I100) -> -131800.03 | ... M101: =SUM(M97:M100) -> -3475196.4
...

Sheet tabhg 1a bs 2026
A1: Graniti Vicentia, L.L.C.
A2: Parent Company : Graniti Vicentia LLC
A3: Graniti Comparative Balance Sheet
A4: End of Jan 2026
A6: Options: Activity Only
A7: Financial Row | B7: Amount
B8: As of Jan 2026 | C8: As of Feb 2026 | D8: As of Mar 2026 | E8: As of Apr 2026 | F8: As of May 2026 | G8: As of Jun 2026 | H8: As of Jul 2026 | I8: As of Aug 2026 | J8: As of Sep 2026 | K8: As of Oct 2026 | L8: As of Nov 2026 | M8: As of Dec 2026
A10: ASSETS
A11: Current Assets
A12: Bank
A13: 10110 - GV Truist Bank - 4637 | B13: -62150.43 | C13: -62150.43 | D13: -62150.43 | E13: -62150.43 | F13: -62150.43 | G13: -62150.43 | H13: -62150.43 | I13: -62150.43 | J13: -62150.43 | K13: -62150.43 | L13: -62150.43 | M13: -62150.43
A14: 21050 - Amex GVLLC | B14: -325692.32 | C14: -360918.7 | D14: -360918.7 | E14: -360918.7 | F14: -360918.7 | G14: -360918.7 | H14: -360918.7 | I14: -360918.7 | J14: -360918.7 | K14: -360918.7 | L14: -360918.7 | M14: -360918.7
A15: A10000 - Cash (GV LLC) (New)
A16: A10001 - Petty Cash On Hand (New) | B16: -6415602.5 | C16: -6415602.5 | D16: -6415602.5 | E16: -6415602.5 | F16: -6415602.5 | G16: -6415602.5 | H16: -6415602.5 | I16: -6415602.5 | J16: -6415602.5 | K16: -6415602.5 | L16: -6415602.5 | M16: -6415602.5
A17: A10002 - Allegiance Bank Texas-2243 (New) | B17: 1029.52 | C17: 1029.52 | D17: 1029.52 | E17: 1029.52 | F17: 1029.52 | G17: 1029.52 | H17: 1029.52 | I17: 1029.52 | J17: 1029.52 | K17: 1029.52 | L17: 1029.52 | M17: 1029.52
A18: A10003 - Truist Bank - 4637 (New) | B18: 3696129.7 | C18: 3561617.5 | D18: 2965801.7 | E18: 2965801.7 | F18: 2965801.7 | G18: 2965801.7 | H18: 2965801.7 | I18: 2965801.7 | J18: 2965801.7 | K18: 2965801.7 | L18: 2965801.7 | M18: 2965801.7
A19: A10004 - Truist - Savings - 4645 (New) | B19: 1176.62 | C19: 1176.62 | D19: 1176.62 | E19: 1176.62 | F19: 1176.62 | G19: 1176.62 | H19: 1176.62 | I19: 1176.62 | J19: 1176.62 | K19: 1176.62 | L19: 1176.62 | M19: 1176.62
A20: A10005 - CC - Clearing Account (New) | B20: -4091.4 | C20: -4091.4 | D20: -4091.4 | E20: -4091.4 | F20: -4091.4 | G20: -4091.4 | H20: -4091.4 | I20: -4091.4 | J20: -4091.4 | K20: -4091.4 | L20: -4091.4 | M20: -4091.4
A21: A10006 - Undeposited Funds (New) | B21: 277725.74 | C21: 277725.74 | D21: 277725.74 | E21: 277725.74 | F21: 277725.74 | G21: 277725.74 | H21: 277725.74 | I21: 277725.74 | J21: 277725.74 | K21: 277725.74 | L21: 277725.74 | M21: 277725.74
A22: Total - A10000 - Cash (GV LLC) (New) | B22: =SUM(B16:B21) -> -2443632.3 | C22: =SUM(C16:C21) -> -2578144.5 | D22: =SUM(D16:D21) -> -3173960.3 | E22: =SUM(E16:E21) -> -3173960.3 | F22: =SUM(F16:F21) -> -3173960.3 | G22: =SUM(G16:G21) -> -3173960.3 | H22: =SUM(H16:H21) -> -3173960.3 | I22: =SUM(I16:I21) -> -3173960.3 | ... M22: =SUM(M16:M21) -> -3173960.3
A23: Total Bank | B23: =SUM(B13:B14,B22) -> -2831475 | C23: =SUM(C13:C14,C22) -> -3001213.6 | D23: =SUM(D13:D14,D22) -> -3597029.4 | E23: =SUM(E13:E14,E22) -> -3597029.4 | F23: =SUM(F13:F14,F22) -> -3597029.4 | G23: =SUM(G13:G14,G22) -> -3597029.4 | H23: =SUM(H13:H14,H22) -> -3597029.4 | I23: =SUM(I13:I14,I22) -> -3597029.4 | ... M23: =SUM(M13:M14,M22) -> -3597029.4
A24: Accounts Receivable
A25: 11000 - Accounts Receivable | B25: 993053.75 | C25: 952000.45 | D25: 952000.45 | E25: 952000.45 | F25: 952000.45 | G25: 952000.45 | H25: 952000.45 | I25: 952000.45 | J25: 952000.45 | K25: 952000.45 | L25: 952000.45 | M25: 952000.45
A26: A11000 - Accounts Receivable (GV LLC) (New)
A27: A11001 - Accounts Receivable (New) | B27: 31840880 | C27: 29681629 | D27: 26763851 | E27: 26763851 | F27: 26763851 | G27: 26763851 | H27: 26763851 | I27: 26763851 | J27: 26763851 | K27: 26763851 | L27: 26763851 | M27: 26763851
A28: A11002 - Accrued Accounts Receivable (New) | B28: 15430 | C28: 15430 | D28: 15430 | E28: 15430 | F28: 15430 | G28: 15430 | H28: 15430 | I28: 15430 | J28: 15430 | K28: 15430 | L28: 15430 | M28: 15430
A29: A11003 - Allowance for Doubtful Accounts (New) | B29: -766001.85 | C29: -766001.85 | D29: -766001.85 | E29: -766001.85 | F29: -766001.85 | G29: -766001.85 | H29: -766001.85 | I29: -766001.85 | J29: -766001.85 | K29: -766001.85 | L29: -766001.85 | M29: -766001.85
A30: Total - A11000 - Accounts Receivable (GV LLC) (New) | B30: =SUM(B27:B29) -> 31090308 | C30: =SUM(C27:C29) -> 28931058 | D30: =SUM(D27:D29) -> 26013279 | E30: =SUM(E27:E29) -> 26013279 | F30: =SUM(F27:F29) -> 26013279 | G30: =SUM(G27:G29) -> 26013279 | H30: =SUM(H27:H29) -> 26013279 | I30: =SUM(I27:I29) -> 26013279 | ... M30: =SUM(M27:M29) -> 26013279
A31: Total Accounts Receivable | B31: =SUM(B25,B30) -> 32083362 | C31: =SUM(C25,C30) -> 29883058 | D31: =SUM(D25,D30) -> 26965280 | E31: =SUM(E25,E30) -> 26965280 | F31: =SUM(F25,F30) -> 26965280 | G31: =SUM(G25,G30) -> 26965280 | H31: =SUM(H25,H30) -> 26965280 | I31: =SUM(I25,I30) -> 26965280 | ... M31: =SUM(M25,M30) -> 26965280
A32: Other Current Asset
A33: 10200 - Undeposited Funds | B33: 817418.46 | C33: 817418.46 | D33: 833224.26 | E33: 833224.26 | F33: 833224.26 | G33: 833224.26 | H33: 833224.26 | I33: 833224.26 | J33: 833224.26 | K33: 833224.26 | L33: 833224.26 | M33: 833224.26
A34: 12000 - Inventory | B34: 2078728.2 | C34: 2085538.6 | D34: 2085557.8 | E34: 2085557.8 | F34: 2085557.8 | G34: 2085557.8 | H34: 2085557.8 | I34: 2085557.8 | J34: 2085557.8 | K34: 2085557.8 | L34: 2085557.8 | M34: 2085557.8
A35: 13000 - Prepaid Expenses | B35: 14215715 | C35: 12755063 | D35: 10050416 | E35: 10050416 | F35: 10050416 | G35: 10050416 | H35: 10050416 | I35: 10050416 | J35: 10050416 | K35: 10050416 | L35: 10050416 | M35: 10050416
A36: 15000 - Intercompany Receivable | B36: -168301.82 | C36: -168301.82 | D36: -168301.82 | E36: -168301.82 | F36: -168301.82 | G36: -168301.82 | H36: -168301.82 | I36: -168301.82 | J36: -168301.82 | K36: -168301.82 | L36: -168301.82 | M36: -168301.82
A37: A12000 - Inventory (GV LLC) (New)
A38: A12001 - Inventory (New) | B38: 10513242 | C38: 11225865 | D38: 11904841 | E38: 11904841 | F38: 11904841 | G38: 11904841 | H38: 11904841 | I38: 11904841 | J38: 11904841 | K38: 11904841 | L38: 11904841 | M38: 11904841
A39: A12002 - Inventory - In Transit (New) | B39: 2135520.9 | C39: 2135520.9 | D39: 2135520.9 | E39: 2135520.9 | F39: 2135520.9 | G39: 2135520.9 | H39: 2135520.9 | I39: 2135520.9 | J39: 2135520.9 | K39: 2135520.9 | L39: 2135520.9 | M39: 2135520.9
A40: A12003 - Obsolete Inventory (New) | B40: 899003.97 | C40: 899003.97 | D40: 899003.97 | E40: 899003.97 | F40: 899003.97 | G40: 899003.97 | H40: 899003.97 | I40: 899003.97 | J40: 899003.97 | K40: 899003.97 | L40: 899003.97 | M40: 899003.97
A41: A12004 - Hotels Projects/ Tub Surrounds For Obsolete Inventory (New) | B41: 1456.86 | C41: 1456.86 | D41: 1456.86 | E41: 1456.86 | F41: 1456.86 | G41: 1456.86 | H41: 1456.86 | I41: 1456.86 | J41: 1456.86 | K41: 1456.86 | L41: 1456.86 | M41: 1456.86
A42: A12005 - Inventory Adjustments (New) | B42: 18722.87 | C42: 18722.87 | D42: 18722.87 | E42: 18722.87 | F42: 18722.87 | G42: 18722.87 | H42: 18722.87 | I42: 18722.87 | J42: 18722.87 | K42: 18722.87 | L42: 18722.87 | M42: 18722.87
A43: A12006 - Inventory Allowances (New) | B43: -1000000 | C43: -1000000 | D43: -1000000 | E43: -1000000 | F43: -1000000 | G43: -1000000 | H43: -1000000 | I43: -1000000 | J43: -1000000 | K43: -1000000 | L43: -1000000 | M43: -1000000
A44: Total - A12000 - Inventory (GV LLC) (New) | B44: =SUM(B38:B43) -> 12567947 | C44: =SUM(C38:C43) -> 13280569 | D44: =SUM(D38:D43) -> 13959546 | E44: =SUM(E38:E43) -> 13959546 | F44: =SUM(F38:F43) -> 13959546 | G44: =SUM(G38:G43) -> 13959546 | H44: =SUM(H38:H43) -> 13959546 | I44: =SUM(I38:I43) -> 13959546 | ... M44: =SUM(M38:M43) -> 13959546
A45: A13000 - Prepaid Expenses (GV LLC) (New)
A46: A13001 - PrePaid Expenses (New) | B46: 177485.31 | C46: 177485.31 | D46: 177485.31 | E46: 177485.31 | F46: 177485.31 | G46: 177485.31 | H46: 177485.31 | I46: 177485.31 | J46: 177485.31 | K46: 177485.31 | L46: 177485.31 | M46: 177485.31
A47: Total - A13000 - Prepaid Expenses (GV LLC) (New) | B47: =SUM(B46) -> 177485.31 | C47: =SUM(C46) -> 177485.31 | D47: =SUM(D46) -> 177485.31 | E47: =SUM(E46) -> 177485.31 | F47: =SUM(F46) -> 177485.31 | G47: =SUM(G46) -> 177485.31 | H47: =SUM(H46) -> 177485.31 | I47: =SUM(I46) -> 177485.31 | ... M47: =SUM(M46) -> 177485.31
A48: Total Other Current Asset | B48: =SUM(B33:B36,B44,B47) -> 29688992 | C48: =SUM(C33:C36,C44,C47) -> 28947772 | D48: =SUM(D33:D36,D44,D47) -> 26937928 | E48: =SUM(E33:E36,E44,E47) -> 26937928 | F48: =SUM(F33:F36,F44,F47) -> 26937928 | G48: =SUM(G33:G36,G44,G47) -> 26937928 | H48: =SUM(H33:H36,H44,H47) -> 26937928 | I48: =SUM(I33:I36,I44,I47) -> 26937928 | ... M48: =SUM(M33:M36,M44,M47) -> 26937928
A49: Total Current Assets | B49: =B23+B31+0+B48 -> 58940879 | C49: =C23+C31+0+C48 -> 55829617 | D49: =D23+D31+0+D48 -> 50306178 | E49: =E23+E31+0+E48 -> 50306178 | F49: =F23+F31+0+F48 -> 50306178 | G49: =G23+G31+0+G48 -> 50306178 | H49: =H23+H31+0+H48 -> 50306178 | I49: =I23+I31+0+I48 -> 50306178 | ... M49: =M23+M31+0+M48 -> 50306178
A50: Fixed Assets
A51: 17000 - Fixed Asset
A52: 17320 - Leasehold Improvements | B52: 3227 | C52: 3227 | D52: 3227 | E52: 3227 | F52: 3227 | G52: 3227 | H52: 3227 | I52: 3227 | J52: 3227 | K52: 3227 | L52: 3227 | M52: 3227
A53: Total - 17000 - Fixed Asset | B53: =SUM(B52) -> 3227 | C53: =SUM(C52) -> 3227 | D53: =SUM(D52) -> 3227 | E53: =SUM(E52) -> 3227 | F53: =SUM(F52) -> 3227 | G53: =SUM(G52) -> 3227 | H53: =SUM(H52) -> 3227 | I53: =SUM(I52) -> 3227 | ... M53: =SUM(M52) -> 3227
A54: A16000 - Fixed Assets (GV LLC) (New)
A55: A16001 - Furniture & Fixture (New) | B55: 41183.31 | C55: 41183.31 | D55: 41183.31 | E55: 41183.31 | F55: 41183.31 | G55: 41183.31 | H55: 41183.31 | I55: 41183.31 | J55: 41183.31 | K55: 41183.31 | L55: 41183.31 | M55: 41183.31
A56: A16002 - Computer & Electronics (New) | B56: 453228.68 | C56: 453228.68 | D56: 453228.68 | E56: 453228.68 | F56: 453228.68 | G56: 453228.68 | H56: 453228.68 | I56: 453228.68 | J56: 453228.68 | K56: 453228.68 | L56: 453228.68 | M56: 453228.68
A57: A16003 - Machinery & Equipment (New) | B57: 2127630.8 | C57: 2127630.8 | D57: 2127630.8 | E57: 2127630.8 | F57: 2127630.8 | G57: 2127630.8 | H57: 2127630.8 | I57: 2127630.8 | J57: 2127630.8 | K57: 2127630.8 | L57: 2127630.8 | M57: 2127630.8
A58: A16004 - Automobile (New) | B58: 496121.46 | C58: 496121.46 | D58: 496121.46 | E58: 496121.46 | F58: 496121.46 | G58: 496121.46 | H58: 496121.46 | I58: 496121.46 | J58: 496121.46 | K58: 496121.46 | L58: 496121.46 | M58: 496121.46
A59: A16005 - Leasehold Improvements (New) | B59: 5953872.4 | C59: 5994382.2 | D59: 6025382.2 | E59: 6025382.2 | F59: 6025382.2 | G59: 6025382.2 | H59: 6025382.2 | I59: 6025382.2 | J59: 6025382.2 | K59: 6025382.2 | L59: 6025382.2 | M59: 6025382.2
A60: A16006 - Construction In Process (New) | B60: 4802 | C60: 4802 | D60: 4802 | E60: 4802 | F60: 4802 | G60: 4802 | H60: 4802 | I60: 4802 | J60: 4802 | K60: 4802 | L60: 4802 | M60: 4802
A61: Total - A16000 - Fixed Assets (GV LLC) (New) | B61: =SUM(B55:B60) -> 9076838.6 | C61: =SUM(C55:C60) -> 9117348.4 | D61: =SUM(D55:D60) -> 9148348.4 | E61: =SUM(E55:E60) -> 9148348.4 | F61: =SUM(F55:F60) -> 9148348.4 | G61: =SUM(G55:G60) -> 9148348.4 | H61: =SUM(H55:H60) -> 9148348.4 | I61: =SUM(I55:I60) -> 9148348.4 | ... M61: =SUM(M55:M60) -> 9148348.4
A62: A16021 - Accumulated Depreciation (New) | B62: -2928443.8 | C62: -2928443.8 | D62: -2928443.8 | E62: -2928443.8 | F62: -2928443.8 | G62: -2928443.8 | H62: -2928443.8 | I62: -2928443.8 | J62: -2928443.8 | K62: -2928443.8 | L62: -2928443.8 | M62: -2928443.8
A63: Total Fixed Assets | B63: =SUM(B53,B61:B62) -> 6151621.8 | C63: =SUM(C53,C61:C62) -> 6192131.6 | D63: =SUM(D53,D61:D62) -> 6223131.6 | E63: =SUM(E53,E61:E62) -> 6223131.6 | F63: =SUM(F53,F61:F62) -> 6223131.6 | G63: =SUM(G53,G61:G62) -> 6223131.6 | H63: =SUM(H53,H61:H62) -> 6223131.6 | I63: =SUM(I53,I61:I62) -> 6223131.6 | ... M63: =SUM(M53,M61:M62) -> 6223131.6
A64: Other Assets
A65: A14000 - Investment in Subsidiaries (GV LLC) (New)
A66: A14001 - Investment in GV India (New) | B66: 62000 | C66: 62000 | D66: 62000 | E66: 62000 | F66: 62000 | G66: 62000 | H66: 62000 | I66: 62000 | J66: 62000 | K66: 62000 | L66: 62000 | M66: 62000
A67: A14002 - Investment in GV Saudi (New) | B67: 365000 | C67: 365000 | D67: 365000 | E67: 365000 | F67: 365000 | G67: 365000 | H67: 365000 | I67: 365000 | J67: 365000 | K67: 365000 | L67: 365000 | M67: 365000
A68: Total - A14000 - Investment in Subsidiaries (GV LLC) (New) | B68: =SUM(B66:B67) -> 427000 | C68: =SUM(C66:C67) -> 427000 | D68: =SUM(D66:D67) -> 427000 | E68: =SUM(E66:E67) -> 427000 | F68: =SUM(F66:F67) -> 427000 | G68: =SUM(G66:G67) -> 427000 | H68: =SUM(H66:H67) -> 427000 | I68: =SUM(I66:I67) -> 427000 | ... M68: =SUM(M66:M67) -> 427000
A69: A15000 - Intercompany (GV LLC) (New)
A70: A15001 - Intercompany GV Realty (New) | B70: 2236414.9 | C70: 2236414.9 | D70: 2236414.9 | E70: 2236414.9 | F70: 2236414.9 | G70: 2236414.9 | H70: 2236414.9 | I70: 2236414.9 | J70: 2236414.9 | K70: 2236414.9 | L70: 2236414.9 | M70: 2236414.9
A71: A15002 - Intercompany GV Realty2 (New) | B71: -221160.07 | C71: -221160.07 | D71: -221160.07 | E71: -221160.07 | F71: -221160.07 | G71: -221160.07 | H71: -221160.07 | I71: -221160.07 | J71: -221160.07 | K71: -221160.07 | L71: -221160.07 | M71: -221160.07
A72: A15003 - Intercompany - GV Facades (New) | B72: 2120112.6 | C72: 2120112.6 | D72: 2120112.6 | E72: 2120112.6 | F72: 2120112.6 | G72: 2120112.6 | H72: 2120112.6 | I72: 2120112.6 | J72: 2120112.6 | K72: 2120112.6 | L72: 2120112.6 | M72: 2120112.6
A73: A15004 - Intercompany GV Canada (New) | B73: 362204.25 | C73: 362204.25 | D73: 362204.25 | E73: 362204.25 | F73: 362204.25 | G73: 362204.25 | H73: 362204.25 | I73: 362204.25 | J73: 362204.25 | K73: 362204.25 | L73: 362204.25 | M73: 362204.25
A74: A15005 - Intercompany GV Saudi (New) | B74: 215000 | C74: 215000 | D74: 215000 | E74: 215000 | F74: 215000 | G74: 215000 | H74: 215000 | I74: 215000 | J74: 215000 | K74: 215000 | L74: 215000 | M74: 215000
A75: A15006 - Intercompany GV INDIA - 33800 (New) | B75: 837922.94 | C75: 863131.73 | D75: 863131.73 | E75: 863131.73 | F75: 863131.73 | G75: 863131.73 | H75: 863131.73 | I75: 863131.73 | J75: 863131.73 | K75: 863131.73 | L75: 863131.73 | M75: 863131.73
A76: Total - A15000 - Intercompany (GV LLC) (New) | B76: =SUM(B70:B75) -> 5550494.6 | C76: =SUM(C70:C75) -> 5575703.4 | D76: =SUM(D70:D75) -> 5575703.4 | E76: =SUM(E70:E75) -> 5575703.4 | F76: =SUM(F70:F75) -> 5575703.4 | G76: =SUM(G70:G75) -> 5575703.4 | H76: =SUM(H70:H75) -> 5575703.4 | I76: =SUM(I70:I75) -> 5575703.4 | ... M76: =SUM(M70:M75) -> 5575703.4
A77: Total Other Assets | B77: =SUM(B68,B76) -> 5977494.6 | C77: =SUM(C68,C76) -> 6002703.4 | D77: =SUM(D68,D76) -> 6002703.4 | E77: =SUM(E68,E76) -> 6002703.4 | F77: =SUM(F68,F76) -> 6002703.4 | G77: =SUM(G68,G76) -> 6002703.4 | H77: =SUM(H68,H76) -> 6002703.4 | I77: =SUM(I68,I76) -> 6002703.4 | ... M77: =SUM(M68,M76) -> 6002703.4
A78: Total ASSETS | B78: =B49+B63+B77 -> 71069995 | C78: =C49+C63+C77 -> 68024452 | D78: =D49+D63+D77 -> 62532013 | E78: =E49+E63+E77 -> 62532013 | F78: =F49+F63+F77 -> 62532013 | G78: =G49+G63+G77 -> 62532013 | H78: =H49+H63+H77 -> 62532013 | I78: =I49+I63+I77 -> 62532013 | ... M78: =M49+M63+M77 -> 62532013
A79: Liabilities & Equity
A80: Current Liabilities
A81: Accounts Payable
A82: 20000 - Accounts Payable | B82: 12151983 | C82: 10690092 | D82: 9688926.4 | E82: 9692270.9 | F82: 9692270.9 | G82: 9692270.9 | H82: 9708392.1 | I82: 9708392.1 | J82: 9708392.1 | K82: 9708392.1 | L82: 9708392.1 | M82: 9708392.1
A83: A20000 - Accounts Payable (GV LLC) (New)
A84: A20001 - Accounts Payable Suppliers & Vendors (New) | B84: 2294398.9 | C84: 2575638.9 | D84: -493825.53 | E84: -493825.53 | F84: -493825.53 | G84: -493825.53 | H84: -493825.53 | I84: -493825.53 | J84: -493825.53 | K84: -493825.53 | L84: -493825.53 | M84: -493825.53
A85: A20002 - Accounts Payable Vendors (New) | B85: 1584789.3 | C85: 1584789.3 | D85: 1584789.3 | E85: 1584789.3 | F85: 1584789.3 | G85: 1584789.3 | H85: 1584789.3 | I85: 1584789.3 | J85: 1584789.3 | K85: 1584789.3 | L85: 1584789.3 | M85: 1584789.3
A86: Total - A20000 - Accounts Payable (GV LLC) (New) | B86: =SUM(B84:B85) -> 3879188.2 | C86: =SUM(C84:C85) -> 4160428.3 | D86: =SUM(D84:D85) -> 1090963.8 | E86: =SUM(E84:E85) -> 1090963.8 | F86: =SUM(F84:F85) -> 1090963.8 | G86: =SUM(G84:G85) -> 1090963.8 | H86: =SUM(H84:H85) -> 1090963.8 | I86: =SUM(I84:I85) -> 1090963.8 | ... M86: =SUM(M84:M85) -> 1090963.8
A87: A20003 - Prepayment to Suppliers (New) | B87: -38542.08 | C87: -38542.08 | D87: -38542.08 | E87: -38542.08 | F87: -38542.08 | G87: -38542.08 | H87: -38542.08 | I87: -38542.08 | J87: -38542.08 | K87: -38542.08 | L87: -38542.08 | M87: -38542.08
A88: N20000 - Accounts Payable (GV LLC)
A89: N20100 - Accounts Payable (GV USA)
A90: N20101 - Accounts Payable Suppliers | B90: 0 | C90: 193491.26 | D90: -307862.18 | E90: -307862.18 | F90: -307862.18 | G90: -307862.18 | H90: -307862.18 | I90: -307862.18 | J90: -307862.18 | K90: -307862.18 | L90: -307862.18 | M90: -307862.18
A91: N20102 - Accounts Payable Vendors | B91: -743.23 | C91: -743.23 | D91: -743.23 | E91: -743.23 | F91: -743.23 | G91: -743.23 | H91: -743.23 | I91: -743.23 | J91: -743.23 | K91: -743.23 | L91: -743.23 | M91: -743.23
A92: Total - N20100 - Accounts Payable (GV USA) | B92: =SUM(B90:B91) -> -743.23 | C92: =SUM(C90:C91) -> 192748.03 | D92: =SUM(D90:D91) -> -308605.41 | E92: =SUM(E90:E91) -> -308605.41 | F92: =SUM(F90:F91) -> -308605.41 | G92: =SUM(G90:G91) -> -308605.41 | H92: =SUM(H90:H91) -> -308605.41 | I92: =SUM(I90:I91) -> -308605.41 | ... M92: =SUM(M90:M91) -> -308605.41
A93: Total - N20000 - Accounts Payable (GV LLC) | B93: =SUM(B92) -> -743.23 | C93: =SUM(C92) -> 192748.03 | D93: =SUM(D92) -> -308605.41 | E93: =SUM(E92) -> -308605.41 | F93: =SUM(F92) -> -308605.41 | G93: =SUM(G92) -> -308605.41 | H93: =SUM(H92) -> -308605.41 | I93: =SUM(I92) -> -308605.41 | ... M93: =SUM(M92) -> -308605.41
A94: Total Accounts Payable | B94: =SUM(B82,B86:B87,B93) -> 15991886 | C94: =SUM(C82,C86:C87,C93) -> 15004727 | D94: =SUM(D82,D86:D87,D93) -> 10432743 | E94: =SUM(E82,E86:E87,E93) -> 10436087 | F94: =SUM(F82,F86:F87,F93) -> 10436087 | G94: =SUM(G82,G86:G87,G93) -> 10436087 | H94: =SUM(H82,H86:H87,H93) -> 10452208 | I94: =SUM(I82,I86:I87,I93) -> 10452208 | ... M94: =SUM(M82,M86:M87,M93) -> 10452208
A95: Credit Card
A96: 21030 - Truist Visa Corp Card | B96: 173107.46 | C96: 173717.07 | D96: 173717.07 | E96: 173717.07 | F96: 173717.07 | G96: 173717.07 | H96: 173717.07 | I96: 173717.07 | J96: 173717.07 | K96: 173717.07 | L96: 173717.07 | M96: 173717.07
A97: 21040 - Truist Visa Purchase Card | B97: 4422861.6 | C97: 4617231.1 | D97: 4891960.5 | E97: 4891960.5 | F97: 4891960.5 | G97: 4891960.5 | H97: 4891960.5 | I97: 4891960.5 | J97: 4891960.5 | K97: 4891960.5 | L97: 4891960.5 | M97: 4891960.5
A98: A23900 - Credit cards
A99: A23901 - Truist Visa -Facades -card - Visa (New) | B99: -1364.87 | C99: -1364.87 | D99: -1364.87 | E99: -1364.87 | F99: -1364.87 | G99: -1364.87 | H99: -1364.87 | I99: -1364.87 | J99: -1364.87 | K99: -1364.87 | L99: -1364.87 | M99: -1364.87
A100: A23902 - American Express - 31013 (New) | B100: -436179.28 | C100: -436179.28 | D100: -436179.28 | E100: -436179.28 | F100: -436179.28 | G100: -436179.28 | H100: -436179.28 | I100: -436179.28 | J100: -436179.28 | K100: -436179.28 | L100: -436179.28 | M100: -436179.28
A101: A23903 - Truist -Visa - 6325- CORP(New) | B101: 29816.93 | C101: 29816.93 | D101: 29816.93 | E101: 29816.93 | F101: 29816.93 | G101: 29816.93 | H101: 29816.93 | I101: 29816.93 | J101: 29816.93 | K101: 29816.93 | L101: 29816.93 | M101: 29816.93
A102: A23904 - Truist -Visa - 4576 -PURCHASE (New) | B102: -3065614.9 | C102: -3065265.9 | D102: -3065265.9 | E102: -3065265.9 | F102: -3065265.9 | G102: -3065265.9 | H102: -3065265.9 | I102: -3065265.9 | J102: -3065265.9 | K102: -3065265.9 | L102: -3065265.9 | M102: -3065265.9
...

Sheet tab 2 IS 2025
A1: Graniti Vicentia, L.L.C.
A2: Parent Company : Graniti Vicentia LLC
A3: Graniti Comparative Income Statement
A4: From Jan 2025 to Dec 2025
A6: Options: Activity Only
A7: Financial Row | B7: Amount
B8: Jan 2025 | C8: Feb 2025 | D8: Mar 2025 | E8: Apr 2025 | F8: May 2025 | G8: Jun 2025 | H8: Jul 2025 | I8: Aug 2025 | J8: Sep 2025 | K8: Oct 2025 | L8: Nov 2025 | M8: Dec 2025
A10: Ordinary Income/Expense
A11: Income
A12: 40000 - Revenue
A13: 40100 - Sales Revenue | B13: 0 | C13: 0 | D13: 0 | E13: 0 | F13: 0 | G13: 0 | H13: 0 | I13: 0 | J13: 30000 | K13: 0 | L13: 130964.94 | M13: 241290.64
A14: 40400 - Sales Discount (SALE) | B14: 0 | C14: 0 | D14: 0 | E14: 0 | F14: 0 | G14: 0 | H14: -435.68 | I14: -2765.45 | J14: -33.92 | K14: -54691.8 | L14: -11130.95 | M14: -117510.55
A15: Total - 40000 - Revenue | B15: =SUM(B13:B14) -> 0 | C15: =SUM(C13:C14) -> 0 | D15: =SUM(D13:D14) -> 0 | E15: =SUM(E13:E14) -> 0 | F15: =SUM(F13:F14) -> 0 | G15: =SUM(G13:G14) -> 0 | H15: =SUM(H13:H14) -> -435.68 | I15: =SUM(I13:I14) -> -2765.45 | ... M15: =SUM(M13:M14) -> 123780.09
A16: A40000 - Revenue (GV LLC) (New)
A17: A40001 - Sales Income (New) | B17: 0 | C17: 0 | D17: 0 | E17: -650707.54 | F17: 0 | G17: 32945684 | H17: 3387410.1 | I17: 5935080 | J17: 372145.86 | K17: 738740.19 | L17: 879104.09 | M17: 12848564
A18: A40004 - Other Income (New) | B18: 0 | C18: 0 | D18: 0 | E18: 0 | F18: 0 | G18: 0 | H18: 0 | I18: 0 | J18: 97947 | K18: 0 | L18: 0 | M18: 0
A19: A40005 - Sales Discount (SALE) (New) | B19: 0 | C19: 0 | D19: 0 | E19: 0 | F19: 0 | G19: -1428154 | H19: 0 | I19: 0 | J19: -97947 | K19: 0 | L19: 0 | M19: 0
A20: A40006 - Delivery Income (New) | B20: 0 | C20: 0 | D20: 0 | E20: 0 | F20: 0 | G20: 5258318.7 | H20: 186080.66 | I20: 1070510.5 | J20: 232169.18 | K20: 294170.78 | L20: 731766.18 | M20: 1819403
A21: A40007 - Service Income (New) | B21: 0 | C21: 0 | D21: 0 | E21: 0 | F21: 0 | G21: 1403377.5 | H21: 135165.82 | I21: 295927.18 | J21: 0 | K21: 0 | L21: 0 | M21: 0
A22: Total - A40000 - Revenue (GV LLC) (New) | B22: =SUM(B17:B21) -> 0 | C22: =SUM(C17:C21) -> 0 | D22: =SUM(D17:D21) -> 0 | E22: =SUM(E17:E21) -> -650707.54 | F22: =SUM(F17:F21) -> 0 | G22: =SUM(G17:G21) -> 38179226 | H22: =SUM(H17:H21) -> 3708656.6 | I22: =SUM(I17:I21) -> 7301517.6 | ... M22: =SUM(M17:M21) -> 14667967
A23: Total - Income | B23: =SUM(B15,B22) -> 0 | C23: =SUM(C15,C22) -> 0 | D23: =SUM(D15,D22) -> 0 | E23: =SUM(E15,E22) -> -650707.54 | F23: =SUM(F15,F22) -> 0 | G23: =SUM(G15,G22) -> 38179226 | H23: =SUM(H15,H22) -> 3708220.9 | I23: =SUM(I15,I22) -> 7298752.2 | ... M23: =SUM(M15,M22) -> 14791747
A24: Cost Of Sales
A25: 50000 - Cost of Good Sold
A26: 50000 - Cost of Good Sold | B26: 0 | C26: 0 | D26: 0 | E26: 0 | F26: 0 | G26: 0 | H26: 0 | I26: 0 | J26: 1284309 | K26: 0 | L26: 0 | M26: -137547.52
A27: 50040 - Freight & Delivery Charges | B27: 31042 | C27: 3225 | D27: 66695.8 | E27: 280094.32 | F27: 226202.12 | G27: 315360.35 | H27: 571461.32 | I27: 492205.31 | J27: 454666.67 | K27: 294479.34 | L27: 213661.21 | M27: -128401.58
A28: 50050 - Contract Labor | B28: 0 | C28: 0 | D28: 0 | E28: 0 | F28: 0 | G28: 26568.29 | H28: 360170.13 | I28: 322244.44 | J28: 219600.96 | K28: 134126.79 | L28: 2916.67 | M28: 2916.67
A29: 50070 - Small Tools & Equipment | B29: 0 | C29: 0 | D29: 30 | E29: 1431.34 | F29: 1528.1 | G29: 3476.43 | H29: 17558.88 | I29: 10353.51 | J29: 2184.36 | K29: 7430.34 | L29: 4820.81 | M29: 104.17
A30: 50090 - Design Services | B30: 0 | C30: 0 | D30: 0 | E30: 0 | F30: 10000 | G30: 100000 | H30: 108072.33 | I30: 8241.4 | J30: 0 | K30: 100000 | L30: 0 | M30: 100000
A31: 50100 - Fabrication Expense | B31: 0 | C31: 0 | D31: 0 | E31: 25574.4 | F31: 5916 | G31: 3013 | H31: 24332.54 | I31: 50549.58 | J31: 51301.91 | K31: 26369.76 | L31: 14498.83 | M31: 948
A32: 50200 - Materials and Product Expense | B32: 0 | C32: 0 | D32: 0 | E32: 0 | F32: 19517.49 | G32: 15516.92 | H32: 110384.43 | I32: -8355883.9 | J32: 8149361 | K32: 325115.07 | L32: 463160.78 | M32: 91942.45
A33: Total - 50000 - Cost of Good Sold | B33: =SUM(B26:B32) -> 31042 | C33: =SUM(C26:C32) -> 3225 | D33: =SUM(D26:D32) -> 66725.8 | E33: =SUM(E26:E32) -> 307100.06 | F33: =SUM(F26:F32) -> 263163.71 | G33: =SUM(G26:G32) -> 463934.99 | H33: =SUM(H26:H32) -> 1191979.6 | I33: =SUM(I26:I32) -> -7472289.6 | ... M33: =SUM(M26:M32) -> -70037.81
A34: A50000 - Cost of Goods Sales 50 (GV LLC) (New) | H34: tab 5 issues
A35: A50001 - Cost Of Goods Sold (New) | B35: 170376.66 | C35: 225150.26 | D35: -12170.1 | E35: 369243.21 | F35: -808653.14 | G35: 27272255 | H35: 2639865.6 | I35: 6944149.4 | J35: -38450.35 | K35: 1013484.3 | L35: 1512264.4 | M35: 4003391.8
A36: A50002 - Other Purchase Charges (New) | B36: 0 | C36: 0 | D36: 0 | E36: 0 | F36: 0 | G36: 3451.47 | H36: 0 | I36: 0 | J36: 0 | K36: 0 | L36: 0 | M36: 0
A37: A50003 - Customs Clearance (New) | B37: 0 | C37: 0 | D37: 0 | E37: 0 | F37: 0 | G37: 186947.96 | H37: -85051.09 | I37: -86444.78 | J37: 0 | K37: 0 | L37: 0 | M37: 0
A38: A50004 - Other Expense (New) | B38: 0 | C38: 0 | D38: 0 | E38: 0 | F38: 1310.29 | G38: 3826.07 | H38: 6939.02 | I38: 3886.71 | J38: 10300.26 | K38: 11659.48 | L38: 10551.89 | M38: 41764.23
A39: Total - A50000 - Cost of Goods Sales 50 (GV LLC) (New) | B39: =SUM(B35:B38) -> 170376.66 | C39: =SUM(C35:C38) -> 225150.26 | D39: =SUM(D35:D38) -> -12170.1 | E39: =SUM(E35:E38) -> 369243.21 | F39: =SUM(F35:F38) -> -807342.85 | G39: =SUM(G35:G38) -> 27466480 | H39: =SUM(H35:H38) -> 2561753.5 | I39: =SUM(I35:I38) -> 6861591.3 | ... M39: =SUM(M35:M38) -> 4045156
A40: A51000 - Cost of Goods Sales 51 (GV LLC) (New)
A41: A51001 - Freight - Out - Expense (New) | B41: 114507.14 | C41: 39463.76 | D41: 70790.84 | E41: 4742.44 | F41: 38742.89 | G41: 1371255.8 | H41: 190640.5 | I41: 937382.8 | J41: 112752.04 | K41: 236826.13 | L41: 563149.25 | M41: 772626.89
A42: A51002 - Freight - Inn - Expenses (New) | B42: 0 | C42: 0 | D42: 0 | E42: 0 | F42: 0 | G42: 76774.35 | H42: -76774.35 | I42: 0 | J42: 247.5 | K42: 488.42 | L42: 9478.57 | M42: 86840.24
A43: A51003 - Freight Variance (New) | B43: 0 | C43: 0 | D43: 0 | E43: 0 | F43: 0 | G43: -0.16 | H43: 0 | I43: 0 | J43: 0 | K43: 0 | L43: 0 | M43: 0
A44: A51004 - Delivery Expense (New) | B44: 0 | C44: 0 | D44: 0 | E44: 0 | F44: 0 | G44: 109621.04 | H44: 0 | I44: 54.4 | J44: 0 | K44: 0 | L44: 0 | M44: 171808.61
A45: A51005 - Payroll - Salary - Ops (New) | B45: 0 | C45: 0 | D45: 0 | E45: 0 | F45: 0 | G45: 0 | H45: 214755.19 | I45: 216026.96 | J45: 321275.61 | K45: 214113.9 | L45: 159806.92 | M45: 178399.44
A46: A51006 - Payroll Taxes-Employer W/H - Ops (New) | B46: 0 | C46: 0 | D46: 0 | E46: 0 | F46: 0 | G46: 0 | H46: 14801.09 | I46: 14858.15 | J46: 22599.9 | K46: 14570.09 | L46: 12156.46 | M46: 11315.82
A47: Total - A51000 - Cost of Goods Sales 51 (GV LLC) (New) | B47: =SUM(B41:B46) -> 114507.14 | C47: =SUM(C41:C46) -> 39463.76 | D47: =SUM(D41:D46) -> 70790.84 | E47: =SUM(E41:E46) -> 4742.44 | F47: =SUM(F41:F46) -> 38742.89 | G47: =SUM(G41:G46) -> 1557651 | H47: =SUM(H41:H46) -> 343422.43 | I47: =SUM(I41:I46) -> 1168322.3 | ... M47: =SUM(M41:M46) -> 1220991
A48: A52000 - Cost of Goods Sales 52 (GV LLC)
A49: A52001 - Equipment Rental (New) | B49: 0 | C49: 0 | D49: 0 | E49: 0 | F49: 10537.28 | G49: 45181.33 | H49: 4174.2 | I49: 2131.68 | J49: 4325.34 | K49: 1165.84 | L49: 270.63 | M49: 1725.11
A50: A52002 - Small Tools And Materials (New) | B50: 0 | C50: 0 | D50: 0 | E50: 0 | F50: 8303.64 | G50: 264822.71 | H50: 56769.09 | I50: 13206.28 | J50: 12058.28 | K50: 11981.82 | L50: 35924.07 | M50: 20080.38
A51: A52003 - Tools & Equipment (New) | B51: 0 | C51: 0 | D51: 0 | E51: 0 | F51: 0 | G51: 4316.18 | H51: 0 | I51: 159.32 | J51: 13.18 | K51: 996.67 | L51: 4097.13 | M51: 11093.83
A52: A52004 - Fabrication And Installation Expense (New) | B52: 0 | C52: 0 | D52: 0 | E52: 0 | F52: 4450 | G52: 392405.44 | H52: 11046.5 | I52: 0 | J52: 0 | K52: 3041.84 | L52: 0 | M52: 9155.03
A53: A52005 - Contract Labor (New) | B53: 0 | C53: 0 | D53: 0 | E53: 0 | F53: 0 | G53: 1591044.5 | H53: 8611.32 | I53: 8611.33 | J53: 23669.76 | K53: 25173.01 | L53: 168319.5 | M53: 195040.88
A54: A52006 - Italian Designers Consulting Expenses (New) | B54: 0 | C54: 0 | D54: 0 | E54: 0 | F54: 0 | G54: 110673.16 | H54: 0 | I54: 0 | J54: 0 | K54: 0 | L54: 18.92 | M54: 0
A55: Total - A52000 - Cost of Goods Sales 52 (GV LLC) | B55: =SUM(B49:B54) -> 0 | C55: =SUM(C49:C54) -> 0 | D55: =SUM(D49:D54) -> 0 | E55: =SUM(E49:E54) -> 0 | F55: =SUM(F49:F54) -> 23290.92 | G55: =SUM(G49:G54) -> 2408443.3 | H55: =SUM(H49:H54) -> 80601.11 | I55: =SUM(I49:I54) -> 24108.61 | ... M55: =SUM(M49:M54) -> 237095.23
A56: Total - Cost Of Sales | B56: =SUM(B33,B39,B47,B55) -> 315925.8 | C56: =SUM(C33,C39,C47,C55) -> 267839.02 | D56: =SUM(D33,D39,D47,D55) -> 125346.54 | E56: =SUM(E33,E39,E47,E55) -> 681085.71 | F56: =SUM(F33,F39,F47,F55) -> -482145.33 | G56: =SUM(G33,G39,G47,G55) -> 31896510 | H56: =SUM(H33,H39,H47,H55) -> 4177756.7 | I56: =SUM(I33,I39,I47,I55) -> 581732.59 | ... M56: =SUM(M33,M39,M47,M55) -> 5433204.5
A57: Gross Profit | B57: =B23-B56 -> -315925.8 | C57: =C23-C56 -> -267839.02 | D57: =D23-D56 -> -125346.54 | E57: =E23-E56 -> -1331793.2 | F57: =F23-F56 -> 482145.33 | G57: =G23-G56 -> 6282716.6 | H57: =H23-H56 -> -469535.75 | I57: =I23-I56 -> 6717019.6 | ... M57: =M23-M56 -> 9358542.3
A58: Expense
A59: 60000 - Sales Expense
A60: 60000 - Sales Expense | B60: 0 | C60: 0 | D60: 0 | E60: 0 | F60: 0 | G60: 0 | H60: 0 | I60: 0 | J60: 0 | K60: 0 | L60: 0 | M60: 1640
A61: 60190 - Event and Trade Show Expense | B61: 0 | C61: 0 | D61: 0 | E61: 0 | F61: 0 | G61: 0 | H61: 0 | I61: 0 | J61: 0 | K61: 0 | L61: 302.68 | M61: 0
A62: 60200 - Marketing & Advertisement | B62: 0 | C62: 0 | D62: 0 | E62: 0 | F62: 0 | G62: 0 | H62: 0 | I62: 0 | J62: 0 | K62: 0 | L62: 0 | M62: 120
A63: Total - 60000 - Sales Expense | B63: =SUM(B60:B62) -> 0 | C63: =SUM(C60:C62) -> 0 | D63: =SUM(D60:D62) -> 0 | E63: =SUM(E60:E62) -> 0 | F63: =SUM(F60:F62) -> 0 | G63: =SUM(G60:G62) -> 0 | H63: =SUM(H60:H62) -> 0 | I63: =SUM(I60:I62) -> 0 | ... M63: =SUM(M60:M62) -> 1760
A64: 70000 - G&A Expense
A65: 70110 - Office Supplies | B65: 0 | C65: 0 | D65: 0 | E65: 0 | F65: 0 | G65: 0 | H65: 29.04 | I65: 0 | J65: 0 | K65: 0 | L65: 0 | M65: 0
A66: 70140 - Rent | B66: 0 | C66: 0 | D66: 0 | E66: 0 | F66: 0 | G66: 0 | H66: -3124.14 | I66: 0 | J66: 0 | K66: 0 | L66: 0 | M66: 0
A67: 70300 - Postage & Courier Expenses | B67: 0 | C67: 0 | D67: 0 | E67: 0 | F67: 1864.08 | G67: 39285.01 | H67: 28830.33 | I67: 15749.34 | J67: 23016.84 | K67: 15453.46 | L67: 0 | M67: 0
A68: 70320 - Bank Charges | B68: 0 | C68: 0 | D68: 0 | E68: 0 | F68: 0 | G68: 0 | H68: 27 | I68: -240.92 | J68: 0 | K68: 0 | L68: 0 | M68: 0
A69: 70340 - Insurance | B69: 0 | C69: 0 | D69: 0 | E69: 0 | F69: 0 | G69: 0 | H69: 0 | I69: -695.19 | J69: 0 | K69: 0 | L69: 0 | M69: 0
A70: Total - 70000 - G&A Expense | B70: =SUM(B65:B69) -> 0 | C70: =SUM(C65:C69) -> 0 | D70: =SUM(D65:D69) -> 0 | E70: =SUM(E65:E69) -> 0 | F70: =SUM(F65:F69) -> 1864.08 | G70: =SUM(G65:G69) -> 39285.01 | H70: =SUM(H65:H69) -> 25762.23 | I70: =SUM(I65:I69) -> 14813.23 | ... M70: =SUM(M65:M69) -> 0
A71: 91000 - Open AP Account | B71: 0 | C71: 0 | D71: 0 | E71: 0 | F71: 0 | G71: 0 | H71: 218515.46 | I71: 0 | J71: 0 | K71: 0 | L71: 0 | M71: 0
A72: A60000 - Selling Expenses (GV LLC) (New)
A73: A60001 - Sales Commissions (New) | B73: 0 | C73: 0 | D73: 0 | E73: 0 | F73: 0 | G73: 601004.76 | H73: 11472.4 | I73: 103846.15 | J73: 139598.16 | K73: 212236.48 | L73: 100000 | M73: 133060
A74: A60002 - Convention And Seminar Expense (New) | B74: 0 | C74: 0 | D74: 0 | E74: 0 | F74: 0 | G74: 149985.05 | H74: 405.86 | I74: 0 | J74: 0 | K74: 1409.85 | L74: 2066.76 | M74: 384.6
A75: A60003 - Advertising Expense (New) | B75: 0 | C75: 0 | D75: 0 | E75: 0 | F75: 0 | G75: 150.6 | H75: 0 | I75: 21.63 | J75: 325.22 | K75: 382.03 | L75: 0 | M75: 0
A76: A60004 - Marketing Expenses (New) | B76: 0 | C76: 0 | D76: 0 | E76: 1038.16 | F76: 0 | G76: 335226.22 | H76: -620.52 | I76: 266.49 | J76: 213.2 | K76: 47202.2 | L76: 26868.31 | M76: 22259.27
A77: A60005 - Payroll - Salary - Sales (New) | B77: 0 | C77: 0 | D77: 0 | E77: 0 | F77: 0 | G77: 0 | H77: 90603.33 | I77: 82724.2 | J77: 144554.01 | K77: 83606.18 | L77: 91298.95 | M77: 93907.63
A78: A60006 - Payroll Taxes - Employer W/H - Sales (New) | B78: 0 | C78: 0 | D78: 0 | E78: 0 | F78: 0 | G78: 0 | H78: 6793.03 | I78: 6467.55 | J78: 9937.89 | K78: 5108.72 | L78: 5671.55 | M78: 4882.82
A79: A60007 - Payroll service charges - Expense - Sales (New) | B79: 0 | C79: 0 | D79: 0 | E79: 0 | F79: 0 | G79: 0 | H79: 2033.25 | I79: 0 | J79: -230.77 | K79: 0 | L79: 0 | M79: 0
A80: A60010 - Fedex-Marketing Expenses (New) | B80: 0 | C80: 0 | D80: 0 | E80: 0 | F80: 0 | G80: 0 | H80: 76774.35 | I80: 0 | J80: 0 | K80: 0 | L80: 86.14 | M80: 12212.69
A81: Total - A60000 - Selling Expenses (GV LLC) (New) | B81: =SUM(B73:B80) -> 0 | C81: =SUM(C73:C80) -> 0 | D81: =SUM(D73:D80) -> 0 | E81: =SUM(E73:E80) -> 1038.16 | F81: =SUM(F73:F80) -> 0 | G81: =SUM(G73:G80) -> 1086366.6 | H81: =SUM(H73:H80) -> 187461.7 | I81: =SUM(I73:I80) -> 193326.02 | ... M81: =SUM(M73:M80) -> 266707.01
A82: A70000 - Professional services (GV LLC) (New)
A83: A70001 - Legal & Accounting (New) | B83: 0 | C83: 0 | D83: 3241.41 | E83: 701.36 | F83: 92.97 | G83: 194349.92 | H83: 61028.8 | I83: 61149.34 | J83: 33813.75 | K83: 22335.09 | L83: 22740.01 | M83: 56793.35
A84: A70002 - Consultation Expenses (New) | B84: 0 | C84: 0 | D84: 0 | E84: 0 | F84: 8100 | G84: 300956.17 | H84: 34504.27 | I84: 10100 | J84: 50025.88 | K84: 33713.54 | L84: 25256.28 | M84: 24810.21
A85: A70101 - Support Services (India) (New) | B85: 0 | C85: 0 | D85: 0 | E85: 0 | F85: 0 | G85: 497107.2 | H85: 0 | I85: 0 | J85: 57500 | K85: 243887 | L85: 187872 | M85: 175000
A86: Total - A70000 - Professional services (GV LLC) (New) | B86: =SUM(B83:B85) -> 0 | C86: =SUM(C83:C85) -> 0 | D86: =SUM(D83:D85) -> 3241.41 | E86: =SUM(E83:E85) -> 701.36 | F86: =SUM(F83:F85) -> 8192.97 | G86: =SUM(G83:G85) -> 992413.29 | H86: =SUM(H83:H85) -> 95533.07 | I86: =SUM(I83:I85) -> 71249.34 | ... M86: =SUM(M83:M85) -> 256603.56
A87: A71000 - Office expenses (GV LLC) (New)
A88: A71001 - Office Supplies (New) | B88: 0 | C88: 161.11 | D88: 1034.78 | E88: 289.18 | F88: 400.47 | G88: 59400.38 | H88: 14531.62 | I88: 7865.83 | J88: 6651.27 | K88: 4766.38 | L88: 17913.6 | M88: 8282.12
A89: A71002 - Printing And Reproduction Expense (New) | B89: 0 | C89: 0 | D89: 0 | E89: 0 | F89: 0 | G89: 13461.91 | H89: 0 | I89: 0 | J89: 0 | K89: 823.32 | L89: 0 | M89: 0
A90: A71003 - Organizational Costs (New) | B90: 0 | C90: 0 | D90: 0 | E90: 0 | F90: 0 | G90: 172119.47 | H90: 0 | I90: 0 | J90: 0 | K90: 0 | L90: 0 | M90: 0
A91: A71004 - Postage & Courier Expenses (New) | B91: 0 | C91: 0 | D91: 0 | E91: 0 | F91: 0 | G91: 95703.58 | H91: 466.83 | I91: 75.6 | J91: 0 | K91: 3599.95 | L91: 19308.3 | M91: 4188.57
A92: Total - A71000 - Office expenses (GV LLC) (New) | B92: =SUM(B88:B91) -> 0 | C92: =SUM(C88:C91) -> 161.11 | D92: =SUM(D88:D91) -> 1034.78 | E92: =SUM(E88:E91) -> 289.18 | F92: =SUM(F88:F91) -> 400.47 | G92: =SUM(G88:G91) -> 340685.34 | H92: =SUM(H88:H91) -> 14998.45 | I92: =SUM(I88:I91) -> 7941.43 | ... M92: =SUM(M88:M91) -> 12470.69
A93: A72000 - Utilities & maintenance (GV LLC) (New)
A94: A72001 - Lawn & Landscaping Expenses (New) | B94: 0 | C94: 0 | D94: 0 | E94: 0 | F94: 0 | G94: 14775 | H94: 11055 | I94: 1155 | J94: 1155 | K94: 4155 | L94: 1155 | M94: 7155
A95: A72002 - Rent (New) | B95: 0 | C95: 0 | D95: 0 | E95: 0 | F95: 0 | G95: 336000 | H95: 427035 | I95: 109500 | J95: 109600 | K95: 112574.04 | L95: 112102.58 | M95: 112101.99
A96: A72003 - Telephone (New) | B96: 0 | C96: 0 | D96: 0 | E96: 0 | F96: 0 | G96: 26104.4 | H96: 4608.13 | I96: 5917.66 | J96: 4743.41 | K96: 4623.49 | L96: 5154.54 | M96: 5251.19
A97: A72004 - Utilities (New) | B97: 0 | C97: 0 | D97: 0 | E97: 0 | F97: 0 | G97: 88558.31 | H97: 45037.94 | I97: 21277.51 | J97: 17864.02 | K97: 23590.86 | L97: 25913.14 | M97: 15055.03
A98: A72005 - Propane Gas Expense (New) | B98: 0 | C98: 0 | D98: 0 | E98: 0 | F98: 0 | G98: 3281.45 | H98: 0 | I98: 0 | J98: 279.48 | K98: 319.48 | L98: 4108.23 | M98: 149.74
A99: A72006 - Repairs And Maintenance (New) | B99: 0 | C99: 0 | D99: 0 | E99: 0 | F99: 0 | G99: 92432.88 | H99: 7582.53 | I99: 10533.32 | J99: 6199.44 | K99: 7042.26 | L99: 8443.05 | M99: 2906.55
A100: A72007 - Cleaning Office & Warehouse | B100: 0 | C100: 0 | D100: 0 | E100: 0 | F100: 0 | G100: 0 | H100: 4520 | I100: 5410 | J100: 6862 | K100: 5710 | L100: 5710 | M100: 3879
A101: Total - A72000 - Utilities & maintenance (GV LLC) (New) | B101: =SUM(B94:B100) -> 0 | C101: =SUM(C94:C100) -> 0 | D101: =SUM(D94:D100) -> 0 | E101: =SUM(E94:E100) -> 0 | F101: =SUM(F94:F100) -> 0 | G101: =SUM(G94:G100) -> 561152.04 | H101: =SUM(H94:H100) -> 499838.6 | I101: =SUM(I94:I100) -> 153793.49 | ... M101: =SUM(M94:M100) -> 146498.5
A102: A73000 - Travel, Conveyance and Gas (GV LLC) (New)
...

Sheet tab 3 bal sheetNtsuite Jan 2026
A1: Graniti Vicentia, L.L.C.
A2: Parent Company : Graniti Vicentia LLC
A3: Balance Sheet Detail
A4: Jan 2026
A7: Financial Row | B7: Type | C7: Date | D7: Document Number | E7: Name | F7: Amount | G7: Balance | I7: {=_xlfn.UNIQUE(B:B)} -> 0
A8: ASSETS | F8: 0 | G8: 0 | I8: Type
A9: Current Assets | F9: 0 | G9: 0 | I9: Item Receipt | J9: =SUMIF(B:B,I9,F:F) -> 1462939.7
A10: Other Current Asset | F10: 0 | G10: 0 | I10: Item Fulfillment | J10: =SUMIF(B:B,I10,F:F) -> -417768.92
A11: A12000 - Inventory (GV LLC) (New) | F11: 0 | G11: 0 | I11: Inventory Adjustment | J11: =SUMIF(B:B,I11,F:F) -> 5079051.3
A12: A12001 - Inventory (New) | F12: 0 | G12: 4389020
B13: Item Receipt | C13: 46023 | D13: IR1444 | E13: U.S. Vinyl Manufacturing Corp | F13: 342.6 | G13: =G12+F13 -> 4389362.6 | I13: Net
B14: Item Receipt | C14: 46023 | D14: IR1444 | E14: U.S. Vinyl Manufacturing Corp | F14: 477.5 | G14: =G13+F14 -> 4389840.1
B15: Item Receipt | C15: 46023 | D15: IR1444 | F15: -342.6 | G15: =G14+F15 -> 4389497.5
B16: Item Receipt | C16: 46023 | D16: IR1444 | F16: -477.5 | G16: =G15+F16 -> 4389020
B17: Item Receipt | C17: 46024 | D17: IR939 | E17: MirageGranitoCeramico S.p.A | F17: 23358.03 | G17: =G16+F17 -> 4412378
B18: Item Receipt | C18: 46024 | D18: IR940 | E18: MirageGranitoCeramico S.p.A | F18: 683.55 | G18: =G17+F18 -> 4413061.5
B19: Item Receipt | C19: 46024 | D19: IR941 | E19: HARMONY HOSPITALITY CO LTD | F19: 345.23 | G19: =G18+F19 -> 4413406.8
B20: Item Receipt | C20: 46024 | D20: IR942 | E20: HARMONY HOSPITALITY CO LTD | F20: 207.73 | G20: =G19+F20 -> 4413614.5
B21: Item Receipt | C21: 46024 | D21: IR943 | E21: HARMONY HOSPITALITY CO LTD | F21: 742.43 | G21: =G20+F21 -> 4414356.9
B22: Item Receipt | C22: 46024 | D22: IR944 | E22: HARMONY HOSPITALITY CO LTD | F22: 386.01 | G22: =G21+F22 -> 4414742.9
B23: Item Receipt | C23: 46024 | D23: IR945 | E23: HARMONY HOSPITALITY CO LTD | F23: 882 | G23: =G22+F23 -> 4415624.9
B24: Item Receipt | C24: 46024 | D24: IR945 | F24: -882 | G24: =G23+F24 -> 4414742.9
B25: Item Receipt | C25: 46024 | D25: IR946 | E25: HARMONY HOSPITALITY CO LTD | F25: 87.75 | G25: =G24+F25 -> 4414830.7
B26: Item Receipt | C26: 46024 | D26: IR946 | F26: -87.75 | G26: =G25+F26 -> 4414742.9
B27: Item Receipt | C27: 46024 | D27: IR947 | E27: HARMONY HOSPITALITY CO LTD | F27: 126.5 | G27: =G26+F27 -> 4414869.4
B28: Item Receipt | C28: 46024 | D28: IR947 | F28: -28.09 | G28: =G27+F28 -> 4414841.4
B29: Item Receipt | C29: 46024 | D29: IR948 | E29: HARMONY HOSPITALITY CO LTD | F29: 2264 | G29: =G28+F29 -> 4417105.4
B30: Item Receipt | C30: 46024 | D30: IR948 | F30: -2264 | G30: =G29+F30 -> 4414841.4
B31: Item Receipt | C31: 46024 | D31: IR949 | E31: HARMONY HOSPITALITY CO LTD | F31: 176 | G31: =G30+F31 -> 4415017.4
B32: Item Receipt | C32: 46024 | D32: IR949 | F32: -176 | G32: =G31+F32 -> 4414841.4
B33: Item Receipt | C33: 46024 | D33: IR950 | E33: HARMONY HOSPITALITY CO LTD | F33: 3144 | G33: =G32+F33 -> 4417985.4
B34: Item Receipt | C34: 46024 | D34: IR951 | E34: HARMONY HOSPITALITY CO LTD | F34: 320 | G34: =G33+F34 -> 4418305.4
B35: Item Receipt | C35: 46024 | D35: IR952 | E35: HARMONY HOSPITALITY CO LTD | F35: 2134.59 | G35: =G34+F35 -> 4420439.9
B36: Item Receipt | C36: 46024 | D36: IR952 | F36: -2134.59 | G36: =G35+F36 -> 4418305.4
B37: Item Receipt | C37: 46024 | D37: IR953 | E37: HARMONY HOSPITALITY CO LTD | F37: 3140.2 | G37: =G36+F37 -> 4421445.6
B38: Item Receipt | C38: 46024 | D38: IR954 | E38: HARMONY HOSPITALITY CO LTD | F38: 1677.8 | G38: =G37+F38 -> 4423123.4
B39: Item Receipt | C39: 46024 | D39: IR954 | F39: -1677.8 | G39: =G38+F39 -> 4421445.6
B40: Item Receipt | C40: 46024 | D40: IR955 | E40: HARMONY HOSPITALITY CO LTD | F40: 1528 | G40: =G39+F40 -> 4422973.6
B41: Item Receipt | C41: 46024 | D41: IR955 | F41: -1528 | G41: =G40+F41 -> 4421445.6
B42: Item Receipt | C42: 46024 | D42: IR956 | E42: HARMONY HOSPITALITY CO LTD | F42: 2060 | G42: =G41+F42 -> 4423505.6
B43: Item Receipt | C43: 46024 | D43: IR956 | F43: -2060 | G43: =G42+F43 -> 4421445.6
B44: Item Receipt | C44: 46024 | D44: IR957 | E44: HARMONY HOSPITALITY CO LTD | F44: 1868.6 | G44: =G43+F44 -> 4423314.2
B45: Item Receipt | C45: 46024 | D45: IR957 | F45: -1868.6 | G45: =G44+F45 -> 4421445.6
B46: Item Receipt | C46: 46024 | D46: IR958 | E46: HARMONY HOSPITALITY CO LTD | F46: 390.26 | G46: =G45+F46 -> 4421835.8
B47: Item Receipt | C47: 46024 | D47: IR958 | F47: -390.26 | G47: =G46+F47 -> 4421445.6
B48: Item Receipt | C48: 46024 | D48: IR959 | E48: HARMONY HOSPITALITY CO LTD | F48: 437.76 | G48: =G47+F48 -> 4421883.3
B49: Item Receipt | C49: 46024 | D49: IR959 | F49: -437.76 | G49: =G48+F49 -> 4421445.6
B50: Item Receipt | C50: 46024 | D50: IR960 | E50: HARMONY HOSPITALITY CO LTD | F50: 745.57 | G50: =G49+F50 -> 4422191.1
B51: Item Receipt | C51: 46024 | D51: IR960 | F51: -745.57 | G51: =G50+F51 -> 4421445.6
B52: Item Receipt | C52: 46024 | D52: IR961 | E52: HARMONY HOSPITALITY CO LTD | F52: 5183 | G52: =G51+F52 -> 4426628.6
B53: Item Receipt | C53: 46024 | D53: IR961 | F53: -5183 | G53: =G52+F53 -> 4421445.6
B54: Item Receipt | C54: 46024 | D54: IR962 | E54: HARMONY HOSPITALITY CO LTD | F54: 742 | G54: =G53+F54 -> 4422187.6
B55: Item Receipt | C55: 46024 | D55: IR962 | F55: -742 | G55: =G54+F55 -> 4421445.6
B56: Item Receipt | C56: 46024 | D56: IR963 | E56: HARMONY HOSPITALITY CO LTD | F56: 588.16 | G56: =G55+F56 -> 4422033.7
B57: Item Receipt | C57: 46024 | D57: IR963 | F57: -588.16 | G57: =G56+F57 -> 4421445.6
B58: Item Receipt | C58: 46024 | D58: IR964 | E58: Stonepeak Ceramics, Inc. | F58: 1012.16 | G58: =G57+F58 -> 4422457.7
B59: Item Receipt | C59: 46025 | D59: IR1035 | E59: Ceramica Refin SPA | F59: 9562.27 | G59: =G58+F59 -> 4432020
B60: Item Receipt | C60: 46025 | D60: IR1036 | E60: Ceramica Refin SPA | F60: 12373.19 | G60: =G59+F60 -> 4444393.2
B61: Item Fulfillment | C61: 46027 | D61: IF333 | E61: Restaurant Renovations Inc | F61: -430.9 | G61: =G60+F61 -> 4443962.3
B62: Item Fulfillment | C62: 46027 | D62: IF334 | E62: ZJZ Hospitality Inc. | F62: -7011.69 | G62: =G61+F62 -> 4436950.6
B63: Item Fulfillment | C63: 46027 | D63: IF947 | E63: Pearl and Posh L.L.C (BODENVY) | F63: -2856.38 | G63: =G62+F63 -> 4434094.2
B64: Item Receipt | C64: 46027 | D64: IR966 | E64: Jasfer Industry Co., Limited | F64: 250 | G64: =G63+F64 -> 4434344.2
B65: Item Receipt | C65: 46027 | D65: IR967 | E65: Jasfer Industry Co., Limited | F65: 1900 | G65: =G64+F65 -> 4436244.2
B66: Item Receipt | C66: 46027 | D66: IR967 | E66: Jasfer Industry Co., Limited | F66: 81 | G66: =G65+F66 -> 4436325.2
B67: Item Receipt | C67: 46027 | D67: IR967 | E67: Jasfer Industry Co., Limited | F67: 110 | G67: =G66+F67 -> 4436435.2
B68: Item Receipt | C68: 46027 | D68: IR967 | E68: Jasfer Industry Co., Limited | F68: 240 | G68: =G67+F68 -> 4436675.2
B69: Item Receipt | C69: 46027 | D69: IR968 | E69: HARMONY HOSPITALITY CO LTD | F69: 8203.08 | G69: =G68+F69 -> 4444878.3
... B76: Item Receipt | C76: 46027 | D76: IR969 | E76: HARMONY HOSPITALITY CO LTD | F76: 740.3 | G76: =G75+F76 -> 4448721.8
B77: Item Receipt | C77: 46027 | D77: IR969 | F77: -29 | G77: =G76+F77 -> 4448692.8
B78: Item Receipt | C78: 46027 | D78: IR969 | F78: -2234 | G78: =G77+F78 -> 4446458.8
B79: Item Receipt | C79: 46027 | D79: IR969 | F79: -32.9 | G79: =G78+F79 -> 4446425.9
B80: Item Receipt | C80: 46027 | D80: IR969 | F80: -30 | G80: =G79+F80 -> 4446395.9
B81: Item Receipt | C81: 46027 | D81: IR969 | F81: -37 | G81: =G80+F81 -> 4446358.9
B82: Item Receipt | C82: 46027 | D82: IR1025 | E82: HARMONY HOSPITALITY CO LTD | F82: 913.53 | G82: =G81+F82 -> 4447272.4
B83: Item Receipt | C83: 46027 | D83: IR1025 | E83: HARMONY HOSPITALITY CO LTD | F83: 639 | G83: =G82+F83 -> 4447911.4
B84: Item Receipt | C84: 46027 | D84: IR1025 | E84: HARMONY HOSPITALITY CO LTD | F84: 167.74 | G84: =G83+F84 -> 4448079.2
B85: Item Receipt | C85: 46027 | D85: IR1025 | E85: HARMONY HOSPITALITY CO LTD | F85: 975 | G85: =G84+F85 -> 4449054.2
B86: Item Receipt | C86: 46027 | D86: IR1025 | E86: HARMONY HOSPITALITY CO LTD | F86: 2870 | G86: =G85+F86 -> 4451924.2
B87: Item Receipt | C87: 46027 | D87: IR1025 | E87: HARMONY HOSPITALITY CO LTD | F87: 3025.96 | G87: =G86+F87 -> 4454950.1
B88: Item Receipt | C88: 46027 | D88: IR1025 | E88: HARMONY HOSPITALITY CO LTD | F88: 2617.95 | G88: =G87+F88 -> 4457568.1
B89: Item Receipt | C89: 46027 | D89: IR1025 | E89: HARMONY HOSPITALITY CO LTD | F89: 1748 | G89: =G88+F89 -> 4459316.1
B90: Item Receipt | C90: 46027 | D90: IR1025 | E90: HARMONY HOSPITALITY CO LTD | F90: 1287 | G90: =G89+F90 -> 4460603.1
B91: Item Receipt | C91: 46027 | D91: IR1025 | E91: HARMONY HOSPITALITY CO LTD | F91: 677 | G91: =G90+F91 -> 4461280.1
B92: Item Receipt | C92: 46027 | D92: IR1025 | E92: HARMONY HOSPITALITY CO LTD | F92: 989.52 | G92: =G91+F92 -> 4462269.6
B93: Item Receipt | C93: 46027 | D93: IR1025 | E93: HARMONY HOSPITALITY CO LTD | F93: 1726.8 | G93: =G92+F93 -> 4463996.4
... B96: Item Receipt | C96: 46027 | D96: IR1025 | E96: HARMONY HOSPITALITY CO LTD | F96: 438.8 | G96: =G95+F96 -> 4466836.5
B97: Item Receipt | C97: 46027 | D97: IR1025 | F97: -823.36 | G97: =G96+F97 -> 4466013.2
B98: Item Receipt | C98: 46027 | D98: IR1025 | F98: -677 | G98: =G97+F98 -> 4465336.2
B99: Item Receipt | C99: 46027 | D99: IR1025 | F99: -2870 | G99: =G98+F99 -> 4462466.2
B100: Item Receipt | C100: 46027 | D100: IR1025 | F100: -989.52 | G100: =G99+F100 -> 4461476.7
B101: Item Receipt | C101: 46027 | D101: IR1025 | F101: -913.53 | G101: =G100+F101 -> 4460563.1
B102: Item Receipt | C102: 46027 | D102: IR1025 | F102: -639 | G102: =G101+F102 -> 4459924.1
B103: Item Receipt | C103: 46027 | D103: IR1025 | F103: -167.74 | G103: =G102+F103 -> 4459756.4
B104: Item Receipt | C104: 46027 | D104: IR1025 | F104: -975 | G104: =G103+F104 -> 4458781.4
B105: Item Receipt | C105: 46027 | D105: IR1025 | F105: -1748 | G105: =G104+F105 -> 4457033.4
B106: Item Receipt | C106: 46027 | D106: IR1025 | F106: -1287 | G106: =G105+F106 -> 4455746.4
B107: Item Receipt | C107: 46027 | D107: IR1025 | F107: -438.8 | G107: =G106+F107 -> 4455307.6
B108: Item Receipt | C108: 46027 | D108: IR1025 | F108: -1726.8 | G108: =G107+F108 -> 4453580.8
... B111: Item Receipt | C111: 46027 | D111: IR1025 | F111: -2617.95 | G111: =G110+F111 -> 4446358.9
B112: Item Receipt | C112: 46027 | D112: IR1029 | E112: Modular Shower Walls | F112: 1186.8 | G112: =G111+F112 -> 4447545.7
...

Sheet tab 4 Nsuite July Income statem
A1: Graniti Vicentia, L.L.C.
A2: Parent Company : Graniti Vicentia LLC
A3: Graniti - Income Statement Detail
A4: Jul 2025
A6: Options: Activity Only
A7: Financial Row | B7: Type | C7: Date | D7: Document Number | E7: Name | F7: Entity (Line) | G7: Clr | H7: Split | I7: Reference No. | J7: Description | K7: Memo | L7: Amount
A8: Ordinary Income/Expense
A9: Cost Of Sales
A10: A50000 - Cost of Goods Sales 50 (GV LLC) (New) | N10: 0
A11: A50001 - Cost Of Goods Sold (New) | N11: Type
B12: Journal | C12: 45839 | D12: JE1831 | F12: LaQuinta - Naples - FL - Raj Mukkirla | G12: F | H12: A12001 - Inventory (GV LLC) (New) : Inventory (New) | I12: 34076 | J12: LaQuinta - Naples - FL - Raj MukkirlaImport July 25 cogs for materials from SPS to Netsuite | K12: LaQuinta - Naples - FL - Raj MukkirlaImport July 25 cogs for materials from SPS to Netsuite | L12: 6083.65 | N12: Journal | O12: =SUMIF(B:B,N12,L:L) -> 2619838.7
B13: Journal | C13: 45839 | D13: JE1011 | F13: Monsoon Flower LLC | G13: F | H13: A12001 - Inventory (GV LLC) (New) : Inventory (New) | I13: 37959/2 | J13: Monsoon Flower LLCImport July 25 cogs for materials from SPS to Netsuite | K13: Monsoon Flower LLCImport July 25 cogs for materials from SPS to Netsuite | L13: 12463.65 | N13: Bill | O13: =SUMIF(B:B,N13,L:L) -> 18605.75
B14: Journal | C14: 45839 | D14: JE1007 | F14: Graniti Vicentia | G14: F | H14: A12001 - Inventory (GV LLC) (New) : Inventory (New) | I14: 36159/4 | J14: Graniti VicentiaImport July 25 cogs for materials from SPS to Netsuite | K14: Graniti VicentiaImport July 25 cogs for materials from SPS to Netsuite | L14: 2609.63 | N14: Item Receipt | O14: =SUMIF(B:B,N14,L:L) -> 1421.14
B15: Journal | C15: 45839 | D15: JE1001 | F15: Magnolia LXR Dallas TX - | G15: F | H15: A12001 - Inventory (GV LLC) (New) : Inventory (New) | I15: 34086/8 | J15: Magnolia LXR Dallas TX -Import July 25 cogs for materials from SPS to Netsuite | K15: Magnolia LXR Dallas TX -Import July 25 cogs for materials from SPS to Netsuite | L15: 10311.03
B16: Journal | C16: 45839 | D16: JE1000 | F16: LaQuinta/Hawthone - Knoxville TN - AMit | G16: F | H16: A12001 - Inventory (GV LLC) (New) : Inventory (New) | I16: 33722/5 | J16: LaQuinta/Hawthone - Knoxville TN - AMitImport July 25 cogs for materials from SPS to Netsuite | K16: LaQuinta/Hawthone - Knoxville TN - AMitImport July 25 cogs for materials from SPS to Netsuite | L16: 848
B17: Journal | C17: 45839 | D17: JE1008 | F17: CANDLEWOOD EASTRIDGE TN | G17: F | H17: A12001 - Inventory (GV LLC) (New) : Inventory (New) | I17: 36221 | J17: CANDLEWOOD EASTRIDGE TNImport July 25 cogs for materials from SPS to Netsuite | K17: CANDLEWOOD EASTRIDGE TNImport July 25 cogs for materials from SPS to Netsuite | L17: 386.87
B18: Journal | C18: 45839 | D18: JE999 | F18: La Quinta Orlando | G18: F | H18: A12001 - Inventory (GV LLC) (New) : Inventory (New) | I18: 33565/10 | J18: LA QUINTA ORLANDOImport July 25 cogs for materials from SPS to Netsuite | K18: LA QUINTA ORLANDOImport July 25 cogs for materials from SPS to Netsuite | L18: 893.18
B19: Journal | C19: 45839 | D19: JE998 | F19: Magnolia LXR Dallas TX - | G19: F | H19: A12001 - Inventory (GV LLC) (New) : Inventory (New) | I19: 33495/7 | J19: Magnolia LXR Dallas TX -Import July 25 cogs for materials from SPS to Netsuite | K19: Magnolia LXR Dallas TX -Import July 25 cogs for materials from SPS to Netsuite | L19: 3554.96
B20: Journal | C20: 45839 | D20: JE1002 | F20: La Quinta, Anaheim CA | G20: F | H20: A12001 - Inventory (GV LLC) (New) : Inventory (New) | I20: 34113/2 | J20: La Quinta, Anaheim CAImport July 25 cogs for materials from SPS to Netsuite | K20: La Quinta, Anaheim CAImport July 25 cogs for materials from SPS to Netsuite | L20: 980.95
B21: Journal | C21: 45839 | D21: JE1823 | F21: La Quinta Inn & Suites - Seatac Airport - Seattle WA | G21: F | H21: A12001 - Inventory (GV LLC) (New) : Inventory (New) | I21: 33555 | J21: La Quinta Inn & Suites- Seatac Airport- Seattle WAImport July 25 cogs for materials from SPS to Netsuite | K21: La Quinta Inn & Suites- Seatac Airport- Seattle WAImport July 25 cogs for materials from SPS to Netsuite | L21: 10748.91
B22: Journal | C22: 45839 | D22: JE1830 | F22: CANDLEWOOD LAFAYETTE | G22: F | H22: A12001 - Inventory (GV LLC) (New) : Inventory (New) | I22: 33984 | J22: CANDLEWOOD LAFAYETTEImport July 25 cogs for materials from SPS to Netsuite | K22: CANDLEWOOD LAFAYETTEImport July 25 cogs for materials from SPS to Netsuite | L22: 345
B23: Journal | C23: 45839 | D23: JE1006 | F23: Graniti Vicentia | G23: F | H23: A12001 - Inventory (GV LLC) (New) : Inventory (New) | I23: 36158 | J23: Graniti VicentiaImport July 25 cogs for materials from SPS to Netsuite | K23: Graniti VicentiaImport July 25 cogs for materials from SPS to Netsuite | L23: 1277.06
B24: Journal | C24: 45839 | D24: JE995 | F24: Magnolia LXR Dallas TX - | G24: F | H24: A12001 - Inventory (GV LLC) (New) : Inventory (New) | I24: 31647 | J24: Import July 25 cogs for materials from SPS to Netsuite | K24: Import July 25 cogs for materials from SPS to Netsuite | L24: 78.61
B25: Journal | C25: 45839 | D25: JE1003 | F25: LaQuinta Yakima WA | G25: F | H25: A12001 - Inventory (GV LLC) (New) : Inventory (New) | I25: 34289/3 | J25: LaQuinta Yakima WAImport July 25 cogs for materials from SPS to Netsuite | K25: LaQuinta Yakima WAImport July 25 cogs for materials from SPS to Netsuite | L25: 541.7
B26: Journal | C26: 45839 | D26: JE1010 | F26: ELEMENT FORTSMITH, ARKANSAS | G26: F | H26: A12001 - Inventory (GV LLC) (New) : Inventory (New) | I26: 37759/3 | J26: ELEMENT FORTSMITH, ARKANSASImport July 25 cogs for materials from SPS to Netsuite | K26: ELEMENT FORTSMITH, ARKANSASImport July 25 cogs for materials from SPS to Netsuite | L26: 8127.55
... B31: Journal | C31: 45839 | D31: JE1004 | F31: LaQuinta Inn & Suites Oxford AL | G31: F | H31: A12001 - Inventory (GV LLC) (New) : Inventory (New) | I31: 34967 | J31: LaQuinta Inn & Suites Oxford ALImport July 25 cogs for materials from SPS to Netsuite | K31: LaQuinta Inn & Suites Oxford ALImport July 25 cogs for materials from SPS to Netsuite | L31: 3300.55
B32: Bill | C32: 45842 | D32: 45812//SR173-5TPM// CAXU9054830 | E32: Richwood Hospitality Co. LTD | F32: - No Entity - | G32: F | H32: 20000 - Accounts Payable | J32: LM-MW-7T.C Quartz Top @ Restore Cabinet | K32: CAXU9054830 | L32: 240.9
B33: Bill | C33: 45842 | D33: 45812//SR173-5TPM// CAXU9054830 | E33: Richwood Hospitality Co. LTD | F33: - No Entity - | G33: F | H33: 20000 - Accounts Payable | J33: LM-MW-9.3.C Quartz Top @ Bar Back Wall Cabinet | K33: CAXU9054830 | L33: 1391.5
B34: Journal | C34: 45845 | D34: JE1019 | F34: Auburn Hospitality Group | G34: F | H34: A12001 - Inventory (GV LLC) (New) : Inventory (New) | I34: 38382/3 | J34: Auburn Hospitality GroupImport July 25 cogs for materials from SPS to Netsuite | K34: Auburn Hospitality GroupImport July 25 cogs for materials from SPS to Netsuite | L34: 207.44
B35: Journal | C35: 45845 | D35: JE1017 | F35: Fairfield Townplace East Hartford | G35: F | H35: A12001 - Inventory (GV LLC) (New) : Inventory (New) | I35: 37579/2 | J35: Fairfield Townplace East HartfordImport July 25 cogs for materials from SPS to Netsuite | K35: Fairfield Townplace East HartfordImport July 25 cogs for materials from SPS to Netsuite | L35: 358.55
B36: Journal | C36: 45845 | D36: JE1016 | F36: Fairfield Townplace East Hartford | G36: F | H36: A12001 - Inventory (GV LLC) (New) : Inventory (New) | I36: 35812 | J36: Fairfield Townplace East HartfordImport July 25 cogs for materials from SPS to Netsuite | K36: Fairfield Townplace East HartfordImport July 25 cogs for materials from SPS to Netsuite | L36: 27258.19
B37: Journal | C37: 45845 | D37: JE1015 | F37: Fairfield Townplace East Hartford | G37: F | H37: A12001 - Inventory (GV LLC) (New) : Inventory (New) | I37: 35808 | J37: Fairfield Townplace East HartfordImport July 25 cogs for materials from SPS to Netsuite | K37: Fairfield Townplace East HartfordImport July 25 cogs for materials from SPS to Netsuite | L37: 7421.01
B38: Journal | C38: 45845 | D38: JE1021 | F38: Auburn Hospitality Group | G38: F | H38: A12001 - Inventory (GV LLC) (New) : Inventory (New) | I38: 38403/3 | J38: Auburn Hospitality GroupImport July 25 cogs for materials from SPS to Netsuite | K38: Auburn Hospitality GroupImport July 25 cogs for materials from SPS to Netsuite | L38: 518.72
B39: Journal | C39: 45845 | D39: JE1023 | F39: Auburn Hospitality Group | G39: F | H39: A12001 - Inventory (GV LLC) (New) : Inventory (New) | I39: 38738 | J39: Auburn Hospitality GroupImport July 25 cogs for materials from SPS to Netsuite | K39: Auburn Hospitality GroupImport July 25 cogs for materials from SPS to Netsuite | L39: 527.46
B40: Journal | C40: 45845 | D40: JE1018 | F40: Hampton Inn Nashville | G40: F | H40: A12001 - Inventory (GV LLC) (New) : Inventory (New) | I40: 38235/4 | J40: Hampton Inn NashvilleImport July 25 cogs for materials from SPS to Netsuite | K40: Hampton Inn NashvilleImport July 25 cogs for materials from SPS to Netsuite | L40: 6139.05
B41: Journal | C41: 45845 | D41: JE1014 | F41: Fairfield Townplace East Hartford | G41: F | H41: A12001 - Inventory (GV LLC) (New) : Inventory (New) | I41: 35807 | J41: Fairfield Townplace East HartfordImport July 25 cogs for materials from SPS to Netsuite | K41: Fairfield Townplace East HartfordImport July 25 cogs for materials from SPS to Netsuite | L41: 1418.87
B42: Journal | C42: 45845 | D42: JE1020 | F42: Auburn Hospitality Group | G42: F | H42: A12001 - Inventory (GV LLC) (New) : Inventory (New) | I42: 38403/2 | J42: Auburn Hospitality GroupImport July 25 cogs for materials from SPS to Netsuite | K42: Auburn Hospitality GroupImport July 25 cogs for materials from SPS to Netsuite | L42: 570.62
B43: Journal | C43: 45845 | D43: JE1022 | F43: Auburn Hospitality Group | G43: F | H43: A12001 - Inventory (GV LLC) (New) : Inventory (New) | I43: 38403/4 | J43: Auburn Hospitality GroupImport July 25 cogs for materials from SPS to Netsuite | K43: Auburn Hospitality GroupImport July 25 cogs for materials from SPS to Netsuite | L43: 3038.69
B44: Journal | C44: 45845 | D44: JE1013 | F44: Fairfield Townplace East Hartford | G44: F | H44: A12001 - Inventory (GV LLC) (New) : Inventory (New) | I44: 35796/2 | J44: Fairfield Townplace East HartfordImport July 25 cogs for materials from SPS to Netsuite | K44: Fairfield Townplace East HartfordImport July 25 cogs for materials from SPS to Netsuite | L44: 5111.26
B45: Journal | C45: 45846 | D45: JE1024 | F45: Auburn Hospitality Group | G45: F | H45: A12001 - Inventory (GV LLC) (New) : Inventory (New) | I45: 38394/3 | J45: Auburn Hospitality GroupImport July 25 cogs for materials from SPS to Netsuite | K45: Auburn Hospitality GroupImport July 25 cogs for materials from SPS to Netsuite | L45: 6013.29
... B54: Journal | C54: 45848 | D54: JE1835 | F54: Interior Dezyn | G54: F | H54: A12001 - Inventory (GV LLC) (New) : Inventory (New) | I54: 38525/2 | J54: Interior DezynImport July 25 cogs for materials from SPS to Netsuite | K54: Interior DezynImport July 25 cogs for materials from SPS to Netsuite | L54: 2004.76
B55: Bill | C55: 45849 | D55: 25JSF05069 - 60169 - DHL# 6363160484; 4920454 | E55: Jasfer Industry Co., Limited | F55: - No Entity - | G55: F | H55: 20000 - Accounts Payable | J55: WTR @ Fireplace A&B 88.79" x 110.04 | L55: 312.8
B56: Bill | C56: 45849 | D56: 25JSF05069 - 60169 - DHL# 6363160484; 4920454 | E56: Jasfer Industry Co., Limited | F56: - No Entity - | G56: F | H56: 20000 - Accounts Payable | J56: WTR @ Employee 70.4" x 59.5" | L56: 74.75
B57: Bill | C57: 45849 | D57: 25JSF05004 - MRSU7509001 - 60021 | E57: Jasfer Industry Co., Limited | F57: - No Entity - | G57: F | H57: 20000 - Accounts Payable | J57: GR-016 LED Strip @ King Headboard | K57: Project: LQ indianapolis, SO#974 Sidemark: GV PO# 60021 | L57: 1880
B58: Bill | C58: 45849 | D58: 25JSF05069 - 60169 - DHL# 6363160484; 4920454 | E58: Jasfer Industry Co., Limited | F58: - No Entity - | G58: F | H58: 20000 - Accounts Payable | J58: WTR @ Office 67" x 84" | L58: 97.75
B59: Bill | C59: 45849 | D59: 25JSF05004 - MRSU7509001 - 60021 | E59: Jasfer Industry Co., Limited | F59: - No Entity - | G59: F | H59: 20000 - Accounts Payable | J59: GR-017 LED Strip @ Queen Headboard | K59: Project: LQ indianapolis, SO#974 Sidemark: GV PO# 60021 | L59: 2320
B60: Bill | C60: 45849 | D60: 25JSF05069 - 60169 - DHL# 6363160484; 4920454 | E60: Jasfer Industry Co., Limited | F60: - No Entity - | G60: F | H60: 20000 - Accounts Payable | J60: WTR @ Meeting room 98" x 72.6" | L60: 327.75
B61: Bill | C61: 45849 | D61: 25JSF05069 - 60169 - DHL# 6363160484; 4920454 | E61: Jasfer Industry Co., Limited | F61: - No Entity - | G61: F | H61: 20000 - Accounts Payable | J61: WTR @ Vestibule 65.27" x 102.12" | L61: 110.4
B62: Bill | C62: 45849 | D62: 25JSF05069 - 60169 - DHL# 6363160484; 4920454 | E62: Jasfer Industry Co., Limited | F62: - No Entity - | G62: F | H62: 20000 - Accounts Payable | J62: WTR @ Fitness 67.9" x 75" | L62: 276
B63: Bill | C63: 45849 | D63: 25JSF05069 - 60169 - DHL# 6363160484; 4920454 | E63: Jasfer Industry Co., Limited | F63: - No Entity - | G63: F | H63: 20000 - Accounts Payable | J63: WTR @ Den A,B,C | L63: 138
B64: Bill | C64: 45849 | D64: 25JSF05069 - 60169 - DHL# 6363160484; 4920454 | E64: Jasfer Industry Co., Limited | F64: - No Entity - | G64: F | H64: 20000 - Accounts Payable | J64: WTR @ Office 47" x 48" | L64: 138
B65: Bill | C65: 45849 | D65: 25JSF05069 - 60169 - DHL# 6363160484; 4920454 | E65: Jasfer Industry Co., Limited | F65: - No Entity - | G65: F | H65: 20000 - Accounts Payable | J65: WTR @ Lobby 63.71" x 52.80" | L65: 63.25
B66: Journal | C66: 45849 | D66: JE1034 | F66: Northlake Innkeepers I Ltd. | G66: F | H66: A12001 - Inventory (GV LLC) (New) : Inventory (New) | I66: 37288/5 | J66: Northlake Innkeepers I Ltd.Import July 25 cogs for materials from SPS to Netsuite | K66: Northlake Innkeepers I Ltd.Import July 25 cogs for materials from SPS to Netsuite | L66: 3301.16
B67: Journal | C67: 45849 | D67: JE1035 | F67: Northlake Innkeepers I Ltd. | G67: F | H67: A12001 - Inventory (GV LLC) (New) : Inventory (New) | I67: 37288/6 | J67: Northlake Innkeepers I Ltd.Import July 25 cogs for materials from SPS to Netsuite | K67: Northlake Innkeepers I Ltd.Import July 25 cogs for materials from SPS to Netsuite | L67: 1429.8
B68: Journal | C68: 45849 | D68: JE1824 | F68: Ascent Home2 Montgomery | G68: F | H68: A12001 - Inventory (GV LLC) (New) : Inventory (New) | I68: 36783/5 | J68: Ascent Home2 MontgomeryImport July 25 cogs for materials from SPS to Netsuite | K68: Ascent Home2 MontgomeryImport July 25 cogs for materials from SPS to Netsuite | L68: 6123.55
B69: Journal | C69: 45849 | D69: JE1032 | F69: DFW Joseph Investments LLC | G69: F | H69: A12001 - Inventory (GV LLC) (New) : Inventory (New) | I69: 37061/6 | J69: DFW Joseph Investments LLCImport July 25 cogs for materials from SPS to Netsuite | K69: DFW Joseph Investments LLCImport July 25 cogs for materials from SPS to Netsuite | L69: 41969.68
B70: Journal | C70: 45849 | D70: JE1033 | F70: Northlake Innkeepers I Ltd. | G70: F | H70: A12001 - Inventory (GV LLC) (New) : Inventory (New) | I70: 37271/12 | J70: Northlake Innkeepers I Ltd.Import July 25 cogs for materials from SPS to Netsuite | K70: Northlake Innkeepers I Ltd.Import July 25 cogs for materials from SPS to Netsuite | L70: 2002.92
B71: Journal | C71: 45849 | D71: JE1036 | F71: DFW Joseph Investments LLC | G71: F | H71: A12001 - Inventory (GV LLC) (New) : Inventory (New) | I71: 37762/3 | J71: DFW Joseph Investments LLCImport July 25 cogs for materials from SPS to Netsuite | K71: DFW Joseph Investments LLCImport July 25 cogs for materials from SPS to Netsuite | L71: 2299
B72: Journal | C72: 45852 | D72: JE1038 | F72: Prince Preferred Hotels | G72: F | H72: A12001 - Inventory (GV LLC) (New) : Inventory (New) | I72: 36576/2 | J72: Prince Preferred HotelsImport July 25 cogs for materials from SPS to Netsuite | K72: Prince Preferred HotelsImport July 25 cogs for materials from SPS to Netsuite | L72: 14000.89
B73: Journal | C73: 45852 | D73: JE1042 | F73: Auburn Hospitality Group | G73: F | H73: A12001 - Inventory (GV LLC) (New) : Inventory (New) | I73: 38388/2 | J73: Auburn Hospitality GroupImport July 25 cogs for materials from SPS to Netsuite | K73: Auburn Hospitality GroupImport July 25 cogs for materials from SPS to Netsuite | L73: 187888.1
B74: Journal | C74: 45852 | D74: JE1039 | F74: Prince Preferred Hotels | G74: F | H74: A12001 - Inventory (GV LLC) (New) : Inventory (New) | I74: 36580/2 | J74: Prince Preferred HotelsImport July 25 cogs for materials from SPS to Netsuite | K74: Prince Preferred HotelsImport July 25 cogs for materials from SPS to Netsuite | L74: 419.36
B75: Journal | C75: 45852 | D75: JE1040 | F75: Prince Preferred Hotels | G75: F | H75: A12001 - Inventory (GV LLC) (New) : Inventory (New) | I75: 36582/2 | J75: Prince Preferred HotelsImport July 25 cogs for materials from SPS to Netsuite | K75: Prince Preferred HotelsImport July 25 cogs for materials from SPS to Netsuite | L75: 6129.97
B76: Journal | C76: 45852 | D76: JE1041 | F76: Prince Preferred Hotels | G76: F | H76: A12001 - Inventory (GV LLC) (New) : Inventory (New) | I76: 36583/4 | J76: Prince Preferred HotelsImport July 25 cogs for materials from SPS to Netsuite | K76: Prince Preferred HotelsImport July 25 cogs for materials from SPS to Netsuite | L76: 449.8
B77: Journal | C77: 45852 | D77: JE1037 | F77: Prince Preferred Hotels | G77: F | H77: A12001 - Inventory (GV LLC) (New) : Inventory (New) | I77: 36569/2 | J77: Prince Preferred HotelsImport July 25 cogs for materials from SPS to Netsuite | K77: Prince Preferred HotelsImport July 25 cogs for materials from SPS to Netsuite | L77: 4467.28
B78: Item Receipt | C78: 45853 | D78: IR442 | E78: Cambodian Zulite Stone Co., LTD. | F78: - No Entity - | G78: F | H78: - Accrued Purchases | J78: Cost of Sales Adjustment | L78: 1738.83
B79: Item Receipt | C79: 45853 | D79: IR444 | E79: Cambodian Zulite Stone Co., LTD. | F79: - No Entity - | G79: F | H79: - Accrued Purchases | J79: Cost of Sales Adjustment | L79: -357.56
B80: Item Receipt | C80: 45853 | D80: IR443 | E80: Cambodian Zulite Stone Co., LTD. | F80: - No Entity - | G80: F | H80: - Accrued Purchases | J80: Cost of Sales Adjustment | L80: 39.87
B81: Journal | C81: 45854 | D81: JE1043 | F81: Auburn Hospitality Group | G81: F | H81: A12001 - Inventory (GV LLC) (New) : Inventory (New) | I81: 38386/3 | J81: Auburn Hospitality GroupImport July 25 cogs for materials from SPS to Netsuite | K81: Auburn Hospitality GroupImport July 25 cogs for materials from SPS to Netsuite | L81: 29426.3
B82: Journal | C82: 45854 | D82: JE1044 | F82: Auburn Hospitality Group | G82: F | H82: A12001 - Inventory (GV LLC) (New) : Inventory (New) | I82: 38394/2 | J82: Auburn Hospitality GroupImport July 25 cogs for materials from SPS to Netsuite | K82: Auburn Hospitality GroupImport July 25 cogs for materials from SPS to Netsuite | L82: 4262
B83: Journal | C83: 45856 | D83: JE1046 | F83: HEBEIVI | G83: F | H83: A12001 - Inventory (GV LLC) (New) : Inventory (New) | I83: DO24-00152 | J83: HEBEI VINCENTAA SCULPTURE ENGINEER CO LTDImport July 25 cogs for materials from SPS to Netsuite | K83: HEBEI VINCENTAA SCULPTURE ENGINEER CO LTDImport July 25 cogs for materials from SPS to Netsuite | L83: 5200
B84: Journal | C84: 45856 | D84: JE1045 | F84: Hampton Inn Nashville | G84: F | H84: A12001 - Inventory (GV LLC) (New) : Inventory (New) | I84: 38213/6 | J84: Hampton Inn NashvilleImport July 25 cogs for materials from SPS to Netsuite | K84: Hampton Inn NashvilleImport July 25 cogs for materials from SPS to Netsuite | L84: 109103.2
B85: Bill | C85: 45858 | D85: GV2025031 - 60117 - TCKU6051496_ ESDU4243886 | E85: Cambodian Zulite Stone Co., LTD. | F85: - No Entity - | G85: F | H85: 20000 - Accounts Payable | J85: PA-805.T - Quartz top on Cabinet 147" W x 25" D @ Meeting room & Banquet Hall | K85: HGI Clackamas Monarch, SO# 1124 Sidemark: PO# 60117 - PA | L85: 4281.76
B86: Bill | C86: 45858 | D86: GV2025031 - 60117 - TCKU6051496_ ESDU4243886 | E86: Cambodian Zulite Stone Co., LTD. | F86: - No Entity - | G86: F | H86: 20000 - Accounts Payable | J86: PA-600.T - Quartz top on Cabinet 84" W x 25" D @ Fitness room | K86: HGI Clackamas Monarch, SO# 1124 Sidemark: PO# 60117 - PA | L86: 226.19
B87: Bill | C87: 45858 | D87: GV2025031 - 60117 - TCKU6051496_ ESDU4243886 | E87: Cambodian Zulite Stone Co., LTD. | F87: - No Entity - | G87: F | H87: 20000 - Accounts Payable | J87: PA-321L.T - Quartz Top on ADA Vanity 113 1/2" W - Left @ First Floor Public Restroom | K87: HGI Clackamas Monarch, SO# 1124 Sidemark: PO# 60117 - PA | L87: 494.73
B88: Bill | C88: 45858 | D88: GV2025031 - 60117 - TCKU6051496_ ESDU4243886 | E88: Cambodian Zulite Stone Co., LTD. | F88: - No Entity - | G88: F | H88: 20000 - Accounts Payable | J88: PA-319.T - Quartz Top at ADA Vanity 100" W @ Corridor restroom | K88: HGI Clackamas Monarch, SO# 1124 Sidemark: PO# 60117 - PA | L88: 437.89
B89: Bill | C89: 45858 | D89: GV2025031 - 60117 - TCKU6051496_ ESDU4243886 | E89: Cambodian Zulite Stone Co., LTD. | F89: - No Entity - | G89: F | H89: 20000 - Accounts Payable | J89: PA-802.T.1 - Quartz top on Registration Desk 46" W x 28" D @ Lobby | K89: HGI Clackamas Monarch, SO# 1124 Sidemark: PO# 60117 - PA | L89: 279.94
B90: Bill | C90: 45858 | D90: GV2025031 - 60117 - TCKU6051496_ ESDU4243886 | E90: Cambodian Zulite Stone Co., LTD. | F90: - No Entity - | G90: F | H90: 20000 - Accounts Payable | J90: PA-801.1T Quartz Top on Retail Millwork Island @ Lobby | K90: HGI Clackamas Monarch, SO# 1124 Sidemark: PO# 60117 - PA | L90: 530.97
B91: Bill | C91: 45858 | D91: GV2025031 - 60117 - TCKU6051496_ ESDU4243886 | E91: Cambodian Zulite Stone Co., LTD. | F91: - No Entity - | G91: F | H91: 20000 - Accounts Payable | J91: PA-800.T - Quartz top on Cabinet 84" W x 17" D @ Conference | K91: HGI Clackamas Monarch, SO# 1124 Sidemark: PO# 60117 - PA | L91: 220.97
B92: Bill | C92: 45858 | D92: GV2025031 - 60117 - TCKU6051496_ ESDU4243886 | E92: Cambodian Zulite Stone Co., LTD. | F92: - No Entity - | G92: F | H92: 20000 - Accounts Payable | J92: PA-313.T - Quartz Top at ADA Vanity 84" W @ Lower Level Public Restroom | K92: HGI Clackamas Monarch, SO# 1124 Sidemark: PO# 60117 - PA | L92: 1126.65
B93: Bill | C93: 45858 | D93: GV2025031 - 60117 - TCKU6051496_ ESDU4243886 | E93: Cambodian Zulite Stone Co., LTD. | F93: - No Entity - | G93: F | H93: 20000 - Accounts Payable | J93: PA-806.T - Quartz top on Print station 86"W x 24" D @ Lobby | K93: HGI Clackamas Monarch, SO# 1124 Sidemark: PO# 60117 - PA | L93: 258.87
B94: Bill | C94: 45858 | D94: GV2025031 - 60117 - TCKU6051496_ ESDU4243886 | E94: Cambodian Zulite Stone Co., LTD. | F94: - No Entity - | G94: F | H94: 20000 - Accounts Payable | J94: PA-320.T - Quartz Top on ADA Vanity36"W @ Pool shower room | K94: HGI Clackamas Monarch, SO# 1124 Sidemark: PO# 60117 - PA | L94: 175.97
B95: Bill | C95: 45858 | D95: GV2025031 - 60117 - TCKU6051496_ ESDU4243886 | E95: Cambodian Zulite Stone Co., LTD. | F95: - No Entity - | G95: F | H95: 20000 - Accounts Payable | J95: PA-302.T - Quartz Top on Coffee table metale base circular dia 24" @ Lobby | K95: HGI Clackamas Monarch, SO# 1124 Sidemark: PO# 60117 - PA | L95: 186.12
B96: Bill | C96: 45858 | D96: GV2025031 - 60117 - TCKU6051496_ ESDU4243886 | E96: Cambodian Zulite Stone Co., LTD. | F96: - No Entity - | G96: F | H96: 20000 - Accounts Payable | J96: PA-312.T - Quartz Top at ADA Vanity 72" W @ Lower Level Public Restroom | K96: HGI Clackamas Monarch, SO# 1124 Sidemark: PO# 60117 - PA | L96: 327.06
... B100: Bill | C100: 45858 | D100: GV2025031 - 60117 - TCKU6051496_ ESDU4243886 | E100: Cambodian Zulite Stone Co., LTD. | F100: - No Entity - | G100: F | H100: 20000 - Accounts Payable | J100: PA-802.T.2 - Quartz top on Registration Desk 166" W x 42" D @ Lobby | K100: HGI Clackamas Monarch, SO# 1124 Sidemark: PO# 60117 - PA | L100: 786.65
B101: Journal | C101: 45861 | D101: JE1825 | F101: Ascent Home2 Montgomery | G101: F | H101: A12001 - Inventory (GV LLC) (New) : Inventory (New) | I101: 37090/2 | J101: Ascent Home2 MontgomeryImport July 25 cogs for materials from SPS to Netsuite | K101: Ascent Home2 MontgomeryImport July 25 cogs for materials from SPS to Netsuite | L101: 32.18
B102: Journal | C102: 45861 | D102: JE1047 | F102: Jasfer Industry Co., Limited | G102: F | H102: A12001 - Inventory (GV LLC) (New) : Inventory (New) | I102: 45839 | J102: Jasfer Industry Co., LimitedImport July 25 cogs for materials from SPS to Netsuite | K102: Jasfer Industry Co., LimitedImport July 25 cogs for materials from SPS to Netsuite | L102: 19568.12
B103: Journal | C103: 45862 | D103: JE1048 | F103: Ascent Residence inn Montgomery | G103: F | H103: A12001 - Inventory (GV LLC) (New) : Inventory (New) | I103: 37678/6 | J103: Ascent Residence inn MontgomeryImport July 25 cogs for materials from SPS to Netsuite | K103: Ascent Residence inn MontgomeryImport July 25 cogs for materials from SPS to Netsuite | L103: 32463.58
B104: Journal | C104: 45863 | D104: JE1049 | F104: Chesterfield Hospitality, Inc. | G104: F | H104: A12001 - Inventory (GV LLC) (New) : Inventory (New) | I104: 38301/3 | J104: Chesterfield Hospitality Inc.Import July 25 cogs for materials from SPS to Netsuite | K104: Chesterfield Hospitality Inc.Import July 25 cogs for materials from SPS to Netsuite | L104: 8893.7
B105: Journal | C105: 45863 | D105: JE1051 | F105: Residence Inn Pearland, TX | G105: F | H105: A12001 - Inventory (GV LLC) (New) : Inventory (New) | I105: 38332 | J105: Residence Inn Pearland, TXImport July 25 cogs for materials from SPS to Netsuite | K105: Residence Inn Pearland, TXImport July 25 cogs for materials from SPS to Netsuite | L105: 7741.34
B106: Journal | C106: 45863 | D106: JE1050 | F106: Chesterfield Hospitality, Inc. | G106: F | H106: A12001 - Inventory (GV LLC) (New) : Inventory (New) | I106: 38304/2 | J106: Chesterfield Hospitality Inc.Import July 25 cogs for materials from SPS to Netsuite | K106: Chesterfield Hospitality Inc.Import July 25 cogs for materials from SPS to Netsuite | L106: 2033.83
B107: Journal | C107: 45864 | D107: JE1052 | F107: Chesterfield Hospitality, Inc. | G107: F | H107: A12001 - Inventory (GV LLC) (New) : Inventory (New) | I107: 38299/2 | J107: Chesterfield Hospitality Inc.Import July 25 cogs for materials from SPS to Netsuite | K107: Chesterfield Hospitality Inc.Import July 25 cogs for materials from SPS to Netsuite | L107: 2336.64
B108: Journal | C108: 45864 | D108: JE1054 | F108: Chesterfield Hospitality, Inc. | G108: F | H108: A12001 - Inventory (GV LLC) (New) : Inventory (New) | I108: 38305/6 | J108: Chesterfield Hospitality Inc.Import July 25 cogs for materials from SPS to Netsuite | K108: Chesterfield Hospitality Inc.Import July 25 cogs for materials from SPS to Netsuite | L108: 3461.21
B109: Journal | C109: 45864 | D109: JE1053 | F109: Chesterfield Hospitality, Inc. | G109: F | H109: A12001 - Inventory (GV LLC) (New) : Inventory (New) | I109: 38305/4 | J109: Chesterfield Hospitality Inc.Import July 25 cogs for materials from SPS to Netsuite | K109: Chesterfield Hospitality Inc.Import July 25 cogs for materials from SPS to Netsuite | L109: 9337.12
B110: Journal | C110: 45864 | D110: JE1055 | F110: Residence Inn Pearland, TX | G110: F | H110: A12001 - Inventory (GV LLC) (New) : Inventory (New) | I110: 38325/5 | J110: Residence Inn Pearland, TXImport July 25 cogs for materials from SPS to Netsuite | K110: Residence Inn Pearland, TXImport July 25 cogs for materials from SPS to Netsuite | L110: 1118.6
B111: Journal | C111: 45868 | D111: JE1058 | F111: Prince Preferred Hotels | G111: F | H111: A12001 - Inventory (GV LLC) (New) : Inventory (New) | I111: 36568/2 | J111: Prince Preferred HotelsImport July 25 cogs for materials from SPS to Netsuite | K111: Prince Preferred HotelsImport July 25 cogs for materials from SPS to Netsuite | L111: 6756.13
B112: Journal | C112: 45868 | D112: JE1063 | F112: Prince Preferred Hotels | G112: F | H112: A12001 - Inventory (GV LLC) (New) : Inventory (New) | I112: 36581 | J112: Prince Preferred HotelsImport July 25 cogs for materials from SPS to Netsuite | K112: Prince Preferred HotelsImport July 25 cogs for materials from SPS to Netsuite | L112: 2749.82
... B149: Journal | C149: 45869 | D149: JE1074 | F149: Fairfield Townplace East Hartford | G149: F | H149: A12001 - Inventory (GV LLC) (New) : Inventory (New) | I149: 37239 | J149: Fairfield Townplace East HartfordImport July 25 cogs for materials from SPS to Netsuite | K149: Fairfield Townplace East HartfordImport July 25 cogs for materials from SPS to Netsuite | L149: 40121.46
A150: Total - A50001 - Cost Of Goods Sold (New) | L150: =SUM(L12:L149) -> 2639865.6
A151: Total - A50000 - Cost of Goods Sales 50 (GV LLC) (New) | L151: =SUM(L150) -> 2639865.6
A152: Total - Cost Of Sales | L152: =SUM(L151) -> 2639865.6
...

Sheet tab 5 Nsuite Aug income statemn
A1: Graniti Vicentia, L.L.C.
A2: Parent Company : Graniti Vicentia LLC
A3: Graniti - Income Statement Detail
A4: Aug 2025
A6: Options: Activity Only
A7: Financial Row | B7: Type | C7: Date | D7: Document Number | E7: Name | F7: Entity (Line) | G7: Clr | H7: Split | I7: Reference No. | J7: Description | K7: Memo | L7: Amount
A8: Ordinary Income/Expense
A9: Cost Of Sales
A10: A50000 - Cost of Goods Sales 50 (GV LLC) (New)
A11: A50001 - Cost Of Goods Sold (New)
B12: Bill | C12: 45870 | D12: BILL_30207 | E12: MirageGranitoCeramico S.p.A | F12: - No Entity - | G12: F | H12: A20001 - Accounts Payable (GV LLC) (New) : Accounts Payable Suppliers & Vendors (New) | J12: Cost of Sales Adjustment | K12: 266/VE - Import SPS data by Invoice in NetSuite | L12: 371.07 | N12: 0
B13: Bill | C13: 45870 | D13: BILL_30208 | E13: MirageGranitoCeramico S.p.A | F13: - No Entity - | G13: F | H13: A20001 - Accounts Payable (GV LLC) (New) : Accounts Payable Suppliers & Vendors (New) | J13: Cost of Sales Adjustment | K13: 266/VE - Import SPS data by Invoice in NetSuite | L13: 6649.38 | N13: Type
B14: Bill | C14: 45870 | D14: BILL_30206 | E14: MirageGranitoCeramico S.p.A | F14: - No Entity - | G14: F | H14: A20001 - Accounts Payable (GV LLC) (New) : Accounts Payable Suppliers & Vendors (New) | J14: Cost of Sales Adjustment | K14: 266/VE - Import SPS data by Invoice in NetSuite | L14: 6350.4 | N14: Bill | O14: =SUMIF(B:B,N14,L:L) -> 30883.73
B15: Bill | C15: 45870 | D15: BILL_30205 | E15: MirageGranitoCeramico S.p.A | F15: - No Entity - | G15: F | H15: A20001 - Accounts Payable (GV LLC) (New) : Accounts Payable Suppliers & Vendors (New) | J15: Cost of Sales Adjustment | K15: 266/VE - Import SPS data by Invoice in NetSuite | L15: 346.32 | N15: Bill Credit | O15: =SUMIF(B:B,N15,L:L) -> -997.93
B16: Bill Credit | C16: 45870 | D16: Credit-1 | E16: MirageGranitoCeramico S.p.A | F16: - No Entity - | G16: F | H16: 20000 - Accounts Payable | J16: apply this one to PO42868 | L16: -924.6 | N16: Journal | O16: =SUMIF(B:B,N16,L:L) -> 6878885.8
B17: Bill Credit | C17: 45870 | D17: Credit-2 | E17: MirageGranitoCeramico S.p.A | F17: - No Entity - | G17: F | H17: 20000 - Accounts Payable | L17: -73.33 | N17: Item Fulfillment | O17: =SUMIF(B:B,N17,L:L) -> 13764.53
B18: Journal | C18: 45870 | D18: JE1844 | F18: Ascent Residence inn Montgomery | G18: F | H18: A12001 - Inventory (GV LLC) (New) : Inventory (New) | I18: 37684/3 | J18: Ascent Residence inn Montgomery - Aug material cost transferred from sps | K18: Ascent Residence inn Montgomery - Aug material cost transferred from sps | L18: 45093.1 | N18: Item Receipt | O18: =SUMIF(B:B,N18,L:L) -> 21613.28
B19: Journal | C19: 45870 | D19: JE1845 | F19: MDC Interior Solutions | G19: F | H19: A12001 - Inventory (GV LLC) (New) : Inventory (New) | I19: 41188101 | J19: MDC Interior Solutions - Aug material cost transferred from sps | K19: MDC Interior Solutions - Aug material cost transferred from sps | L19: 113.4
B20: Item Fulfillment | C20: 45873 | D20: IF367 | E20: Ascent Hospitality Management Co | F20: Ascent Hospitality Management Co | G20: F | H20: A12001 - Inventory (GV LLC) (New) : Inventory (New) | J20: Cost of Sales | L20: 3703.47
B21: Journal | C21: 45873 | D21: JE1846 | F21: Fairfield Townplace East Hartford | G21: F | H21: A12001 - Inventory (GV LLC) (New) : Inventory (New) | I21: 35804/4 | J21: Fairfield Townplace East Hartford - Aug material cost transferred from sps | K21: Fairfield Townplace East Hartford - Aug material cost transferred from sps | L21: 21564.59
B22: Journal | C22: 45873 | D22: JE1847 | F22: Classic American Homes & Renovations | G22: F | H22: A12001 - Inventory (GV LLC) (New) : Inventory (New) | I22: 38633 | J22: Classic American Homes & Renovations - Aug material cost transferred from sps | K22: Classic American Homes & Renovations - Aug material cost transferred from sps | L22: 996.55
B23: Bill | C23: 45874 | D23: 19542/VE | E23: MirageGranitoCeramico S.p.A | F23: - No Entity - | G23: F | H23: A20001 - Accounts Payable (GV LLC) (New) : Accounts Payable Suppliers & Vendors (New) | J23: Cost of Sales Adjustment | K23: Import SPS data by Invoice in NetSuite | L23: 2116.8
B24: Journal | C24: 45874 | D24: JE1849 | F24: Chesterfield Hospitality, Inc. | G24: F | H24: A12001 - Inventory (GV LLC) (New) : Inventory (New) | I24: 38299/3 | J24: Chesterfield Hospitality, Inc. - Aug material cost transferred from sps | K24: Chesterfield Hospitality, Inc. - Aug material cost transferred from sps | L24: 11730.06
B25: Journal | C25: 45874 | D25: JE1850 | F25: Chesterfield Hospitality, Inc. | G25: F | H25: A12001 - Inventory (GV LLC) (New) : Inventory (New) | I25: 38301/4 | J25: Chesterfield Hospitality, Inc. - Aug material cost transferred from sps | K25: Chesterfield Hospitality, Inc. - Aug material cost transferred from sps | L25: 7314.78
B26: Journal | C26: 45874 | D26: JE1848 | F26: Hampton Inn Nashville | G26: F | H26: A12001 - Inventory (GV LLC) (New) : Inventory (New) | I26: 38235/6 | J26: Hampton Inn Nashville - Aug material cost transferred from sps | K26: Hampton Inn Nashville - Aug material cost transferred from sps | L26: 14077.81
B27: Journal | C27: 45874 | D27: JE1851 | F27: Chesterfield Hospitality, Inc. | G27: F | H27: A12001 - Inventory (GV LLC) (New) : Inventory (New) | I27: 38304/3 | J27: Chesterfield Hospitality, Inc. - Aug material cost transferred from sps | K27: Chesterfield Hospitality, Inc. - Aug material cost transferred from sps | L27: 1256.79
B28: Item Fulfillment | C28: 45875 | D28: IF279 | E28: Umang patel | F28: Umang patel | G28: F | H28: A12001 - Inventory (GV LLC) (New) : Inventory (New) | J28: Cost of Sales | L28: 3965.73
B29: Item Fulfillment | C29: 45876 | D29: IF280 | E29: SKIMS Retail | F29: SKIMS Retail | G29: F | H29: A12001 - Inventory (GV LLC) (New) : Inventory (New) | J29: Cost of Sales | L29: 6095.33
B30: Journal | C30: 45876 | D30: JE1853 | F30: Ascent Residence inn Montgomery | G30: F | H30: A12001 - Inventory (GV LLC) (New) : Inventory (New) | I30: 37697/3 | J30: Ascent Residence inn Montgomery - Aug material cost transferred from sps | K30: Ascent Residence inn Montgomery - Aug material cost transferred from sps | L30: 708.57
B31: Journal | C31: 45876 | D31: JE1854 | F31: Comfort Suites NC330 | G31: F | H31: A12001 - Inventory (GV LLC) (New) : Inventory (New) | I31: 38661 | J31: Comfort suites NC330 - Aug material cost transferred from sps | K31: Comfort suites NC330 - Aug material cost transferred from sps | L31: 2966.73
B32: Journal | C32: 45876 | D32: JE1852 | F32: Ascent Residence inn Montgomery | G32: F | H32: A12001 - Inventory (GV LLC) (New) : Inventory (New) | I32: 37687 | J32: Ascent Residence inn Montgomery - Aug material cost transferred from sps | K32: Ascent Residence inn Montgomery - Aug material cost transferred from sps | L32: 222.07
B33: Journal | C33: 45877 | D33: JE1855 | F33: Kings Bay Coastal Hotel Management LLC / Wingate Kingsland | G33: F | H33: A12001 - Inventory (GV LLC) (New) : Inventory (New) | I33: 36248 | J33: Kings Bay Coastal Hotel Management LLC / Wingate Kingsland - Aug material cost transferred from sps | K33: Kings Bay Coastal Hotel Management LLC / Wingate Kingsland - Aug material cost transferred from sps | L33: 20
B34: Journal | C34: 45877 | D34: JE1858 | F34: Veranda Homes | G34: F | H34: A12001 - Inventory (GV LLC) (New) : Inventory (New) | I34: 38292 | J34: Veranda Homes - Aug material cost transferred from sps | K34: Veranda Homes - Aug material cost transferred from sps | L34: 24766.76
B35: Journal | C35: 45877 | D35: JE1857 | F35: Ascent Hospitality Element Carmel Indiana | G35: F | H35: A12001 - Inventory (GV LLC) (New) : Inventory (New) | I35: 37412/2 | J35: Ascent Hospitality Element Carmel Indiana - Aug material cost transferred from sps | K35: Ascent Hospitality Element Carmel Indiana - Aug material cost transferred from sps | L35: 708.08
B36: Journal | C36: 45877 | D36: JE1859 | F36: Veranda Homes | G36: F | H36: A12001 - Inventory (GV LLC) (New) : Inventory (New) | I36: 38292/2 | J36: Veranda Homes - Aug material cost transferred from sps | K36: Veranda Homes - Aug material cost transferred from sps | L36: 9768.7
B37: Journal | C37: 45877 | D37: JE1856 | F37: Kings Bay Coastal Hotel Management LLC / Wingate Kingsland | G37: F | H37: A12001 - Inventory (GV LLC) (New) : Inventory (New) | I37: 36250 | J37: Kings Bay Coastal Hotel Management LLC / Wingate Kingsland - Aug material cost transferred from sps | K37: Kings Bay Coastal Hotel Management LLC / Wingate Kingsland - Aug material cost transferred from sps | L37: 7206.63
B38: Journal | C38: 45880 | D38: JE3155 | F38: HOME2 SOMERSET | G38: F | H38: A12001 - Inventory (GV LLC) (New) : Inventory (New) | I38: 38260 | J38: HOME2 SOMERSET - Aug material cost transferred from sps | K38: HOME2 SOMERSET - Aug material cost transferred from sps | L38: 6467.32
B39: Journal | C39: 45880 | D39: JE1861 | F39: Mesquite Gaming | G39: F | H39: A12001 - Inventory (GV LLC) (New) : Inventory (New) | I39: 38579 | J39: Mesquite Gaming - Aug material cost transferred from sps | K39: Mesquite Gaming - Aug material cost transferred from sps | L39: 990.31
B40: Journal | C40: 45880 | D40: JE3154 | F40: HOME2 SOMERSET | G40: F | H40: A12001 - Inventory (GV LLC) (New) : Inventory (New) | I40: 38259 | J40: HOME2 SOMERSET - Aug material cost transferred from sps | K40: HOME2 SOMERSET - Aug material cost transferred from sps | L40: 365.65
B41: Journal | C41: 45880 | D41: JE1860 | F41: Ascent Hospitality Tribute Carmel Indiana | G41: F | H41: A12001 - Inventory (GV LLC) (New) : Inventory (New) | I41: 36663/2 | J41: Ascent Hospitality Tribute Carmel Indiana - Aug material cost transferred from sps | K41: Ascent Hospitality Tribute Carmel Indiana - Aug material cost transferred from sps | L41: 566.78
B42: Bill | C42: 45881 | D42: 60104 - TCNU5700574 | E42: Jasfer Industry Co., Limited | F42: - No Entity - | G42: F | H42: 20000 - Accounts Payable | J42: PA-311 - Dining Table Artie Marra T301 @ Outdoor Pool Area | K42: HGI Clackamas Monarch, SO# 1124 Sidemark: PO# 60104 - PA | L42: 1050
B43: Bill | C43: 45881 | D43: 60190 - 25JSF04054 - TCNU5700574 | E43: Jasfer Industry Co., Limited | F43: - No Entity - | G43: F | H43: 20000 - Accounts Payable | J43: PA-003 Metal brise soleil @ Lobby | K43: HGI Clackamas Monarch, SO# 1124 Sidemark: PO# 60190 - PA | L43: 1680
B44: Bill | C44: 45881 | D44: 60190 - 25JSF04054 - TCNU5700574 | E44: Jasfer Industry Co., Limited | F44: - No Entity - | G44: F | H44: 20000 - Accounts Payable | J44: PA-002 Wooden Slats @ Lobby | K44: HGI Clackamas Monarch, SO# 1124 Sidemark: PO# 60190 - PA | L44: 730
B45: Bill | C45: 45881 | D45: 60175 - 25AR060501 - TCNU5700574 | E45: Jasfer Industry Co., Limited | F45: - No Entity - | G45: F | H45: 20000 - Accounts Payable | J45: PA-114 - Artie Garden Muses Single Sofa A369A-4 @ Outdoor Pool Area | K45: HGI Clackamas Monarch, SO# 1124 Sidemark: PO# 60175 - PA | L45: 2026.46
B46: Bill | C46: 45881 | D46: 60175 - 25AR060501 - TCNU5700574 | E46: Jasfer Industry Co., Limited | F46: - No Entity - | G46: F | H46: 20000 - Accounts Payable | J46: PA-112 - Sun Lounger Artie Garden L423 Reyne lounge @ Outdoor Pool Area | K46: HGI Clackamas Monarch, SO# 1124 Sidemark: PO# 60175 - PA | L46: 6579.14
B47: Bill | C47: 45881 | D47: 60175 - 25AR060501 - TCNU5700574 | E47: Jasfer Industry Co., Limited | F47: - No Entity - | G47: F | H47: 20000 - Accounts Payable | J47: PA-113 - Dining Chair Artie Garden Reyne C423F @ Outdoor Pool Area | K47: HGI Clackamas Monarch, SO# 1124 Sidemark: PO# 60175 - PA | L47: 2360.16
B48: Bill | C48: 45881 | D48: 60104 - TCNU5700574 | E48: Jasfer Industry Co., Limited | F48: - No Entity - | G48: F | H48: 20000 - Accounts Payable | J48: PA-310 - Side Table T242 Artie @ Outdoor Pool Area | K48: HGI Clackamas Monarch, SO# 1124 Sidemark: PO# 60104 - PA | L48: 624
B49: Journal | C49: 45881 | D49: JE3156 | F49: HOME2 SOMERSET | G49: F | H49: A12001 - Inventory (GV LLC) (New) : Inventory (New) | I49: 38251/3 | J49: HOME2 SOMERSET - Aug material cost transferred from sps | K49: HOME2 SOMERSET - Aug material cost transferred from sps | L49: 7343.21
B50: Journal | C50: 45881 | D50: JE1863 | F50: Ascent Hospitality Tribute Carmel Indiana | G50: F | H50: A12001 - Inventory (GV LLC) (New) : Inventory (New) | I50: 36681/9 | J50: Ascent Hospitality Tribute Carmel Indiana - Aug material cost transferred from sps | K50: Ascent Hospitality Tribute Carmel Indiana - Aug material cost transferred from sps | L50: 2222.38
B51: Journal | C51: 45881 | D51: JE1864 | F51: Ascent Home2 Montgomery | G51: F | H51: A12001 - Inventory (GV LLC) (New) : Inventory (New) | I51: 36782/2 | J51: Ascent Home2 Montgomery - Aug material cost transferred from sps | K51: Ascent Home2 Montgomery - Aug material cost transferred from sps | L51: 838.15
B52: Journal | C52: 45881 | D52: JE1871 | F52: Ascent Residence inn Montgomery | G52: F | H52: A12001 - Inventory (GV LLC) (New) : Inventory (New) | I52: 37683/10 | J52: Ascent Residence inn Montgomery - Aug material cost transferred from sps | K52: Ascent Residence inn Montgomery - Aug material cost transferred from sps | L52: 29639.67
B53: Journal | C53: 45881 | D53: JE1867 | F53: Ascent Residence inn Montgomery | G53: F | H53: A12001 - Inventory (GV LLC) (New) : Inventory (New) | I53: 37676/4 | J53: Ascent Residence inn Montgomery - Aug material cost transferred from sps | K53: Ascent Residence inn Montgomery - Aug material cost transferred from sps | L53: 20317.56
B54: Journal | C54: 45881 | D54: JE1866 | F54: Ascent Home2 Montgomery | G54: F | H54: A12001 - Inventory (GV LLC) (New) : Inventory (New) | I54: 36786/3 | J54: Ascent Home2 Montgomery - Aug material cost transferred from sps | K54: Ascent Home2 Montgomery - Aug material cost transferred from sps | L54: 9522.39
B55: Journal | C55: 45881 | D55: JE1862 | F55: Ascent Hospitality Tribute Carmel Indiana | G55: F | H55: A12001 - Inventory (GV LLC) (New) : Inventory (New) | I55: 36681/10 | J55: Ascent Hospitality Tribute Carmel Indiana - Aug material cost transferred from sps | K55: Ascent Hospitality Tribute Carmel Indiana - Aug material cost transferred from sps | L55: 147.48
B56: Journal | C56: 45881 | D56: JE3159 | F56: HOME2 SOMERSET | G56: F | H56: A12001 - Inventory (GV LLC) (New) : Inventory (New) | I56: 38253/2 | J56: HOME2 SOMERSET - Aug material cost transferred from sps | K56: HOME2 SOMERSET - Aug material cost transferred from sps | L56: 17550.43
B57: Journal | C57: 45881 | D57: JE1869 | F57: Ascent Residence inn Montgomery | G57: F | H57: A12001 - Inventory (GV LLC) (New) : Inventory (New) | I57: 37678/3 | J57: Ascent Residence inn Montgomery - Aug material cost transferred from sps | K57: Ascent Residence inn Montgomery - Aug material cost transferred from sps | L57: 1232.29
B58: Journal | C58: 45881 | D58: JE3162 | F58: HOME2 SOMERSET | G58: F | H58: A12001 - Inventory (GV LLC) (New) : Inventory (New) | I58: 38268 | J58: HOME2 SOMERSET - Aug material cost transferred from sps | K58: HOME2 SOMERSET - Aug material cost transferred from sps | L58: 427.87
B59: Journal | C59: 45881 | D59: JE3158 | F59: HOME2 SOMERSET | G59: F | H59: A12001 - Inventory (GV LLC) (New) : Inventory (New) | I59: 38252/2 | J59: HOME2 SOMERSET - Aug material cost transferred from sps | K59: HOME2 SOMERSET - Aug material cost transferred from sps | L59: 6729.76
B60: Journal | C60: 45881 | D60: JE1872 | F60: Ascent Residence inn Montgomery | G60: F | H60: A12001 - Inventory (GV LLC) (New) : Inventory (New) | I60: 37683/9 | J60: Ascent Residence inn Montgomery - Aug material cost transferred from sps | K60: Ascent Residence inn Montgomery - Aug material cost transferred from sps | L60: 1750.49
... B78: Journal | C78: 45890 | D78: JE1883 | F78: Fairfield Townplace East Hartford | G78: F | H78: A12001 - Inventory (GV LLC) (New) : Inventory (New) | I78: 35795/2 | J78: Fairfield Townplace East Hartford - Aug material cost transferred from sps | K78: Fairfield Townplace East Hartford - Aug material cost transferred from sps | L78: 33567.36
B79: Item Receipt | C79: 45892 | D79: IR658 | E79: Jasfer Industry Co., Limited | F79: - No Entity - | G79: F | H79: - Accrued Purchases | J79: Cost of Sales Adjustment | L79: 21613.28
B80: Journal | C80: 45892 | D80: JE1884 | F80: Auburn Hospitality Group | G80: F | H80: A12001 - Inventory (GV LLC) (New) : Inventory (New) | I80: 38403/5 | J80: Auburn Hospitality Group - Aug material cost transferred from sps | K80: Auburn Hospitality Group - Aug material cost transferred from sps | L80: 34804.4
B81: Journal | C81: 45894 | D81: JE1891 | F81: La Quinta Orlando | G81: F | H81: A12001 - Inventory (GV LLC) (New) : Inventory (New) | I81: 33571 | J81: LA QUINTA ORLANDO - Aug material cost transferred from sps | K81: LA QUINTA ORLANDO - Aug material cost transferred from sps | L81: 1368.69
B82: Journal | C82: 45894 | D82: JE1890 | F82: La Quinta Orlando | G82: F | H82: A12001 - Inventory (GV LLC) (New) : Inventory (New) | I82: 33569/5 | J82: LA QUINTA ORLANDO - Aug material cost transferred from sps | K82: LA QUINTA ORLANDO - Aug material cost transferred from sps | L82: 35534.57
B83: Journal | C83: 45894 | D83: JE1893 | F83: La Quinta Orlando | G83: F | H83: A12001 - Inventory (GV LLC) (New) : Inventory (New) | I83: 33945/4 | J83: LA QUINTA ORLANDO - Aug material cost transferred from sps | K83: LA QUINTA ORLANDO - Aug material cost transferred from sps | L83: 736.03
B84: Journal | C84: 45894 | D84: JE1899 | F84: La Quinta Orlando | G84: F | H84: A12001 - Inventory (GV LLC) (New) : Inventory (New) | I84: 33951/6 | J84: LA QUINTA ORLANDO - Aug material cost transferred from sps | K84: LA QUINTA ORLANDO - Aug material cost transferred from sps | L84: 1122.45
B85: Journal | C85: 45894 | D85: JE1889 | F85: La Quinta Orlando | G85: F | H85: A12001 - Inventory (GV LLC) (New) : Inventory (New) | I85: 33569/4 | J85: LA QUINTA ORLANDO - Aug material cost transferred from sps | K85: LA QUINTA ORLANDO - Aug material cost transferred from sps | L85: 21347.89
B86: Journal | C86: 45894 | D86: JE3164 | F86: Wingate by Wyndham / Indianapolis | G86: F | H86: A12001 - Inventory (GV LLC) (New) : Inventory (New) | I86: 36456/6 | J86: Wingate by Wyndham / Indianapolis - Aug material cost transferred from sps | K86: Wingate by Wyndham / Indianapolis - Aug material cost transferred from sps | L86: 3338
B87: Journal | C87: 45894 | D87: JE1902 | F87: Autograph Maya-PS | G87: F | H87: A12001 - Inventory (GV LLC) (New) : Inventory (New) | I87: 36943 | J87: AUTOGRAPH MAYA-PS - Aug material cost transferred from sps | K87: AUTOGRAPH MAYA-PS - Aug material cost transferred from sps | L87: 3983
B88: Journal | C88: 45894 | D88: JE1885 | F88: La Quinta Orlando | G88: F | H88: A12001 - Inventory (GV LLC) (New) : Inventory (New) | I88: 33565/11 | J88: LA QUINTA ORLANDO - Aug material cost transferred from sps | K88: LA QUINTA ORLANDO - Aug material cost transferred from sps | L88: 5718.97
B89: Journal | C89: 45894 | D89: JE1900 | F89: La Quinta Orlando | G89: F | H89: A12001 - Inventory (GV LLC) (New) : Inventory (New) | I89: 33958/4 | J89: LA QUINTA ORLANDO - Aug material cost transferred from sps | K89: LA QUINTA ORLANDO - Aug material cost transferred from sps | L89: 7346.59
B90: Journal | C90: 45894 | D90: JE1886 | F90: La Quinta Orlando | G90: F | H90: A12001 - Inventory (GV LLC) (New) : Inventory (New) | I90: 33565/12 | J90: LA QUINTA ORLANDO - Aug material cost transferred from sps | K90: LA QUINTA ORLANDO - Aug material cost transferred from sps | L90: 4424.85
B91: Journal | C91: 45894 | D91: JE1888 | F91: La Quinta Orlando | G91: F | H91: A12001 - Inventory (GV LLC) (New) : Inventory (New) | I91: 33566/9 | J91: LA QUINTA ORLANDO - Aug material cost transferred from sps | K91: LA QUINTA ORLANDO - Aug material cost transferred from sps | L91: 442.6
... B1014: Journal | C1014: 45900 | D1014: JE2534 | F1014: Monsoon Flower LLC | G1014: F | H1014: A12001 - Inventory (GV LLC) (New) : Inventory (New) | I1014: 37955/2 | J1014: Monsoon Flower LLC - Aug material cost transferred from sps | K1014: Monsoon Flower LLC - Aug material cost transferred from sps | L1014: 18012.85
A1015: Total - A50001 - Cost Of Goods Sold (New) | L1015: =SUM(L12:L1014) -> 6944149.4
A1016: Total - A50000 - Cost of Goods Sales 50 (GV LLC) (New) | L1016: =SUM(L1015) -> 6944149.4
A1017: Total - Cost Of Sales | L1017: =SUM(L1016) -> 6944149.4
A1018: Gross Profit | L1018: =0-L1017 -> -6944149.4
A1019: Net Ordinary Income | L1019: =L1018-0 -> -6944149.4
A1020: Net Income | L1020: =L1019+0 -> -6944149.4

Sheet tab 6 Nsuite Jul Bs Inventory
A1: Graniti Vicentia, L.L.C.
A2: Parent Company : Graniti Vicentia LLC
A3: Balance Sheet Detail
A4: Jul 2025
A7: Financial Row | B7: Type | C7: Date | D7: Document Number | E7: Name | F7: Amount | G7: Balance
A8: ASSETS | F8: 0 | G8: 0
A9: Current Assets | F9: 0 | G9: 0
A10: Other Current Asset | F10: 0 | G10: 0
A11: A12000 - Inventory (GV LLC) (New) | F11: 0 | G11: 0
A12: A12001 - Inventory (New) | F12: 0 | G12: 14946309 | I12: {=_xlfn.UNIQUE(B:B)} -> 0
B13: Journal | C13: 45839 | D13: JE995 | E13: Magnolia LXR Dallas TX - | F13: -78.61 | G13: =G12+F13 -> 14946230 | I13: Type
B14: Journal | C14: 45839 | D14: JE998 | E14: Magnolia LXR Dallas TX - | F14: -3554.96 | G14: =G13+F14 -> 14942675 | I14: Journal | J14: =SUMIF(B:B,I14,F:F) -> -1944660.1
B15: Journal | C15: 45839 | D15: JE999 | E15: La Quinta Orlando | F15: -893.18 | G15: =G14+F15 -> 14941782 | I15: Item Receipt | J15: =SUMIF(B:B,I15,F:F) -> 582955.58
B16: Journal | C16: 45839 | D16: JE1000 | E16: LaQuinta/Hawthone - Knoxville TN - AMit | F16: -848 | G16: =G15+F16 -> 14940934 | I16: Bill | J16: =SUMIF(B:B,I16,F:F) -> 16120.06
B17: Journal | C17: 45839 | D17: JE1001 | E17: Magnolia LXR Dallas TX - | F17: -10311.03 | G17: =G16+F17 -> 14930623
B18: Journal | C18: 45839 | D18: JE1002 | E18: La Quinta, Anaheim CA | F18: -980.95 | G18: =G17+F18 -> 14929642
B19: Journal | C19: 45839 | D19: JE1003 | E19: LaQuinta Yakima WA | F19: -541.7 | G19: =G18+F19 -> 14929101
B20: Journal | C20: 45839 | D20: JE1004 | E20: LaQuinta Inn & Suites Oxford AL | F20: -3300.55 | G20: =G19+F20 -> 14925800
B21: Journal | C21: 45839 | D21: JE1005 | E21: Hampton Downtown Montgomery | F21: -28372.9 | G21: =G20+F21 -> 14897427
B22: Journal | C22: 45839 | D22: JE1006 | E22: Graniti Vicentia | F22: -1277.06 | G22: =G21+F22 -> 14896150
B23: Journal | C23: 45839 | D23: JE1007 | E23: Graniti Vicentia | F23: -2609.63 | G23: =G22+F23 -> 14893540
B24: Journal | C24: 45839 | D24: JE1008 | E24: CANDLEWOOD EASTRIDGE TN | F24: -386.87 | G24: =G23+F24 -> 14893154
B25: Journal | C25: 45839 | D25: JE1009 | E25: Fairfield Townplace East Hartford | F25: -23478.33 | G25: =G24+F25 -> 14869675
B26: Journal | C26: 45839 | D26: JE1010 | E26: ELEMENT FORTSMITH, ARKANSAS | F26: -8127.55 | G26: =G25+F26 -> 14861548
B27: Journal | C27: 45839 | D27: JE1011 | E27: Monsoon Flower LLC | F27: -12463.65 | G27: =G26+F27 -> 14849084
B28: Journal | C28: 45839 | D28: JE1012 | E28: Pitt-Cran Hospitality, LLC/ Wingate Cranberry | F28: -787.36 | G28: =G27+F28 -> 14848297
... B42: Item Receipt | C42: 45843 | D42: IR912 | E42: Jasfer Industry Co., Limited | F42: 261.99 | G42: =G41+F42 -> 14840195
B43: Bill | C43: 45845 | D43: 60174 - MSKU1005018 - 20250717 | F43: 12814 | G43: =G42+F43 -> 14853009
B44: Bill | C44: 45845 | D44: 60174 - MSKU1005018 - 20250717 | F44: 461.5 | G44: =G43+F44 -> 14853471
B45: Item Receipt | C45: 45845 | D45: IR914 | E45: Modular Shower Walls | F45: 9925.2 | G45: =G44+F45 -> 14863396
B46: Item Receipt | C46: 45845 | D46: IR914 | E46: Modular Shower Walls | F46: 10476.6 | G46: =G45+F46 -> 14873873
B47: Item Receipt | C47: 45845 | D47: IR914 | E47: Modular Shower Walls | F47: 530.2 | G47: =G46+F47 -> 14874403
B48: Item Receipt | C48: 45845 | D48: IR915 | E48: Modular Shower Walls | F48: 4995.9 | G48: =G47+F48 -> 14879399
B49: Item Receipt | C49: 45845 | D49: IR915 | E49: Modular Shower Walls | F49: 6185.4 | G49: =G48+F49 -> 14885584
B50: Item Receipt | C50: 45845 | D50: IR915 | E50: Modular Shower Walls | F50: 488.2 | G50: =G49+F50 -> 14886072
B51: Item Receipt | C51: 45845 | D51: IR915 | E51: Modular Shower Walls | F51: 696 | G51: =G50+F51 -> 14886768
B52: Item Receipt | C52: 45845 | D52: IR915 | E52: Modular Shower Walls | F52: 658 | G52: =G51+F52 -> 14887426
B53: Item Receipt | C53: 45845 | D53: IR916 | E53: Easy Stones | F53: 1275 | G53: =G52+F53 -> 14888701
B54: Item Receipt | C54: 45845 | D54: IR917 | E54: Modular Shower Walls | F54: 542.88 | G54: =G53+F54 -> 14889244
B55: Item Receipt | C55: 45845 | D55: IR918 | E55: Kronos USA | F55: 18135 | G55: =G54+F55 -> 14907379
B56: Item Receipt | C56: 45845 | D56: IR921 | E56: Jasfer Industry Co., Limited | F56: 23449.8 | G56: =G55+F56 -> 14930829
... B114: Journal | C114: 45852 | D114: JE1122 | E114: Richwood Hospitality Co. LTD | F114: 41907.9 | G114: =G113+F114 -> 14540409
B115: Item Receipt | C115: 45853 | D115: IR442 | F115: -316.13 | G115: =G114+F115 -> 14540093
B116: Item Receipt | C116: 45853 | D116: IR442 | F116: -14.56 | G116: =G115+F116 -> 14540079
B117: Item Receipt | C117: 45853 | D117: IR442 | F117: -168.14 | G117: =G116+F117 -> 14539910
B118: Item Receipt | C118: 45853 | D118: IR442 | F118: -1002.84 | G118: =G117+F118 -> 14538908
B119: Item Receipt | C119: 45853 | D119: IR442 | F119: -237.16 | G119: =G118+F119 -> 14538670
B120: Item Receipt | C120: 45853 | D120: IR443 | F120: -39.87 | G120: =G119+F120 -> 14538631
B121: Item Receipt | C121: 45853 | D121: IR444 | F121: 357.56 | G121: =G120+F121 -> 14538988
B122: Item Receipt | C122: 45853 | D122: IR642 | E122: Jasfer Industry Co., Limited | F122: 34506 | G122: =G121+F122 -> 14573494
B123: Item Receipt | C123: 45853 | D123: IR923 | E123: Easy Stones | F123: 343.05 | G123: =G122+F123 -> 14573837
B124: Item Receipt | C124: 45853 | D124: IR923 | E124: Easy Stones | F124: 408.02 | G124: =G123+F124 -> 14574245
B125: Item Receipt | C125: 45853 | D125: IR924 | E125: MIRAGE GRANITO CERAMICO USA INC | F125: 268.18 | G125: =G124+F125 -> 14574513
B126: Item Receipt | C126: 45854 | D126: IR926 | E126: MileStone Florim USA, Inc. | F126: 7841.44 | G126: =G125+F126 -> 14582355
B127: Item Receipt | C127: 45854 | D127: IR926 | E127: MileStone Florim USA, Inc. | F127: 5950.29 | G127: =G126+F127 -> 14588305
B128: Item Receipt | C128: 45854 | D128: IR927 | E128: MileStone Florim USA, Inc. | F128: 11932.65 | G128: =G127+F128 -> 14600238
B129: Item Receipt | C129: 45854 | D129: IR927 | E129: MileStone Florim USA, Inc. | F129: 5702.6 | G129: =G128+F129 -> 14605940
B130: Journal | C130: 45854 | D130: JE1043 | E130: Auburn Hospitality Group | F130: -29426.3 | G130: =G129+F130 -> 14576514
B131: Journal | C131: 45854 | D131: JE1044 | E131: Auburn Hospitality Group | F131: -4262 | G131: =G130+F131 -> 14572252
B132: Journal | C132: 45854 | D132: JE1123 | E132: Atlas Concorde | F132: 3115.34 | G132: =G131+F132 -> 14575367
B133: Item Receipt | C133: 45855 | D133: IR644 | E133: Jasfer Industry Co., Limited | F133: 7211.1 | G133: =G132+F133 -> 14582579
... B213: Journal | C213: 45860 | D213: JE1161 | E213: ZBOM Cabinets Corp. | F213: 487.5 | G213: =G212+F213 -> 14666354
B214: Bill | C214: 45861 | D214: 22534925-E - MSMU5584330 - 60849 | F214: 134.59 | G214: =G213+F214 -> 14666489
B215: Bill | C215: 45861 | D215: 22534925-E - MSMU5584330 - 60849 | F215: 171.97 | G215: =G214+F215 -> 14666661
B216: Journal | C216: 45861 | D216: JE1047 | E216: Jasfer Industry Co., Limited | F216: -19568.12 | G216: =G215+F216 -> 14647093
B217: Journal | C217: 45861 | D217: JE1163 | E217: Jasfer Industry Co., Limited | F217: 287692.1 | G217: =G216+F217 -> 14934785
B218: Journal | C218: 45861 | D218: JE1825 | E218: Ascent Home2 Montgomery | F218: -32.18 | G218: =G217+F218 -> 14934753
B219: Bill | C219: 45862 | D219: 25RT062501 - UPS# 1ZC23F730434707054 - 60322 | F219: 253.8 | G219: =G218+F219 -> 14935006
B220: Item Receipt | C220: 45862 | D220: IR647 | E220: Jasfer Industry Co., Limited | F220: 34506 | G220: =G219+F220 -> 14969512
B221: Item Receipt | C221: 45862 | D221: IR648 | E221: Jasfer Industry Co., Limited | F221: 34506 | G221: =G220+F221 -> 15004018
B222: Item Receipt | C222: 45862 | D222: IR649 | E222: Jasfer Industry Co., Limited | F222: 34506 | G222: =G221+F222 -> 15038524
B223: Item Receipt | C223: 45862 | D223: IR920 | E223: Beijing Topli Decorative Materials Co., LTD | F223: 9480 | G223: =G222+F223 -> 15048004
B224: Item Receipt | C224: 45862 | D224: IR920 | E224: Beijing Topli Decorative Materials Co., LTD | F224: 33528 | G224: =G223+F224 -> 15081532
B225: Item Receipt | C225: 45862 | D225: IR920 | E225: Beijing Topli Decorative Materials Co., LTD | F225: 15760.5 | G225: =G224+F225 -> 15097293
B226: Item Receipt | C226: 45862 | D226: IR920 | E226: Beijing Topli Decorative Materials Co., LTD | F226: 3149.4 | G226: =G225+F226 -> 15100442
B227: Item Receipt | C227: 45862 | D227: IR920 | E227: Beijing Topli Decorative Materials Co., LTD | F227: 2250 | G227: =G226+F227 -> 15102692
B228: Journal | C228: 45862 | D228: JE1048 | E228: Ascent Residence inn Montgomery | F228: -32463.58 | G228: =G227+F228 -> 15070229
B229: Journal | C229: 45862 | D229: JE1166 | E229: Gibam Shops SPA | F229: 50 | G229: =G228+F229 -> 15070279
B230: Journal | C230: 45862 | D230: JE1168 | E230: Gibam Shops SPA | F230: 55 | G230: =G229+F230 -> 15070334
B231: Journal | C231: 45862 | D231: JE1178 | E231: Gibam Shops SPA | F231: 55 | G231: =G230+F231 -> 15070389
... B242: Journal | C242: 45862 | D242: JE1226 | E242: Gibam Shops SPA | F242: 55 | G242: =G241+F242 -> 15084434
B243: Bill | C243: 45863 | D243: 25RT062501 - KOCU4663570 - 60322-2 | F243: 2284.2 | G243: =G242+F243 -> 15086718
B244: Journal | C244: 45863 | D244: JE1049 | E244: Chesterfield Hospitality, Inc. | F244: -8893.7 | G244: =G243+F244 -> 15077825
B245: Journal | C245: 45863 | D245: JE1050 | E245: Chesterfield Hospitality, Inc. | F245: -2033.83 | G245: =G244+F245 -> 15075791
B246: Journal | C246: 45863 | D246: JE1051 | E246: Residence Inn Pearland, TX | F246: -7741.34 | G246: =G245+F246 -> 15068050
B247: Journal | C247: 45863 | D247: JE1190 | E247: Jasfer Industry Co., Limited | F247: 468.09 | G247: =G246+F247 -> 15068518
B248: Journal | C248: 45863 | D248: JE1191 | E248: Jasfer Industry Co., Limited | F248: 170.48 | G248: =G247+F248 -> 15068688
B249: Journal | C249: 45863 | D249: JE1192 | E249: Jasfer Industry Co., Limited | F249: 5609.12 | G249: =G248+F249 -> 15074297
B250: Journal | C250: 45863 | D250: JE1195 | E250: Jasfer Industry Co., Limited | F250: 66.18 | G250: =G249+F250 -> 15074363
B251: Journal | C251: 45863 | D251: JE1196 | E251: Jasfer Industry Co., Limited | F251: 536.59 | G251: =G250+F251 -> 15074900
B252: Journal | C252: 45863 | D252: JE1197 | E252: MirageGranitoCeramico S.p.A | F252: 3922.02 | G252: =G251+F252 -> 15078822
B253: Journal | C253: 45863 | D253: JE1198 | E253: Jasfer Industry Co., Limited | F253: 1290.15 | G253: =G252+F253 -> 15080112
B254: Journal | C254: 45863 | D254: JE1199 | E254: Jasfer Industry Co., Limited | F254: 594.47 | G254: =G253+F254 -> 15080707
B255: Journal | C255: 45863 | D255: JE1200 | E255: Jasfer Industry Co., Limited | F255: 927.59 | G255: =G254+F255 -> 15081634
... B578: Journal | C578: 45869 | D578: JE1838 | E578: NEFCO Corporation | F578: -128.39 | G578: =G577+F578 -> 13600724
A579: Total - A12001 - Inventory (New) | F579: =SUM(F12:F578) -> -1345584.5 | G579: =G578 -> 13600724
A580: Total - A12000 - Inventory (GV LLC) (New) | F580: =SUM(F11,F579) -> -1345584.5 | G580: =G11+G579 -> 13600724
A581: Total Other Current Asset | F581: =SUM(F10,F580) -> -1345584.5 | G581: =G10+G580 -> 13600724
A582: Total Current Assets | F582: =0+0+0+F581 -> -1345584.5 | G582: =0+0+0+G581 -> 13600724
A583: Total ASSETS | F583: =F582+0+0 -> -1345584.5 | G583: =G582+0+0 -> 13600724

Sheet tab 7 nsuite aug bs inventry
A1: Graniti Vicentia, L.L.C.
A2: Parent Company : Graniti Vicentia LLC
A3: Balance Sheet Detail
A4: Aug 2025
A7: Financial Row | B7: Type | C7: Date | D7: Document Number | E7: Name | F7: Amount | G7: Balance | I7: 0
A8: ASSETS | F8: 0 | G8: 0 | I8: Type
A9: Current Assets | F9: 0 | G9: 0 | I9: Bill | J9: =SUMIF(B:B,I9,F:F) -> 485
A10: Other Current Asset | F10: 0 | G10: 0 | I10: Inventory Adjustment | J10: =SUMIF(B:B,I10,F:F) -> 3703.47
A11: A12000 - Inventory (GV LLC) (New) | F11: 0 | G11: 0 | I11: Journal | J11: =SUMIF(B:B,I11,F:F) -> -6830880.6
A12: A12001 - Inventory (New) | F12: 0 | G12: 13600724 | I12: Item Fulfillment | J12: =SUMIF(B:B,I12,F:F) -> -13764.53
B13: Bill | C13: 45870 | D13: BILL_30205 | F13: 346.32 | G13: =G12+F13 -> 13601071 | I13: Item Receipt | J13: =SUMIF(B:B,I13,F:F) -> 367472.18
B14: Bill | C14: 45870 | D14: BILL_30205 | F14: -346.32 | G14: =G13+F14 -> 13600724
B15: Bill | C15: 45870 | D15: BILL_30206 | F15: 6350.4 | G15: =G14+F15 -> 13607075 | J15: =SUM(J9:J13) -> -6472984.5
B16: Bill | C16: 45870 | D16: BILL_30206 | F16: -6350.4 | G16: =G15+F16 -> 13600724
B17: Bill | C17: 45870 | D17: BILL_30207 | F17: 371.07 | G17: =G16+F17 -> 13601096
B18: Bill | C18: 45870 | D18: BILL_30207 | F18: -371.07 | G18: =G17+F18 -> 13600724
B19: Bill | C19: 45870 | D19: BILL_30208 | F19: 6649.38 | G19: =G18+F19 -> 13607374
B20: Bill | C20: 45870 | D20: BILL_30208 | F20: -6649.38 | G20: =G19+F20 -> 13600724
B21: Inventory Adjustment | C21: 45870 | D21: IA350 | F21: 3703.47 | G21: =G20+F21 -> 13604428
B22: Journal | C22: 45870 | D22: JE1844 | E22: Ascent Residence inn Montgomery | F22: -45093.1 | G22: =G21+F22 -> 13559335
B23: Journal | C23: 45870 | D23: JE1845 | E23: MDC Interior Solutions | F23: -113.4 | G23: =G22+F23 -> 13559221
B24: Item Fulfillment | C24: 45873 | D24: IF367 | E24: Ascent Hospitality Management Co | F24: -3703.47 | G24: =G23+F24 -> 13555518
B25: Item Receipt | C25: 45873 | D25: IR607 | E25: WOW USA, Inc. | F25: 497 | G25: =G24+F25 -> 13556015
B26: Item Receipt | C26: 45873 | D26: IR610 | E26: MS International, Inc. | F26: 481.14 | G26: =G25+F26 -> 13556496
B27: Item Receipt | C27: 45873 | D27: IR610 | E27: MS International, Inc. | F27: 199.2 | G27: =G26+F27 -> 13556695
B28: Journal | C28: 45873 | D28: JE1846 | E28: Fairfield Townplace East Hartford | F28: -21564.59 | G28: =G27+F28 -> 13535131
B29: Journal | C29: 45873 | D29: JE1847 | E29: Classic American Homes & Renovations | F29: -996.55 | G29: =G28+F29 -> 13534134
B30: Bill | C30: 45874 | D30: 19542/VE | F30: 2116.8 | G30: =G29+F30 -> 13536251
B31: Bill | C31: 45874 | D31: 19542/VE | F31: -2116.8 | G31: =G30+F31 -> 13534134
B32: Journal | C32: 45874 | D32: JE1848 | E32: Hampton Inn Nashville | F32: -14077.81 | G32: =G31+F32 -> 13520056
B33: Journal | C33: 45874 | D33: JE1849 | E33: Chesterfield Hospitality, Inc. | F33: -11730.06 | G33: =G32+F33 -> 13508326
B34: Journal | C34: 45874 | D34: JE1850 | E34: Chesterfield Hospitality, Inc. | F34: -7314.78 | G34: =G33+F34 -> 13501012
B35: Journal | C35: 45874 | D35: JE1851 | E35: Chesterfield Hospitality, Inc. | F35: -1256.79 | G35: =G34+F35 -> 13499755
B36: Item Fulfillment | C36: 45875 | D36: IF279 | E36: Umang patel | F36: -3965.73 | G36: =G35+F36 -> 13495789
B37: Item Receipt | C37: 45875 | D37: IR654 | E37: Jasfer Industry Co., Limited | F37: 21750.87 | G37: =G36+F37 -> 13517540
B38: Item Receipt | C38: 45875 | D38: IR654 | E38: Jasfer Industry Co., Limited | F38: 1409.54 | G38: =G37+F38 -> 13518949
B39: Item Receipt | C39: 45875 | D39: IR654 | E39: Jasfer Industry Co., Limited | F39: 24042.13 | G39: =G38+F39 -> 13542992
B40: Item Receipt | C40: 45875 | D40: IR654 | E40: Jasfer Industry Co., Limited | F40: 15228.78 | G40: =G39+F40 -> 13558220
B41: Item Receipt | C41: 45875 | D41: IR654 | E41: Jasfer Industry Co., Limited | F41: 750.04 | G41: =G40+F41 -> 13558970
B42: Item Receipt | C42: 45875 | D42: IR654 | E42: Jasfer Industry Co., Limited | F42: 2351.95 | G42: =G41+F42 -> 13561322
B43: Item Receipt | C43: 45875 | D43: IR654 | E43: Jasfer Industry Co., Limited | F43: 3379.6 | G43: =G42+F43 -> 13564702
... B66: Item Receipt | C66: 45879 | D66: IR1443 | E66: ZBOM Cabinets Corp. | F66: 3715.47 | G66: =G65+F66 -> 13567229
B67: Bill | C67: 45880 | D67: 60128 - SR410-14 - SKIU9139606 | F67: 276 | G67: =G66+F67 -> 13567505
B68: Bill | C68: 45880 | D68: 60128 - SR410-14 - SKIU9139606 | F68: 209 | G68: =G67+F68 -> 13567714
B69: Item Receipt | C69: 45880 | D69: IR611 | E69: WOW USA, Inc. | F69: 2091.33 | G69: =G68+F69 -> 13569806
B70: Item Receipt | C70: 45880 | D70: IR612 | E70: WOW USA, Inc. | F70: 911.59 | G70: =G69+F70 -> 13570717
B71: Item Receipt | C71: 45880 | D71: IR612 | E71: WOW USA, Inc. | F71: 623.71 | G71: =G70+F71 -> 13571341
B72: Item Receipt | C72: 45880 | D72: IR613 | E72: WOW USA, Inc. | F72: 249.32 | G72: =G71+F72 -> 13571590
B73: Item Receipt | C73: 45880 | D73: IR613 | E73: WOW USA, Inc. | F73: 243.25 | G73: =G72+F73 -> 13571833
B74: Journal | C74: 45880 | D74: JE1860 | E74: Ascent Hospitality Tribute Carmel Indiana | F74: -566.78 | G74: =G73+F74 -> 13571267
B75: Journal | C75: 45880 | D75: JE1861 | E75: Mesquite Gaming | F75: -990.31 | G75: =G74+F75 -> 13570276
B76: Journal | C76: 45880 | D76: JE3154 | E76: HOME2 SOMERSET | F76: -365.65 | G76: =G75+F76 -> 13569911
B77: Journal | C77: 45880 | D77: JE3155 | E77: HOME2 SOMERSET | F77: -6467.32 | G77: =G76+F77 -> 13563443
B78: Journal | C78: 45881 | D78: JE1862 | E78: Ascent Hospitality Tribute Carmel Indiana | F78: -147.48 | G78: =G77+F78 -> 13563296
B79: Journal | C79: 45881 | D79: JE1863 | E79: Ascent Hospitality Tribute Carmel Indiana | F79: -2222.38 | G79: =G78+F79 -> 13561074
B80: Journal | C80: 45881 | D80: JE1864 | E80: Ascent Home2 Montgomery | F80: -838.15 | G80: =G79+F80 -> 13560235
... B152: Item Receipt | C152: 45892 | D152: IR657 | E152: Jasfer Industry Co., Limited | F152: 5 | G152: =G151+F152 -> 13418289
B153: Item Receipt | C153: 45892 | D153: IR658 | F153: -20527.2 | G153: =G152+F153 -> 13397761
B154: Item Receipt | C154: 45892 | D154: IR658 | F154: -1086.08 | G154: =G153+F154 -> 13396675
B155: Item Receipt | C155: 45892 | D155: IR663 | E155: Fama Sofas S.L.U | F155: 134.59 | G155: =G154+F155 -> 13396810
B156: Item Receipt | C156: 45892 | D156: IR663 | E156: Fama Sofas S.L.U | F156: 171.97 | G156: =G155+F156 -> 13396982
B157: Item Receipt | C157: 45892 | D157: IR664 | E157: Jasfer Industry Co., Limited | F157: 24443.88 | G157: =G156+F157 -> 13421426
B158: Item Receipt | C158: 45892 | D158: IR664 | E158: Jasfer Industry Co., Limited | F158: 2459.16 | G158: =G157+F158 -> 13423885
B159: Item Receipt | C159: 45892 | D159: IR664 | E159: Jasfer Industry Co., Limited | F159: 4803.12 | G159: =G158+F159 -> 13428688
B160: Item Receipt | C160: 45892 | D160: IR664 | E160: Jasfer Industry Co., Limited | F160: 3280.9 | G160: =G159+F160 -> 13431969
B161: Item Receipt | C161: 45892 | D161: IR664 | E161: Jasfer Industry Co., Limited | F161: 3419.36 | G161: =G160+F161 -> 13435388
B162: Item Receipt | C162: 45892 | D162: IR664 | E162: Jasfer Industry Co., Limited | F162: 2260.96 | G162: =G161+F162 -> 13437649
B163: Item Receipt | C163: 45892 | D163: IR664 | E163: Jasfer Industry Co., Limited | F163: 5813.94 | G163: =G162+F163 -> 13443463
B164: Item Receipt | C164: 45892 | D164: IR664 | E164: Jasfer Industry Co., Limited | F164: 2957.52 | G164: =G163+F164 -> 13446421
B165: Item Receipt | C165: 45892 | D165: IR664 | E165: Jasfer Industry Co., Limited | F165: 166.88 | G165: =G164+F165 -> 13446588
B166: Item Receipt | C166: 45892 | D166: IR664 | E166: Jasfer Industry Co., Limited | F166: 333.76 | G166: =G165+F166 -> 13446921
... B1160: Journal | C1160: 45900 | D1160: JE3339 | E1160: Didier Nader | F1160: -166.1 | G1160: =G1159+F1160 -> 7127740
A1161: Total - A12001 - Inventory (New) | F1161: =SUM(F12:F1160) -> -6472984.5 | G1161: =G1160 -> 7127740
A1162: Total - A12000 - Inventory (GV LLC) (New) | F1162: =SUM(F11,F1161) -> -6472984.5 | G1162: =G11+G1161 -> 7127740
A1163: Total Other Current Asset | F1163: =SUM(F10,F1162) -> -6472984.5 | G1163: =G10+G1162 -> 7127740
A1164: Total Current Assets | F1164: =0+0+0+F1163 -> -6472984.5 | G1164: =0+0+0+G1163 -> 7127740
A1165: Total ASSETS | F1165: =F1164+0+0 -> -6472984.5 | G1165: =G1164+0+0 -> 7127740

Sheet tab 11 SpS comparative 
A1: Balance Sheet Comparison: Monthly
A2: All Locations
B3: 45748 | D3: 45778 | F3: 45809 | H3: 45839 | J3: 45870 | L3: 45901 | N3: 45931 | P3: 45962 | R3: 45992 | T3: 46023 | V3: 46054 | X3: 46082
A4: ASSETS
A5: Current Assets
A6: 10002 - Truist -Savings -4645 | B6: 1311.53 | D6: 1311.53 | F6: 1311.53 | H6: 1311.53 | J6: 1311.53 | L6: 1311.53 | N6: 1311.53 | P6: 1311.53 | R6: 1311.53 | T6: 1311.53 | V6: 1311.53 | X6: 1311.53
A7: 10003 - Allegiance Bank Texas-2243 | B7: 39327.11 | D7: 50582.4 | F7: 936.03 | H7: 936.03 | J7: 936.03 | L7: 616.03 | N7: 616.03 | P7: 616.03 | R7: 616.03 | T7: 616.03 | V7: 616.03 | X7: 616.03
A8: 10008 - Truist Bank - 4637 | B8: -4673.75 | D8: 20762.76 | F8: 8099.13 | H8: 8099.13 | J8: 8099.13 | L8: 2437119.5 | N8: 2437119.5 | P8: 2437119.5 | R8: 2437119.5 | T8: 2437119.5 | V8: 2437119.5 | X8: 2437119.5
A9: 10010 - Petty Cash On Hand | B9: 2063.36 | D9: 2063.36 | F9: 2063.36 | H9: 2063.36 | J9: 2063.36 | L9: -7238.14 | N9: -7238.14 | P9: -7238.14 | R9: -7238.14 | T9: -7238.14 | V9: -7238.14 | X9: -7238.14
A10: 10017 - Prepayment to Suppliers | B10: 5225.47 | D10: 5226.45 | F10: 38259.34 | H10: 38259.34 | J10: 38259.34 | L10: 38259.34 | N10: 38259.34 | P10: 38259.34 | R10: 38259.34 | T10: 38259.34 | V10: 38259.34 | X10: 38259.34
A11: 10019 - CC-Clearing Account | B11: -1993.65 | D11: -2633.85 | F11: -4091.4 | H11: -4091.4 | J11: -4091.4 | L11: -4091.4 | N11: -4091.4 | P11: -4091.4 | R11: -4091.4 | T11: -4091.4 | V11: -4091.4 | X11: -4091.4
A12: 11000 - Accounts Receivable | B12: 10320476 | D12: 9213673.8 | F12: 13450222 | H12: 15765431 | J12: 16292262 | L12: 17023453 | N12: 17023453 | P12: 17023453 | R12: 17023453 | T12: 17023453 | V12: 17023453 | X12: 17023453
A13: 11000.01 - Allowance for Doubtful Accounts | B13: -766001.85 | D13: -766001.85 | F13: -766001.85 | H13: -766001.85 | J13: -766001.85 | L13: -766001.85 | N13: -766001.85 | P13: -766001.85 | R13: -766001.85 | T13: -766001.85 | V13: -766001.85 | X13: -766001.85
A14: Total Current Assets | B14: 9595734 | D14: 8524984.6 | F14: 12730798 | H14: 15046008 | J14: 15572838 | L14: 18723428 | N14: 18723428 | P14: 18723428 | R14: 18723428 | T14: 18723428 | V14: 18723428 | X14: 18723428
A15: Fixed Assets
A16: 14000 - Automobile | B16: 437491.46 | D16: 437491.46 | F16: 437491.46 | H16: 437491.46 | J16: 437491.46 | L16: 437491.46 | N16: 437491.46 | P16: 437491.46 | R16: 437491.46 | T16: 437491.46 | V16: 437491.46 | X16: 437491.46
A17: 14100 - Furniture & Fixture | B17: 41183.31 | D17: 41183.31 | F17: 41183.31 | H17: 41183.31 | J17: 41183.31 | L17: 41183.31 | N17: 41183.31 | P17: 41183.31 | R17: 41183.31 | T17: 41183.31 | V17: 41183.31 | X17: 41183.31
A18: 14150 - Computer & Electronics | B18: 449068.68 | D18: 449068.68 | F18: 449068.68 | H18: 449068.68 | J18: 449068.68 | L18: 449068.68 | N18: 449068.68 | P18: 449068.68 | R18: 449068.68 | T18: 449068.68 | V18: 449068.68 | X18: 449068.68
A19: 14200 - Machinery & Equipment | B19: 2120560.2 | D19: 2120560.2 | F19: 2120560.2 | H19: 2120560.2 | J19: 2120560.2 | L19: 2120560.2 | N19: 2120560.2 | P19: 2120560.2 | R19: 2120560.2 | T19: 2120560.2 | V19: 2120560.2 | X19: 2120560.2
A20: 14300 - Leasehold Improvements | B20: 4413527.2 | D20: 4413527.2 | F20: 5633130.9 | H20: 5633130.9 | J20: 5633130.9 | L20: 5633130.9 | N20: 5633130.9 | P20: 5633130.9 | R20: 5633130.9 | T20: 5633130.9 | V20: 5633130.9 | X20: 5633130.9
A21: 14600 - Construction in Process | B21: 1500 | D21: 4802 | F21: 4802 | H21: 4802 | J21: 4802 | L21: 4802 | N21: 4802 | P21: 4802 | R21: 4802 | T21: 4802 | V21: 4802 | X21: 4802
A22: 14500 - Accumulated Depreciation | B22: -2794367.4 | D22: -2839202.7 | F22: -2884036.8 | H22: -2973211.9 | J22: -3062453.6 | L22: -3137996.9 | N22: -3137996.9 | P22: -3093656 | R22: -3004974 | T22: -3004974 | V22: -3004974 | X22: -3004974
A23: Total Fixed Assets | B23: 4668963.5 | D23: 4627430.2 | F23: 5802199.8 | H23: 5713024.7 | J23: 5623782.9 | L23: 5548239.7 | N23: 5548239.7 | P23: 5592580.6 | R23: 5681262.5 | T23: 5681262.5 | V23: 5681262.5 | X23: 5681262.5
A24: Other Current Assets
A25: 11050 - Accrued Accounts Receivable | B25: 11870 | D25: 11150 | F25: 15430 | H25: 15430 | J25: 15430 | L25: 15430 | N25: 15430 | P25: 15430 | R25: 15430 | T25: 15430 | V25: 15430 | X25: 15430
A26: 12000 - Inventory | B26: 19713436 | D26: 20197448 | F26: 14933430 | H26: 15686330 | J26: 11836929 | L26: 14171144 | N26: 14171144 | P26: 14171144 | R26: 14171144 | T26: 14171144 | V26: 14171144 | X26: 14171144
A27: 12050 - Inventory Allowances | B27: -1000000 | D27: -1000000 | F27: -1000000 | H27: -1000000 | J27: -1000000 | L27: -1000000 | N27: -1000000 | P27: -1000000 | R27: -1000000 | T27: -1000000 | V27: -1000000 | X27: -1000000
A28: 12100 - Obsolete Inventory | B28: 899003.97 | D28: 899003.97 | F28: 899003.97 | H28: 899003.97 | J28: 899003.97 | L28: 899003.97 | N28: 899003.97 | P28: 899003.97 | R28: 899003.97 | T28: 899003.97 | V28: 899003.97 | X28: 899003.97
A29: 12500 - PrePaid Expenses | B29: 156105.82 | D29: 173515.01 | F29: 177485.31 | H29: 177485.31 | J29: 177485.31 | L29: 177485.31 | N29: 177485.31 | P29: 177485.31 | R29: 177485.31 | T29: 177485.31 | V29: 177485.31 | X29: 177485.31
A30: 13200 - Undeposited Funds | B30: 31901.7 | D30: 28147.34 | F30: 84255.67 | H30: 84255.67 | J30: 84255.67 | L30: 84255.67 | N30: 84255.67 | P30: 84255.67 | R30: 84255.67 | T30: 84255.67 | V30: 84255.67 | X30: 84255.67
A31: 14700 - Organizational Costs | B31: 437119.47 | D31: 437119.47 | F31: 172119.47 | H31: 172119.47 | J31: 172119.47 | L31: 172119.47 | N31: 172119.47 | P31: 172119.47 | R31: 172119.47 | T31: 172119.47 | V31: 172119.47 | X31: 172119.47
A32: 14750 - Other Current Assets New Account | B32: 0 | D32: 0 | F32: 0 | H32: 0 | J32: 0 | L32: 9297194 | N32: 9297194 | P32: 9297194 | R32: 9297194 | T32: 9297194 | V32: 9297194 | X32: 9297194
A33: 15000 - Advance To Suppliers | B33: 282.74 | D33: 282.74 | F33: 282.74 | H33: 282.74 | J33: 282.74 | L33: 282.74 | N33: 282.74 | P33: 282.74 | R33: 282.74 | T33: 282.74 | V33: 282.74 | X33: 282.74
A34: 15500 - Investment in GV India | B34: 62000 | D34: 62000 | F34: 62000 | H34: 62000 | J34: 62000 | L34: 62000 | N34: 62000 | P34: 62000 | R34: 62000 | T34: 62000 | V34: 62000 | X34: 62000
A35: 15600 - Investment in GV Saudi | B35: 100000 | D35: 100000 | F35: 365000 | H35: 365000 | J35: 365000 | L35: 365000 | N35: 365000 | P35: 365000 | R35: 365000 | T35: 365000 | V35: 365000 | X35: 365000
A36: 16000 - Intercompany GV Realty | B36: 2141414.9 | D36: 2148414.9 | F36: 2151414.9 | H36: 2151414.9 | J36: 2151414.9 | L36: 2151414.9 | N36: 2151414.9 | P36: 2151414.9 | R36: 2151414.9 | T36: 2151414.9 | V36: 2151414.9 | X36: 2151414.9
... A40: 22014 - Intercompany GV INDIA -33800 | B40: 176239.94 | D40: 176239.94 | F40: 176239.94 | H40: 106239.94 | J40: 36239.94 | L40: -33760.06 | N40: -33760.06 | P40: -33760.06 | R40: -33760.06 | T40: -33760.06 | V40: -33760.06 | X40: -33760.06
A41: 4 - Inventory - In Transit | B41: 4863125.3 | D41: 7599714.8 | F41: 2135520.9 | G41: =F41+F28+F27+F26 -> 16967955 | H41: 1915453 | J41: 1708066.1 | L41: 1708066.1 | N41: 1708066.1 | P41: 1708066.1 | R41: 1708066.1 | T41: 1708066.1 | V41: 1708066.1 | X41: 1708066.1
A42: Total Other Current Assets | B42: 29088525 | D42: 31712867 | F42: 21076013 | G42: inventory | H42: 21576432 | J42: 17449645 | L42: 29455284 | N42: 29455284 | P42: 29455284 | R42: 29455284 | T42: 29455284 | V42: 29455284 | X42: 29455284
A43: Total ASSETS | B43: 43353223 | D43: 44865282 | F43: 39609011 | G43: transfer | H43: 42335465 | J43: 38646266 | L43: 53726952 | N43: 53726952 | P43: 53771293 | R43: 53859975 | T43: 53859975 | V43: 53859975 | X43: 53859975
A44: LIABILITIES & EQUITY
A45: Current Liabilities
A46: 16050 - Intercompany GV Realty2 | B46: 785127.11 | D46: 785799.36 | F46: 821160.07 | H46: 821160.07 | J46: 821160.07 | L46: 821160.07 | N46: 821160.07 | P46: 821160.07 | R46: 821160.07 | T46: 821160.07 | V46: 821160.07 | X46: 821160.07
A47: 20000 - Accrued Accounts Payable | B47: 0 | D47: 0 | F47: 0 | H47: 0 | J47: 0 | L47: -3863595.2 | N47: -3863595.2 | P47: -3863595.2 | R47: -3863595.2 | T47: -3863595.2 | V47: -3863595.2 | X47: -3863595.2
A48: 20001 - American Express - 31013 | B48: -78927.46 | D48: -75452.27 | F48: -74865.99 | H48: -74865.99 | J48: -74865.99 | L48: -35022.42 | N48: -35022.42 | P48: -35022.42 | R48: -35022.42 | T48: -35022.42 | V48: -35022.42 | X48: -35022.42
A49: 20002 - Truist -Visa -6769 | B49: 969545.04 | D49: 668950.84 | F49: 1175253.5 | H49: 1175253.5 | J49: 1175253.5 | L49: 2719394.7 | N49: 2719394.7 | P49: 2719394.7 | R49: 2719394.7 | T49: 2719394.7 | V49: 2719394.7 | X49: 2719394.7
A50: 20010 - Accounts Payable Suppliers | B50: 3605980.8 | D50: 3237155.2 | F50: 2067844.5 | H50: 5082011.8 | J50: 5781196.5 | L50: 11118773 | N50: 11118773 | P50: 11118773 | R50: 11118773 | T50: 11118773 | V50: 11118773 | X50: 11118773
A51: 20013 - Accumulated Foreign Exchange ADJ | B51: 125997.94 | D51: 125997.94 | F51: 125997.94 | H51: 125997.94 | J51: 125997.94 | L51: 125997.94 | N51: 125997.94 | P51: 125997.94 | R51: 125997.94 | T51: 125997.94 | V51: 125997.94 | X51: 125997.94
A52: 20020 - Accounts Payable Vendors | B52: 2072933.1 | D52: 1758138.7 | F52: 1579078.4 | H52: 1865908.1 | J52: 2260279.2 | L52: 2432978.4 | N52: 2432978.4 | P52: 2432978.4 | R52: 2432978.4 | T52: 2432978.4 | V52: 2432978.4 | X52: 2432978.4
A53: 20030 - Payroll Liabilities | B53: 9906.85 | D53: 5434.53 | F53: 6754.53 | H53: 6754.53 | J53: 6754.53 | L53: 6754.53 | N53: 6754.53 | P53: 6754.53 | R53: 6754.53 | T53: 6754.53 | V53: 6754.53 | X53: 6754.53
A54: 20050 - 401K Payable | B54: 2761.93 | D54: 2742.61 | F54: 3827.62 | H54: 3827.62 | J54: 3827.62 | L54: -6068.82 | N54: -6068.82 | P54: -6068.82 | R54: -6068.82 | T54: -6068.82 | V54: -6068.82 | X54: -6068.82
A55: 22011 - Intercompany GV Facades | B55: 818253.46 | D55: 1825249.2 | F55: 1305339.3 | H55: 1305339.3 | J55: 1306668.9 | L55: 1406668.9 | N55: 1406668.9 | P55: 1406668.9 | R55: 1406668.9 | T55: 1406668.9 | V55: 1406668.9 | X55: 1406668.9
A56: 22012 - Customer deposits | B56: 29790250 | D56: 33047440 | F56: 21611892 | H56: 20394691 | J56: 13623041 | L56: 30830835 | N56: 30830835 | P56: 30830835 | R56: 30830835 | T56: 30830835 | V56: 30830835 | X56: 30830835
A57: 22064 - Line Of Credit | B57: 2384782.9 | D57: 2263971.4 | F57: 2344942.1 | H57: 2344942.1 | J57: 2344942.1 | L57: 2499017.2 | N57: 2499017.2 | P57: 2499017.2 | R57: 2499017.2 | T57: 2499017.2 | V57: 2499017.2 | X57: 2499017.2
... A59: Total Current Liabilities | B59: 40974424 | D59: 44136813 | F59: 31838149 | H59: 33954318 | J59: 28453010 | L59: 49163614 | N59: 49163614 | P59: 49163614 | R59: 49163614 | T59: 49163614 | V59: 49163614 | X59: 49163614
A60: Long Term Liabilities
A61: 22049 - Loan-Wells Fargo-Forklift - Equipment-301-0026727-000 | B61: 52637.51 | D61: 58023 | F61: 58023 | H61: 58023 | J61: 58023 | L61: 54154.8 | N61: 54154.8 | P61: 54154.8 | R61: 54154.8 | T61: 54154.8 | V61: 54154.8 | X61: 54154.8
A62: 22052 - Loan-Wells Fargo-Forklift - Equipment-301-0021960-000 | B62: 28668.41 | D62: 29858 | F62: 29858 | H62: 29858 | J62: 29858 | L62: 26872.16 | N62: 26872.16 | P62: 26872.16 | R62: 26872.16 | T62: 26872.16 | V62: 26872.16 | X62: 26872.16
A63: 22056 - Loan-Wells Fargo-Forklift -301-0026729-000 | B63: 46876.28 | D63: 51626.99 | F63: 51626.99 | H63: 51626.99 | J63: 51626.99 | L63: 48025.1 | N63: 48025.1 | P63: 48025.1 | R63: 48025.1 | T63: 48025.1 | V63: 48025.1 | X63: 48025.1
A64: 22079 - Loan-Wells Fargo-Forklift -301-0181012-006 | B64: 5804.32 | D64: 7062.25 | F64: 6481.35 | H64: 6481.35 | J64: 6481.35 | L64: 4612.8 | N64: 4612.8 | P64: 4612.8 | R64: 4612.8 | T64: 4612.8 | V64: 4612.8 | X64: 4612.8
A65: 22081 - Note payables Allegiance Boomlifs -8001055614 | B65: 335584.7 | D65: 330455.92 | F65: 325347.25 | H65: 325347.25 | J65: 325347.25 | L65: 325347.25 | N65: 325347.25 | P65: 325347.25 | R65: 325347.25 | T65: 325347.25 | V65: 325347.25 | X65: 325347.25
A66: 25001 - Loan from SBA(7571187400) | B66: 497066.41 | D66: 489750.91 | F66: 489750.91 | H66: 489750.91 | J66: 489750.91 | L66: 489750.91 | N66: 489750.91 | P66: 489750.91 | R66: 489750.91 | T66: 489750.91 | V66: 489750.91 | X66: 489750.91
A67: Total Long Term Liabilities | B67: 966637.63 | D67: 966777.07 | F67: 961087.5 | H67: 961087.5 | J67: 961087.5 | L67: 948763.02 | N67: 948763.02 | P67: 948763.02 | R67: 948763.02 | T67: 948763.02 | V67: 948763.02 | X67: 948763.02
A68: Equity
A69: 13100 - Draws -Srini (Due To /From) | B69: -561663.27 | D69: -561663.27 | F69: -61663.27 | H69: -61663.27 | J69: -61663.27 | L69: -61663.27 | N69: -61663.27 | P69: -61663.27 | R69: -61663.27 | T69: -61663.27 | V69: -61663.27 | X69: -61663.27
A70: 13150 - Srini -Contributions | B70: -1333.3 | D70: -1333.3 | F70: -1333.3 | H70: -1333.3 | J70: -1333.3 | L70: -1333.3 | N70: -1333.3 | P70: -1333.3 | R70: -1333.3 | T70: -1333.3 | V70: -1333.3 | X70: -1333.3
A71: 31100 - Additional paid in Capital | B71: 49079.32 | D71: 49079.32 | F71: 49079.32 | H71: 49079.32 | J71: 49079.32 | L71: 49079.32 | N71: 49079.32 | P71: 49079.32 | R71: 49079.32 | T71: 49079.32 | V71: 49079.32 | X71: 49079.32
A72: 31500 - Paid In Capital | B72: 1060 | D72: 1060 | F72: 1060 | H72: 1060 | J72: 1060 | L72: 1060 | N72: 1060 | P72: 1060 | R72: 1060 | T72: 1060 | V72: 1060 | X72: 1060
A73: 32000 - Retained Earnings | B73: 1690664.6 | D73: 1690664.6 | F73: 1690664.6 | H73: 1690664.6 | J73: 1690664.6 | L73: 1692664.9 | N73: 1692664.9 | P73: 1692664.9 | R73: 1692664.9 | T73: 3765029 | V73: 3765029 | X73: 3765029
A74: Net Income | B74: 234353.26 | D74: -1416115.9 | F74: 5131967.1 | H74: 5742251.8 | J74: 7554361.6 | L74: 1934767.5 | N74: 1934767.5 | P74: 1979108.4 | R74: 2067790.3 | T74: -4573.8 | V74: -4573.8 | X74: -4573.8
A75: Total Equity | B75: 1412160.6 | D75: -238308.6 | F75: 6809774.4 | H75: 7420059.1 | J75: 9232168.9 | L75: 3614575.1 | N75: 3614575.1 | P75: 3658916.1 | R75: 3747598 | T75: 3747598 | V75: 3747598 | X75: 3747598
A76: Total LIABILITIES & EQUITY | B76: 43353223 | D76: 44865282 | F76: 39609011 | H76: 42335465 | J76: 38646266 | L76: 53726952 | N76: 53726952 | P76: 53771293 | R76: 53859975 | T76: 53859975 | V76: 53859975 | X76: 53859975

Sheet tab12July cogs in sps
A1: Date | B1: Transaction# | C1: Invoice# | D1: Location | E1: Type | F1: Description | G1: Party | H1: Debit | I1: Credit | J1: Balance
A2: BALANCE FORWARD | J2: 14938003
A3: 45839 | B3: 31647 | C3: 31647 | D3: GV | E3: Invoice | F3: PS-CP-403-LT Pendant over Communal Table | G3: CANDLEWOOD LAFAYETTE | I3: 78.61 | J3: 14937925
A4: 45839 | B4: 33495/7 | C4: 33495/7 | D4: GV | E4: Invoice | F4: MR-100 Custom Full-height Mirror - Dims: 36"W x 8 | G4: Magnolia LXR Dallas TX - | I4: 474.66 | J4: 14937450
A5: 45839 | B5: 33495/7 | C5: 33495/7 | D5: GV | E5: Invoice | F5: MR-101B Custom Vanity Mirror with TV @ Junior Suite Bathroom - Dims: 56"W x 48"H x 1.75"D, :Vanity makeup mirror -Size:200x200x290mm - Magnification : 5 times -Material:Brass& Zinc-Alloy - CCT Options: Warm color:3000K Operating by power supply -ON/OFF switch Wall-mounted Low Iron Clear Mirror with Lighting & TV in Custom Size TV 15.6" | G5: Magnolia LXR Dallas TX - | I5: 847.66 | J5: 14936602
A6: 45839 | B6: 33495/7 | C6: 33495/7 | D6: GV | E6: Invoice | F6: MR-102 Make-up Mirror @ Bathrooms - Vanity makeup mirror -Size:200x200x290mm (8"W x 8"H) - Magnification : 5 times -Material:Brass& Zinc-Alloy - CCT Options: Warm color:3000K Operating by power supply -ON/OFF switch | G6: Magnolia LXR Dallas TX - | I6: 395.64 | J6: 14936207
A7: 45839 | B7: 33495/7 | C7: 33495/7 | D7: GV | E7: Invoice | F7: Decorative Mirror @ Corridor: 5mm reflective glass mirror + 1.12eva + 5mm rainbow glass, Dimensions: 139 1/1" x 3/8" x 108" | G7: Magnolia LXR Dallas TX - | I7: 1118.5 | J7: 14935088
A8: 45839 | B8: 33495/7 | C8: 33495/7 | D8: GV | E8: Invoice | F8: Metal Bars @ Decorative Mirror - stainless/MT01, Dimensions: 355 1/4" x 1 7/8" x 3/8" | G8: Magnolia LXR Dallas TX - | I8: 248.5 | J8: 14934840
A9: 45839 | B9: 33495/7 | C9: 33495/7 | D9: GV | E9: Invoice | F9: Decorative baseboard: Aluminum Alloy & Acrylic/wooden finish, 6"*3/4" MDF with venner on the surface, PU painted finish match with the doors, Dimensions: 139 1/4" x 3/4" x 6" | G9: Magnolia LXR Dallas TX - | I9: 227.5 | J9: 14934612
A10: 45839 | B10: 33495/7 | C10: 33495/7 | D10: GV | E10: Invoice | F10: LED Lightstrips @ Corridor Door: "1. Material: Aluminum Alloy & Acrylic 2. 2835LED lightstrips, 120chips/M, 15-16LUMEN/chip, CRI=90, CCT 3000K,Warm white color, 10w/m, length 48"", UL listed 3. LED driver 24v, 20w, UL listed 4. 2M black cord, 20#, with 2Pin plug, UL listed", Dimensions: 139 1/4" x 1/2" x 2/3" | G10: Magnolia LXR Dallas TX - | I10: 242.5 | J10: 14934370
A11: 45839 | B11: 33555 | C11: 33555 | D11: GV | E11: Invoice | F11: CORR-301 Corridor Wall Sconce (ADA Complaint) | G11: La Quinta Inn & Suites- Seatac Airport- Seattle WA | I11: 3194.94 | J11: 14931175
A12: 45839 | B12: 33555 | C12: 33555 | D12: GV | E12: Invoice | F12: ELEV-301 Pendant Light @ Lobby Entrance | G12: La Quinta Inn & Suites- Seatac Airport- Seattle WA | I12: 693.8 | J12: 14930481
A13: 45839 | B13: 33555 | C13: 33555 | D13: GV | E13: Invoice | F13: ELEV-302 Pendant Light @ Elevator Lobby (Upper Floors) | G13: La Quinta Inn & Suites- Seatac Airport- Seattle WA | I13: 1339.5 | J13: 14929142
A14: 45839 | B14: 33555 | C14: 33555 | D14: GV | E14: Invoice | F14: REG-301 Pendants @ Reception Desk | G14: La Quinta Inn & Suites- Seatac Airport- Seattle WA | I14: 1293.8 | J14: 14927848
A15: 45839 | B15: 33555 | C15: 33555 | D15: GV | E15: Invoice | F15: GRT-301 Pendant Fixture @ Breakfast Counter | G15: La Quinta Inn & Suites- Seatac Airport- Seattle WA | I15: 741.35 | J15: 14927106
A16: 45839 | B16: 33555 | C16: 33555 | D16: GV | E16: Invoice | F16: GRT-302 Pendant Fixture @ Communal Table | G16: La Quinta Inn & Suites- Seatac Airport- Seattle WA | I16: 1170.9 | J16: 14925936
A17: 45839 | B17: 33555 | C17: 33555 | D17: GV | E17: Invoice | F17: GRT-307C Elevator Lobby Wall Scones | G17: La Quinta Inn & Suites- Seatac Airport- Seattle WA | I17: 173.28 | J17: 14925762
A18: 45839 | B18: 33555 | C18: 33555 | D18: GV | E18: Invoice | F18: CORR-301 Corridor Wall Sconce (ADA Complaint) | G18: La Quinta Inn & Suites- Seatac Airport- Seattle WA | I18: 1341.87 | J18: 14924420
A19: 45839 | B19: 33555 | C19: 33555 | D19: GV | E19: Invoice | F19: GRT-311C Wall Sconce Exit (Beside Fitness center) | G19: La Quinta Inn & Suites- Seatac Airport- Seattle WA | I19: 799.47 | J19: 14923621
A20: 45839 | B20: 33565/10 | C20: 33565/10 | D20: GV | E20: Invoice | F20: GR-401 Round Mirror @ Luggage Bench | G20: LA QUINTA ORLANDO | I20: 893.18 | J20: 14922728
A21: 45839 | B21: 33722/5 | C21: 33722/5 | D21: GV | E21: Invoice | F21: GRT-306 LED Wall Light Installation @ Entry Lounge (Neon Sign is Included) | G21: LaQuinta/Hawthone - Knoxville TN - AMit | I21: 848 | J21: 14921880
A22: 45839 | B22: 33984 | C22: 33984 | D22: GV | E22: Invoice | F22: PS-CP-401-LT Pendant # Lounge Area | G22: CANDLEWOOD LAFAYETTE | I22: 230 | J22: 14921650
A23: 45839 | B23: 33984 | C23: 33984 | D23: GV | E23: Invoice | F23: PS-CP-401-LT Pendant # Lounge Area | G23: CANDLEWOOD LAFAYETTE | I23: 115 | J23: 14921535
A24: 45839 | B24: 34076 | C24: 34076 | D24: GV | E24: Invoice | F24: LED lightstrips GRT-905 | G24: LaQuinta - Naples - FL - Raj Mukkirla | I24: 897.68 | J24: 14920637
A25: 45839 | B25: 34076 | C25: 34076 | D25: GV | E25: Invoice | F25: LED Neon Sign GRT-306 | G25: LaQuinta - Naples - FL - Raj Mukkirla | I25: 467.68 | J25: 14920169
A26: 45839 | B26: 34076 | C26: 34076 | D26: GV | E26: Invoice | F26: Metal Iluminated Wall artwork REG-901 | G26: LaQuinta - Naples - FL - Raj Mukkirla | I26: 2710.66 | J26: 14917459
A27: 45839 | B27: 34076 | C27: 34076 | D27: GV | E27: Invoice | F27: Metal Screen GRT-904 | G27: LaQuinta - Naples - FL - Raj Mukkirla | I27: 2007.63 | J27: 14915451
A28: 45839 | B28: 34086/8 | C28: 34086/8 | D28: GV | E28: Invoice | F28: GUEST POWDER BATH TRAVERTINE FLOORING & WALLS: Marble / Silver Travertine (HONED) , Stone Flooring, Polished , 41 1/4 x 30 x 5/7, Per Drawing #2 | G28: Magnolia LXR Dallas TX - | I28: 1010 | J28: 14914441
A29: 45839 | B29: 34086/8 | C29: 34086/8 | D29: GV | E29: Invoice | F29: POWDER ROOM DOORS - THRESHOLD: Marble / Silver Travertine (HONED) , Threshold, Beveled Edge, 34 x 6 1/2 x 5/7, Per Drawing #5 | G29: Magnolia LXR Dallas TX - | I29: 78.52 | J29: 14914363
A30: 45839 | B30: 34086/8 | C30: 34086/8 | D30: GV | E30: Invoice | F30: BATH POCKET DOORS - THRESHOLD: Marble / ERA Silver Travertine (HONED) , Threshold, Beveled Edge, 34 x 3-1/2 x 5/7, Per Drawing #6 | G30: Magnolia LXR Dallas TX - | I30: 108.8 | J30: 14914254
A31: 45839 | B31: 34086/8 | C31: 34086/8 | D31: GV | E31: Invoice | F31: MR-500A Custom Table lamp @ Bed - Opt1 | G31: Magnolia LXR Dallas TX - | I31: 1169.12 | J31: 14913085
A32: 45839 | B32: 34086/8 | C32: 34086/8 | D32: GV | E32: Invoice | F32: MR-500B Table lamp @ Bed - Opt2 | G32: Magnolia LXR Dallas TX - | I32: 512.67 | J32: 14912572
A33: 45839 | B33: 34086/8 | C33: 34086/8 | D33: GV | E33: Invoice | F33: MR-501A Pendant Lamp @ Bed - Opt1 | G33: Magnolia LXR Dallas TX - | I33: 427.61 | J33: 14912144
A34: 45839 | B34: 34086/8 | C34: 34086/8 | D34: GV | E34: Invoice | F34: MR-501B Pendant Lamp @ Bed - Opt2 | G34: Magnolia LXR Dallas TX - | I34: 585.08 | J34: 14911559
A35: 45839 | B35: 34086/8 | C35: 34086/8 | D35: GV | E35: Invoice | F35: MR-503 Table lamp @ Standard Room Entry | G35: Magnolia LXR Dallas TX - | I35: 534.19 | J35: 14911025
A36: 45839 | B36: 34086/8 | C36: 34086/8 | D36: GV | E36: Invoice | F36: MR-504 "Custom Floor Lamp @ 2 Bay Suite Dining Area" | G36: Magnolia LXR Dallas TX - | I36: 1044.32 | J36: 14909981
A37: 45839 | B37: 34086/8 | C37: 34086/8 | D37: GV | E37: Invoice | F37: MR-505A Custom Floor Lamp | G37: Magnolia LXR Dallas TX - | I37: 816.47 | J37: 14909164
A38: 45839 | B38: 34086/8 | C38: 34086/8 | D38: GV | E38: Invoice | F38: MR-505B Custom Floor Lamp | G38: Magnolia LXR Dallas TX - | I38: 1781.03 | J38: 14907383
A39: 45839 | B39: 34086/8 | C39: 34086/8 | D39: GV | E39: Invoice | F39: MR-506 Custom Table Lamp @ Sofa | G39: Magnolia LXR Dallas TX - | I39: 527.1 | J39: 14906856
... A44: 45839 | B44: 34289/3 | C44: 34289/3 | D44: GV | E44: Invoice | F44: LED Marquee Letters - Dims: 19.3" x 24" x 5-1/2", 1.0mm 201sus, with E26 LED Bulbs, CCT 3000K, Finish: Chemetal 931 Brushed Golden, Various Letters Based on List Shared and Approved Shop Drawings for Each Specific Property | G44: LaQuinta Yakima WA | I44: 541.7 | J44: 14903617
A45: 45839 | B45: 34967 | C45: 34967 | D45: GV | E45: Invoice | F45: GR-302C Desk Lamp | G45: LaQuinta Inn & Suites Oxford AL | I45: 3300.55 | J45: 14900317
A46: 45839 | B46: 35518 | C46: 35518 | D46: GV | E46: Invoice | F46: GR-200- C Entry Light @ Guestroom | G46: Hampton Downtown Montgomery | I46: 7976.1 | J46: 14892341
A47: 45839 | B47: 35518 | C47: 35518 | D47: GV | E47: Invoice | F47: GR-202- C Bedside Table Lamp @ Guestroom Nightstand | G47: Hampton Downtown Montgomery | I47: 1871.75 | J47: 14890469
A48: 45839 | B48: 35518 | C48: 35518 | D48: GV | E48: Invoice | F48: GR-203- C Single Nightstand Wall Sconce @ Guestroom | G48: Hampton Downtown Montgomery | I48: 7073.82 | J48: 14883395
A49: 45839 | B49: 35518 | C49: 35518 | D49: GV | E49: Invoice | F49: GR-204- C Double Nightstand Wall Sconce @ Guestroom | G49: Hampton Downtown Montgomery | I49: 1104.92 | J49: 14882290
A50: 45839 | B50: 35518 | C50: 35518 | D50: GV | E50: Invoice | F50: GR-205- C Desk Lamp @ Guestroom | G50: Hampton Downtown Montgomery | I50: 3898.07 | J50: 14878392
A51: 45839 | B51: 35518 | C51: 35518 | D51: GV | E51: Invoice | F51: GR-206- C Floor Lamp @ Guestroom | G51: Hampton Downtown Montgomery | I51: 6448.24 | J51: 14871944
A52: 45839 | B52: 36158 | C52: 36158 | D52: GV | E52: Invoice | F52: GR-202.B-SG Task Chair @ Guest Room | G52: Graniti Vicentia | I52: 288.76 | J52: 14871655
A53: 45839 | B53: 36158 | C53: 36158 | D53: GV | E53: Invoice | F53: GR-400-WT Window Treatment Panel Fabrication | G53: Graniti Vicentia | I53: 317.41 | J53: 14871338
A54: 45839 | B54: 36158 | C54: 36158 | D54: GV | E54: Invoice | F54: GR-504-LT Floor Lamp at King | G54: Graniti Vicentia | I54: 412.3 | J54: 14870926
A55: 45839 | B55: 36158 | C55: 36158 | D55: GV | E55: Invoice | F55: GR-801-MR (alt) Full Length Mirror @ Guestroom Alternate | G55: Graniti Vicentia | I55: 258.59 | J55: 14870667
A56: 45839 | B56: 36159/4 | C56: 36159/4 | D56: GV | E56: Invoice | F56: SG-805C Headboard Art (Small) @ Guestroom | G56: Graniti Vicentia | I56: 68.03 | J56: 14870599
A57: 45839 | B57: 36159/4 | C57: 36159/4 | D57: GV | E57: Invoice | F57: SG-806C Headboard Art (Large) @ Guestroom | G57: Graniti Vicentia | I57: 68.03 | J57: 14870531
A58: 45839 | B58: 36159/4 | C58: 36159/4 | D58: GV | E58: Invoice | F58: SG-804C Artwork at Sleeper Sofa | G58: Graniti Vicentia | I58: 68.03 | J58: 14870463
A59: 45839 | B59: 36159/4 | C59: 36159/4 | D59: GV | E59: Invoice | F59: SG-810C Artwork @ Guestbath, Please select Option 4. SP-810C.4. : | G59: Graniti Vicentia | I59: 176.01 | J59: 14870287
A60: 45839 | B60: 36159/4 | C60: 36159/4 | D60: GV | E60: Invoice | F60: SG-442C LED Mirror @ Guestbath | G60: Graniti Vicentia | I60: 488.42 | J60: 14869798
A61: 45839 | B61: 36159/4 | C61: 36159/4 | D61: GV | E61: Invoice | F61: SG-807C Full Length Mirror @ Guestroom | G61: Graniti Vicentia | I61: 152.23 | J61: 14869646
A62: 45839 | B62: 36159/4 | C62: 36159/4 | D62: GV | E62: Invoice | F62: SG-401C Desk Lamp @ Guestroom | G62: Graniti Vicentia | I62: 359.67 | J62: 14869286
A63: 45839 | B63: 36159/4 | C63: 36159/4 | D63: GV | E63: Invoice | F63: SG-403C End Table Lamp @ Guestroom | G63: Graniti Vicentia | I63: 283.67 | J63: 14869003
A64: 45839 | B64: 36159/4 | C64: 36159/4 | D64: GV | E64: Invoice | F64: SG-405C Headboard Sconce @ Guestroom | G64: Graniti Vicentia | I64: 347.35 | J64: 14868655
A65: 45839 | B65: 36159/4 | C65: 36159/4 | D65: GV | E65: Invoice | F65: SG-154C 24" Towel Bar @ Guest Bath | G65: Graniti Vicentia | I65: 45.37 | J65: 14868610
A66: 45839 | B66: 36159/4 | C66: 36159/4 | D66: GV | E66: Invoice | F66: SG-164C Toilet Paper Holder @ Guest Bath | G66: Graniti Vicentia | I66: 44.37 | J66: 14868566
A67: 45839 | B67: 36159/4 | C67: 36159/4 | D67: GV | E67: Invoice | F67: SG-166C Robe Hook @ Guest Bath | G67: Graniti Vicentia | I67: 40.35 | J67: 14868525
A68: 45839 | B68: 36159/4 | C68: 36159/4 | D68: GV | E68: Invoice | G68: Graniti Vicentia | I68: 468.1 | J68: 14868057
A69: 45839 | B69: 36221 | C69: 36221 | D69: GV | E69: Invoice | G69: CANDLEWOOD EASTRIDGE TN | I69: 144.47 | J69: 14867913
A70: 45839 | B70: 36221 | C70: 36221 | D70: GV | E70: Invoice | F70: GR-CG-406 Nightstand replacement | G70: CANDLEWOOD EASTRIDGE TN | I70: 242.4 | J70: 14867670
A71: 45839 | B71: 37217 | C71: 37217 | D71: GV | E71: Invoice | F71: GREAT-LT-05 Long pendant lamp @ Great room. GLASS SHADE ONLY. Great - LT-05. | G71: Continental Inns of America La Quinta Inn | I71: 127 | J71: 14867543
A72: 45839 | B72: 37579/3 | C72: 37579/3 | D72: GV | E72: Invoice | F72: F-X-302.CUR2 Desk Lamp @ FF Guestroom | G72: Fairfield Townplace East Hartford | I72: 3691.78 | J72: 14863852
A73: 45839 | B73: 37579/3 | C73: 37579/3 | D73: GV | E73: Invoice | F73: T-X-403.CU Decorative Wall Sconce @ TPS Guestroom | G73: Fairfield Townplace East Hartford | I73: 2231.97 | J73: 14861620
A74: 45839 | B74: 37579/3 | C74: 37579/3 | D74: GV | E74: Invoice | F74: T-AC-03 Puck Light @ TPS Guestroom | G74: Fairfield Townplace East Hartford | I74: 5616.46 | J74: 14856003
A75: 45839 | B75: 37579/3 | C75: 37579/3 | D75: GV | E75: Invoice | F75: EL-003.CU LED Strip Light | G75: Fairfield Townplace East Hartford | I75: 1164.61 | J75: 14854839
A76: 45839 | B76: 37579/3 | C76: 37579/3 | D76: GV | E76: Invoice | F76: GR-503-LT Reading Lamp at Headboard (Upgrade Option) | G76: Fairfield Townplace East Hartford | I76: 9135.09 | J76: 14845704
A77: 45839 | B77: 37579/3 | C77: 37579/3 | D77: GV | E77: Invoice | F77: T-X-003.CU Wall Base @ TPS Guestroom | G77: Fairfield Townplace East Hartford | I77: 751.78 | J77: 14844952
A78: 45839 | B78: 37579/3 | C78: 37579/3 | D78: GV | E78: Invoice | F78: 3x12â€ white matt straightedge / handmade (CLC75306) | G78: Fairfield Townplace East Hartford | I78: 886.64 | J78: 14844065
A79: 45839 | B79: 37759/3 | C79: 37759/3 | D79: GV | E79: Invoice | F79: Couch sleeper X-241-C legs and brackets | G79: ELEMENT FORTSMITH, ARKANSAS | I79: 455.33 | J79: 14843610
A80: 45839 | B80: 37759/3 | C80: 37759/3 | D80: GV | E80: Invoice | F80: Couch sleeper X-241-C pillows and back panels | G80: ELEMENT FORTSMITH, ARKANSAS | I80: 1065.93 | J80: 14842544
A81: 45839 | B81: 37759/3 | C81: 37759/3 | D81: GV | E81: Invoice | F81: Wall Sconce @ Guest_Corridor | G81: ELEMENT FORTSMITH, ARKANSAS | I81: 510.96 | J81: 14842033
A82: 45839 | B82: 37759/3 | C82: 37759/3 | D82: GV | E82: Invoice | F82: PG-402-C Wall sconce @ Guest corridor | G82: ELEMENT FORTSMITH, ARKANSAS | I82: 859.88 | J82: 14841173
A83: 45839 | B83: 37759/3 | C83: 37759/3 | D83: GV | E83: Invoice | F83: LM-229-C 93" Communal table @ Lounge | G83: ELEMENT FORTSMITH, ARKANSAS | I83: 800.5 | J83: 14840372
... A104: 45839 | B104: 37959/2 | C104: 37959/2 | D104: GV | E104: Invoice | F104: GST-502.C Headboard Sconces @ GR | G104: Monsoon Flower LLC | I104: 6110.49 | J104: 14823474
A105: 45839 | B105: 38130 | C105: 38130 | D105: GV | E105: Invoice | F105: LL-J-LT Pendant Lamp @ Reception Desk | G105: Pitt-Cran Hospitality, LLC/ Wingate Cranberry | I105: 787.36 | J105: 14822687
A106: 45839 | B106: 42390 | C106: 1143438 | D106: GV | E106: SupplierInvoice | F106: CPT-002A (City) Carpet Tile | G106: Signature Flooring | H106: 24023.91 | J106: 14846710
A107: 45839 | B107: 45991 | C107: S021249 | D107: GV | E107: SupplierInvoice | F107: TW -01 B.2.C Shower Surrounds - Back Panel (6" x 24" Vision - 60"W X 96"H) | G107: Modular Shower Walls | H107: 366.02 | J107: 14847076
A108: 45839 | B108: 45991 | C108: S021249 | D108: GV | E108: SupplierInvoice | F108: A FRAME (CENTER) / TARIMAS ESPECIALES | G108: Modular Shower Walls | H108: 200 | J108: 14847276
A109: 45839 | B109: 45991B | C109: S021295 | D109: GV | E109: SupplierInvoice | F109: PF-601A.C ADA Shower Pan with Trench Drain - 36" X 36" | G109: Modular Shower Walls | H109: 161.44 | J109: 14847438
A110: 45841 | B110: 45750 | C110: INV-HE.05-02-03-25 | D110: GV | E110: SupplierInvoice | F110: RF-01 SPC Flooring @ Guest Entry & Bath | G110: AMY ACT CO., LTD | H110: 26768.52 | J110: 14874206
A111: 45845 | B111: 35796/2 | C111: 35796/2 | D111: GV | E111: Invoice | F111: F-X-306.CU Floor Lamp @ FF Guestroom | G111: Fairfield Townplace East Hartford | I111: 2365.61 | J111: 14871841
A112: 45845 | B112: 35796/2 | C112: 35796/2 | D112: GV | E112: Invoice | F112: F-X-306.CU Floor Lamp @ FF Guestroom | G112: Fairfield Townplace East Hartford | I112: 230.75 | J112: 14871610
A113: 45845 | B113: 35796/2 | C113: 35796/2 | D113: GV | E113: Invoice | F113: F-X-302.CU Desk Lamp @ FF Guestroom | G113: Fairfield Townplace East Hartford | I113: 2462.3 | J113: 14869148
A114: 45845 | B114: 35796/2 | C114: 35796/2 | D114: GV | E114: Invoice | F114: F-X-407.CU Ceiling Light Fixture @ FF Guestroom | G114: Fairfield Townplace East Hartford | I114: 52.6 | J114: 14869095
A115: 45845 | B115: 35807 | C115: 35807 | D115: GV | E115: Invoice | F115: PA-OL-201 Circular Side Table @ Open Lounge | G115: Fairfield Townplace East Hartford | I115: 497.83 | J115: 14868597
A116: 45845 | B116: 35807 | C116: 35807 | D116: GV | E116: Invoice | F116: PA-FS-200 Dining Table @ Flex Space | G116: Fairfield Townplace East Hartford | I116: 530.2 | J116: 14868067
A117: 45845 | B117: 35807 | C117: 35807 | D117: GV | E117: Invoice | F117: PA-OP-200 Coffee table @ Outdoor Patio | G117: Fairfield Townplace East Hartford | I117: 390.84 | J117: 14867676
A118: 45845 | B118: 35808 | C118: 35808 | D118: GV | E118: Invoice | F118: PA-BR-300 Ceiling Light @ Breakfast Area | G118: Fairfield Townplace East Hartford | I118: 2822.91 | J118: 14864853
A119: 45845 | B119: 35808 | C119: 35808 | D119: GV | E119: Invoice | F119: PA-BR-300 Ceiling Light @ Breakfast Area | G119: Fairfield Townplace East Hartford | I119: 2575.18 | J119: 14862278
A120: 45845 | B120: 35808 | C120: 35808 | D120: GV | E120: Invoice | F120: PA-BR-302 Wall Sconce @ Breakfast Area | G120: Fairfield Townplace East Hartford | I120: 438.7 | J120: 14861839
A121: 45845 | B121: 35808 | C121: 35808 | D121: GV | E121: Invoice | F121: PA-GRT-301 Wall Sconce @ Great Room | G121: Fairfield Townplace East Hartford | I121: 431.98 | J121: 14861408
A122: 45845 | B122: 35808 | C122: 35808 | D122: GV | E122: Invoice | F122: PA-OA-300 Ceiling Light Fixture @ Ofiice area | G122: Fairfield Townplace East Hartford | I122: 742.27 | J122: 14860665
A123: 45845 | B123: 35808 | C123: 35808 | D123: GV | E123: Invoice | F123: PA-REG-300 Ceiling Light @ Registration | G123: Fairfield Townplace East Hartford | I123: 409.97 | J123: 14860255
A124: 45845 | B124: 35812 | C124: 35812 | D124: GV | E124: Invoice | F124: PA-BAR-800 Bar Counter ADA complaint with Footrest @ Bar | G124: Fairfield Townplace East Hartford | I124: 21460 | J124: 14838795
...

Sheet tab 13 aug cogs in sps
A1: Date | B1: Transaction# | C1: Invoice# | D1: Location | E1: Type | F1: Description | G1: Party | H1: Debit | I1: Credit | J1: Balance
A2: BALANCE FORWARD | J2: 15690904
A3: 45870 | B3: 37684/3 | C3: 37684/3 | D3: GV | E3: Invoice | F3: X-MW-710.C Closet Doors - 3 | G3: Ascent Residence inn Montgomery | I3: 43455.07 | J3: 15647449
A4: 45870 | B4: 37684/3 | C4: 37684/3 | D4: GV | E4: Invoice | F4: X-MW-710.C Closet Doors - 2 | G4: Ascent Residence inn Montgomery | I4: 1638.03 | J4: 15645811
A5: 45873 | B5: 35804/4 | C5: 35804/4 | D5: GV | E5: Invoice | F5: LEFT SIDE PANEL | G5: Fairfield Townplace East Hartford | I5: 3539.36 | J5: 15642271
A6: 45873 | B6: 35804/4 | C6: 35804/4 | D6: GV | E6: Invoice | F6: RIGHT SIDE PANEL | G6: Fairfield Townplace East Hartford | I6: 10925.86 | J6: 15631346
A7: 45873 | B7: 35804/4 | C7: 35804/4 | D7: GV | E7: Invoice | F7: BACK PANEL | G7: Fairfield Townplace East Hartford | I7: 5787.88 | J7: 15625558
A8: 45873 | B8: 35804/4 | C8: 35804/4 | D8: GV | E8: Invoice | F8: BACK PANEL | G8: Fairfield Townplace East Hartford | I8: 553.17 | J8: 15625004
A9: 45873 | B9: 35804/4 | C9: 35804/4 | D9: GV | E9: Invoice | F9: LEFT SIDE PANEL | G9: Fairfield Townplace East Hartford | I9: 314.32 | J9: 15624690
A10: 45873 | B10: 35804/4 | C10: 35804/4 | D10: GV | E10: Invoice | F10: RIGHT SIDE PANEL | G10: Fairfield Townplace East Hartford | I10: 314.32 | J10: 15624376
A11: 45873 | B11: 35804/4 | C11: 35804/4 | D11: GV | E11: Invoice | F11: COMES WITH PACKAGE DEAL @ NO CHARGE | G11: Fairfield Townplace East Hartford | I11: 113.07 | J11: 15624263
A12: 45873 | B12: 35804/4 | C12: 35804/4 | D12: GV | E12: Invoice | F12: ATTTIC STOCK - NO ADDTIONAL CHARGE - BACK PANEL | G12: Fairfield Townplace East Hartford | I12: 16.61 | J12: 15624246
A13: 45873 | B13: 38633 | C13: 38633 | D13: GV | E13: Invoice | G13: Classic American Homes & Renovations | I13: 996.55 | J13: 15623250
A14: 45873 | B14: 40272C | C14: SR273-33,ctnr1.2,GV002-8,GV038 | D14: GV | E14: SupplierInvoice | F14: Clean up PO# | G14: RICHWOOD HOSPITALITY CO LTD | J14: 15623250
A15: 45874 | B15: 38235/6 | C15: 38235/6 | D15: GV | E15: Invoice | F15: GR-103-C Side chair @ GR | G15: Hampton Inn Nashville | I15: 3554.18 | J15: 15619695
A16: 45874 | B16: 38235/6 | C16: 38235/6 | D16: GV | E16: Invoice | F16: GR-103-C Side chair @ GR | G16: Hampton Inn Nashville | I16: 323.11 | J16: 15619372
A17: 45874 | B17: 38235/6 | C17: 38235/6 | D17: GV | E17: Invoice | F17: GR-102-C Lounge chair @ GR | G17: Hampton Inn Nashville | I17: 10200.52 | J17: 15609172
A18: 45874 | B18: 38299/3 | C18: 38299/3 | D18: GV | E18: Invoice | F18: GR-316 ST - 58" Bathroom Vanity | G18: Chesterfield Hospitality Inc. | I18: 7364.1 | J18: 15601808
A19: 45874 | B19: 38299/3 | C19: 38299/3 | D19: GV | E19: Invoice | F19: GR-317 ST. 68" Bathroom Vanity | G19: Chesterfield Hospitality Inc. | I19: 3282.45 | J19: 15598525
A20: 45874 | B20: 38299/3 | C20: 38299/3 | D20: GV | E20: Invoice | F20: GR-361 ST 48" Accessible Bathroom Vanity | G20: Chesterfield Hospitality Inc. | I20: 748.55 | J20: 15597777
A21: 45874 | B21: 38299/3 | C21: 38299/3 | D21: GV | E21: Invoice | F21: GR-362.ADA ST 42" Accessible Bathroom Vanity | G21: Chesterfield Hospitality Inc. | I21: 334.96 | J21: 15597442
A22: 45874 | B22: 38301/4 | C22: 38301/4 | D22: GV | E22: Invoice | F22: GR-502 Full Length Mirror | G22: Chesterfield Hospitality Inc. | I22: 7314.78 | J22: 15590127
A23: 45874 | B23: 38304/3 | C23: 38304/3 | D23: GV | E23: Invoice | G23: Chesterfield Hospitality Inc. | I23: 1060.71 | J23: 15589066
A24: 45874 | B24: 38304/3 | C24: 38304/3 | D24: GV | E24: Invoice | G24: Chesterfield Hospitality Inc. | I24: 196.08 | J24: 15588870
A25: 45876 | B25: 37687 | C25: 37687 | D25: GV | E25: Invoice | G25: Ascent Residence inn Montgomery | I25: 222.07 | J25: 15588648
A26: 45876 | B26: 37697/3 | C26: 37697/3 | D26: GV | E26: Invoice | F26: ADA Sink @ Public Restroom Vanity | G26: Ascent Residence inn Montgomery | I26: 708.57 | J26: 15587940
A27: 45876 | B27: 38661 | C27: 38661 | D27: GV | E27: Invoice | F27: Reception Wall @ 3 panel Reception Back Wall @ comprised of 3 panel - 47 1/4 "W x 94" H, 23 5/8"W x 94" H & 27 1/8W x 94" H | G27: Comfort suites NC330 | I27: 1863.95 | J27: 15586076
A28: 45876 | B28: 38661 | C28: 38661 | D28: GV | E28: Invoice | F28: LED Strip Lights @ Custom Reception Back wall - 2 5/8 @ 46pcs | G28: Comfort suites NC330 | I28: 848.82 | J28: 15585227
A29: 45876 | B29: 38661 | C29: 38661 | D29: GV | E29: Invoice | F29: C LED Sign @ Reception Back Wall @ 1pc | G29: Comfort suites NC330 | I29: 253.96 | J29: 15584973
A30: 45877 | B30: 36248 | C30: 36248 | D30: GV | E30: Invoice | F30: LL-AA01-DP Decorative Pillows at Lounge Sectional - Per Spec | G30: Kings Bay Coastal Hotel Management LLC / Wingate Kingsland | I30: 20 | J30: 15584953
A31: 45877 | B31: 36250 | C31: 36250 | D31: GV | E31: Invoice | F31: LL-CH02-SG Dining Chair at Lounge/Dining Area | G31: Kings Bay Coastal Hotel Management LLC / Wingate Kingsland | I31: 1943.32 | J31: 15583009
A32: 45877 | B32: 36250 | C32: 36250 | D32: GV | E32: Invoice | F32: LL-CH04-SG Bar Stool at Bar Height Communal Table | G32: Kings Bay Coastal Hotel Management LLC / Wingate Kingsland | I32: 1315.99 | J32: 15581693
A33: 45877 | B33: 36250 | C33: 36250 | D33: GV | E33: Invoice | F33: LL-CH06-SG Lounge Chairs | G33: Kings Bay Coastal Hotel Management LLC / Wingate Kingsland | I33: 648.66 | J33: 15581045
A34: 45877 | B34: 36250 | C34: 36250 | D34: GV | E34: Invoice | F34: LL-CH09-SG Lobby Sectional at Reception Area | G34: Kings Bay Coastal Hotel Management LLC / Wingate Kingsland | I34: 2789.33 | J34: 15578255
A35: 45877 | B35: 36250 | C35: 36250 | D35: GV | E35: Invoice | F35: LL-CH10-SG Lounge Sectional Component: Armless Loveseat with Metal Legs | G35: Kings Bay Coastal Hotel Management LLC / Wingate Kingsland | I35: 509.33 | J35: 15577746
A36: 45877 | B36: 37412/2 | C36: 37412/2 | D36: GV | E36: Invoice | F36: TABLE LAMP X-300ALT1: Description: Slim profile desk lamp with integrated LED lighting. Base plate provided with Black rocker switch, (1) AC outlet, (1) Type C unit & (1) USB port. Finish: Brushed Nickel Dimensions: OA : 18"W X 8.3"D X 13.8"H , Lamp Type: Integrated LED Lamp Wattage: 5 W ; 2700K ; 120V LED Driver Lamp Quantity: 1 Switch Type: (1) On/Off Rocker Switch on Base Cord Length: 8 | G36: Ascent Hospitality Element Carmel Indiana | I36: 144.77 | J36: 15577601
A37: 45877 | B37: 37412/2 | C37: 37412/2 | D37: GV | E37: Invoice | F37: FLOOR LAMP X303C: Description: Floor lamp with metal post and tapered White Cylinderical lamp shade. Dimensions: 20.5"W X 14 | G37: Ascent Hospitality Element Carmel Indiana | I37: 563.31 | J37: 15577038
A38: 45877 | B38: 38292 | C38: 38292 | D38: GV | E38: Invoice | F38: To be produced in Italy on 12.1.24.(5 boxes) | G38: Veranda Homes | I38: 1364.62 | J38: 15575673
A39: 45877 | B39: 38292 | C39: 38292 | D39: GV | E39: Invoice | F39: Not in stock. To be produced in Italy. Production lead time 4-6 weeks (17 boxes) | G39: Veranda Homes | I39: 2304.57 | J39: 15573369
A40: 45877 | B40: 38292 | C40: 38292 | D40: GV | E40: Invoice | F40: In stock in Spain. | G40: Veranda Homes | I40: 4044.83 | J40: 15569324
A41: 45877 | B41: 38292 | C41: 38292 | D41: GV | E41: Invoice | F41: In stock in Spain. | G41: Veranda Homes | I41: 1819.97 | J41: 15567504
A42: 45877 | B42: 38292 | C42: 38292 | D42: GV | E42: Invoice | F42: In stock in Spain. | G42: Veranda Homes | I42: 985.77 | J42: 15566518
A43: 45877 | B43: 38292 | C43: 38292 | D43: GV | E43: Invoice | F43: In stock in Spain. | G43: Veranda Homes | I43: 1408.81 | J43: 15565110
A44: 45877 | B44: 38292 | C44: 38292 | D44: GV | E44: Invoice | G44: Veranda Homes | I44: 302.66 | J44: 15564807
A45: 45877 | B45: 38292 | C45: 38292 | D45: GV | E45: Invoice | F45: In stock in Spain. | G45: Veranda Homes | I45: 2852.21 | J45: 15561955
A46: 45877 | B46: 38292 | C46: 38292 | D46: GV | E46: Invoice | F46: In stock in Italy. (6 boxes) | G46: Veranda Homes | I46: 2025.41 | J46: 15559929
A47: 45877 | B47: 38292 | C47: 38292 | D47: GV | E47: Invoice | F47: In stock in Spain. | G47: Veranda Homes | I47: 2066.08 | J47: 15557863
A48: 45877 | B48: 38292 | C48: 38292 | D48: GV | E48: Invoice | F48: In stock in Spain. | G48: Veranda Homes | I48: 4695.63 | J48: 15553168
A49: 45877 | B49: 38292 | C49: 38292 | D49: GV | E49: Invoice | F49: In stock in Italy. Estimated lead time 9-11 weeks. (6 boxes ) | G49: Veranda Homes | I49: 317.29 | J49: 15552850
A50: 45877 | B50: 38292 | C50: 38292 | D50: GV | E50: Invoice | F50: To be produced in Italy on 11.22.24. Estimated lead time 10-12 weeks. (10 boxes) | G50: Veranda Homes | I50: 552.84 | J50: 15552297
A51: 45877 | B51: 38292 | C51: 38292 | D51: GV | E51: Invoice | F51: 3x6 glossy white (STA75150) | G51: Veranda Homes | I51: 26.07 | J51: 15552271
A52: 45877 | B52: 38292/2 | C52: 38292/2 | D52: GV | E52: Invoice | G52: Veranda Homes | I52: 2393.67 | J52: 15549878
A53: 45877 | B53: 38292/2 | C53: 38292/2 | D53: GV | E53: Invoice | G53: Veranda Homes | I53: 3901.31 | J53: 15545976
A54: 45877 | B54: 38292/2 | C54: 38292/2 | D54: GV | E54: Invoice | G54: Veranda Homes | I54: 508.72 | J54: 15545468
A55: 45877 | B55: 38292/2 | C55: 38292/2 | D55: GV | E55: Invoice | F55: In stock in Spain. | G55: Veranda Homes | I55: 1647.15 | J55: 15543820
A56: 45877 | B56: 38292/2 | C56: 38292/2 | D56: GV | E56: Invoice | F56: In stock in Spain. | G56: Veranda Homes | I56: 1317.85 | J56: 15542503
A57: 45880 | B57: 36663/2 | C57: 36663/2 | D57: GV | E57: Invoice | F57: Blackout Roller Shade & Sheer Drapery for ADA rooms | G57: Ascent Hospitality Tribute Carmel Indiana | I57: 566.78 | J57: 15541936
A58: 45880 | B58: 38259 | C58: 38259 | D58: GV | E58: Invoice | F58: PA - 109, Counter Stool @ Laundry Room | G58: HOME2 SOMERSET | I58: 365.65 | J58: 15541570
A59: 45880 | B59: 38260 | C59: 38260 | D59: GV | E59: Invoice | F59: PA - 201 Pendant Lighting @ Focus Booth | G59: HOME2 SOMERSET | I59: 1828.85 | J59: 15539741
A60: 45880 | B60: 38260 | C60: 38260 | D60: GV | E60: Invoice | F60: PA - 202 Bathroom Vanity Light | G60: HOME2 SOMERSET | I60: 419.17 | J60: 15539322
A61: 45880 | B61: 38260 | C61: 38260 | D61: GV | E61: Invoice | F61: PA - 203 Floor Lamp @ TV Lounge | G61: HOME2 SOMERSET | I61: 503.35 | J61: 15538819
A62: 45880 | B62: 38260 | C62: 38260 | D62: GV | E62: Invoice | F62: PA - 204 Wall Sconce @ Guest Corridor | G62: HOME2 SOMERSET | I62: 2651.64 | J62: 15536167
A63: 45880 | B63: 38260 | C63: 38260 | D63: GV | E63: Invoice | F63: PA - 205 Pendant Lighting @ Reception | G63: HOME2 SOMERSET | I63: 946.34 | J63: 15535221
A64: 45880 | B64: 38260 | C64: 38260 | D64: GV | E64: Invoice | F64: PA - 206 Table Lamp @ TV Lounge | G64: HOME2 SOMERSET | I64: 117.97 | J64: 15535103
A65: 45880 | B65: 38579 | C65: 38579 | D65: GV | E65: Invoice | F65: CORR-100 Accent Table Lamp | G65: Mesquite Gaming | I65: 990.31 | J65: 15534113
A66: 45881 | B66: 36681/10 | C66: 36681/10 | D66: GV | E66: Return Order | G66: Ascent Hospitality Tribute Carmel Indiana | H66: 73.11 | J66: 15534186
A67: 45881 | B67: 36681/10 | C67: 36681/10 | D67: GV | E67: Return Order | F67: 2 CNTR | G67: Ascent Hospitality Tribute Carmel Indiana | H67: 47.48 | J67: 15534233
A68: 45881 | B68: 36681/10 | C68: 36681/10 | D68: GV | E68: Return Order | F68: 2 CNTR | G68: Ascent Hospitality Tribute Carmel Indiana | H68: 26.69 | J68: 15534260
A69: 45881 | B69: 36681/10 | C69: 36681/10 | D69: GV | E69: Return Order | F69: 2 CNTR | G69: Ascent Hospitality Tribute Carmel Indiana | H69: 0.2 | J69: 15534260
A70: 45881 | B70: 36681/9 | C70: 36681/9 | D70: GV | E70: Return Order | F70: 2 CNTR | G70: Ascent Hospitality Tribute Carmel Indiana | H70: 2222.38 | J70: 15536482
A71: 45881 | B71: 36782/2 | C71: 36782/2 | D71: GV | E71: Invoice | G71: Ascent Home2 Montgomery | I71: 838.15 | J71: 15535644
A72: 45881 | B72: 36782/4 | C72: 36782/4 | D72: GV | E72: Invoice | F72: GR-002 43 1/2" LED Strip Light @ GR Closet | G72: Ascent Home2 Montgomery | I72: 3379.29 | J72: 15532265
A73: 45881 | B73: 36782/4 | C73: 36782/4 | D73: GV | E73: Invoice | F73: GR-003 37 1/2" LED Strip Light @ GR Closet | G73: Ascent Home2 Montgomery | I73: 3374.07 | J73: 15528891
A74: 45881 | B74: 36786/3 | C74: 36786/3 | D74: GV | E74: Invoice | F74: STAINLESS STEEL SINKS - Model# UMS-7, Dims: 460x410x228mm | G74: Ascent Home2 Montgomery | I74: 883.5 | J74: 15528007
A75: 45881 | B75: 36786/3 | C75: 36786/3 | D75: GV | E75: Invoice | F75: STAINLESS STEEL SINKS - Model# UMS-7, Dims: 460x410x228mm | G75: Ascent Home2 Montgomery | I75: 883.5 | J75: 15527124
A76: 45881 | B76: 36786/3 | C76: 36786/3 | D76: GV | E76: Invoice | F76: Nacarado 3 CM | G76: Ascent Home2 Montgomery | I76: 2120.84 | J76: 15525003
A77: 45881 | B77: 36786/3 | C77: 36786/3 | D77: GV | E77: Invoice | F77: side splashes | G77: Ascent Home2 Montgomery | I77: 23.73 | J77: 15524979
A78: 45881 | B78: 36786/3 | C78: 36786/3 | D78: GV | E78: Invoice | F78: Back Splash for Vanity Standard | G78: Ascent Home2 Montgomery | I78: 54.38 | J78: 15524925
A79: 45881 | B79: 36786/3 | C79: 36786/3 | D79: GV | E79: Invoice | F79: SAM-GVQZ-31. Sample Quartz Box. Includes 400 sets. | G79: Ascent Home2 Montgomery | I79: 3060 | J79: 15521865
A80: 45881 | B80: 36786/3 | C80: 36786/3 | D80: GV | E80: Invoice | F80: LBY-200B Sierra Solid R03 Carrara 31.5"Dia - Option 1 - China local quartz to match R03 Carrara | G80: Ascent Home2 Montgomery | I80: 925 | J80: 15520940
A81: 45881 | B81: 36786/3 | C81: 36786/3 | D81: GV | E81: Invoice | F81: A1, A2, B, C, D, E - LEFT | G81: Ascent Home2 Montgomery | I81: 1047.63 | J81: 15519892
A82: 45881 | B82: 36786/3 | C82: 36786/3 | D82: GV | E82: Invoice | F82: E ANSI TYPE A - LEFT | G82: Ascent Home2 Montgomery | I82: 523.81 | J82: 15519369
A83: 45881 | B83: 37676/4 | C83: 37676/4 | D83: GV | E83: Invoice | F83: X-CG-241.2.C Dresser Table Infront Of Closet - 38"W | G83: Ascent Residence inn Montgomery | I83: 20317.56 | J83: 15499051
... A92: 45881 | B92: 37678/7 | C92: 37678/7 | D92: GV | E92: Invoice | F92: X-SG-212PF.C Fabric at Lounge chair Pillow 1 | G92: Ascent Residence inn Montgomery | I92: 308.47 | J92: 15461633
A93: 45881 | B93: 37683/10 | C93: 37683/10 | D93: GV | E93: Invoice | G93: Ascent Residence inn Montgomery | I93: 16114.26 | J93: 15445519
A94: 45881 | B94: 37683/10 | C94: 37683/10 | D94: GV | E94: Invoice | F94: with ramp | G94: Ascent Residence inn Montgomery | I94: 332.7 | J94: 15445186
A95: 45881 | B95: 37683/10 | C95: 37683/10 | D95: GV | E95: Invoice | F95: Back Panel | G95: Ascent Residence inn Montgomery | I95: 4022.79 | J95: 15441163
A96: 45881 | B96: 37683/10 | C96: 37683/10 | D96: GV | E96: Invoice | F96: Side Panel (Stacked) | G96: Ascent Residence inn Montgomery | I96: 504.38 | J96: 15440659
A97: 45881 | B97: 37683/10 | C97: 37683/10 | D97: GV | E97: Invoice | F97: Side Panel (Stacked) | G97: Ascent Residence inn Montgomery | I97: 375.84 | J97: 15440283
A98: 45881 | B98: 37683/10 | C98: 37683/10 | D98: GV | E98: Invoice | G98: Ascent Residence inn Montgomery | I98: 2052.32 | J98: 15438231
A99: 45881 | B99: 37683/10 | C99: 37683/10 | D99: GV | E99: Invoice | G99: Ascent Residence inn Montgomery | I99: 2611.38 | J99: 15435619
A100: 45881 | B100: 37683/10 | C100: 37683/10 | D100: GV | E100: Invoice | F100: PF-TA-503.C 3" x 30" Accessory Ledge | G100: Ascent Residence inn Montgomery | I100: 1826 | J100: 15433793
A101: 45881 | B101: 37683/10 | C101: 37683/10 | D101: GV | E101: Invoice | F101: Attick Stock | G101: Ascent Residence inn Montgomery | J101: 15433793
A102: 45881 | B102: 37683/10 | C102: 37683/10 | D102: GV | E102: Invoice | F102: "A" frame for shower surrounds | G102: Ascent Residence inn Montgomery | I102: 200 | J102: 15433593
A103: 45881 | B103: 37683/10 | C103: 37683/10 | D103: GV | E103: Invoice | F103: Reinforced Packaging | G103: Ascent Residence inn Montgomery | I103: 200 | J103: 15433393
A104: 45881 | B104: 37683/10 | C104: 37683/10 | D104: GV | E104: Invoice | F104: "A" frame for shower surrounds | G104: Ascent Residence inn Montgomery | I104: 1400 | J104: 15431993
A105: 45881 | B105: 37683/9 | C105: 37683/9 | D105: GV | E105: Invoice | G105: Ascent Residence inn Montgomery | I105: 1750.49 | J105: 15430243
A106: 45881 | B106: 37688/3 | C106: 37688/3 | D106: GV | E106: Invoice | F106: LM-CG-200.C C table at bench | G106: Ascent Residence inn Montgomery | I106: 206.4 | J106: 15430036
A107: 45881 | B107: 37688/3 | C107: 37688/3 | D107: GV | E107: Invoice | F107: LM-CG-200.C C table at bench | G107: Ascent Residence inn Montgomery | I107: 206.4 | J107: 15429830
A108: 45881 | B108: 37688/3 | C108: 37688/3 | D108: GV | E108: Invoice | F108: LM-CG-232.C Accent Table at Lobby - 13 Dia | G108: Ascent Residence inn Montgomery | I108: 853.18 | J108: 15428977
...

Sheet tab 14 Q325 suppli activity sps
A1: Date | B1: Transaction# | C1: Invoice# | D1: Location | E1: Type | F1: Description | G1: Party | H1: Debit | I1: Credit | J1: Balance | K1: SPS | L1: NetSuite | M1: Remark | N1: SO#
A2: BALANCE FORWARD | J2: -2067844.5
A3: 45839 | B3: 43919 | C3: SR412-2 | D3: GV | E3: SupplierInvoice | G3: RICHWOOD HOSPITALITY CO LTD | I3: 6784.96 | J3: -2074629.5 | K3: Yes | L3: No
A4: 45839 | B4: 46779D | C4: SR151-10 | D4: GV | E4: SupplierInvoice | G4: HARMONY HOSPITALITY CO LTD | I4: 46332.04 | J4: -2120961.5 | K4: Yes | L4: No
A5: 45839 | B5: 46779E | C5: SR151-10 | D5: GV | E5: SupplierInvoice | G5: HARMONY HOSPITALITY CO LTD | I5: 39383.34 | J5: -2160344.9 | K5: Yes | L5: No
A6: 45839 | B6: 46779F | C6: SR151-10 | D6: GV | E6: SupplierInvoice | G6: HARMONY HOSPITALITY CO LTD | I6: 47598.07 | J6: -2207942.9 | K6: Yes | L6: No
A7: 45840 | B7: 44418F | C7: SR151-10 | D7: GV | E7: SupplierInvoice | G7: RICHWOOD HOSPITALITY CO LTD | I7: 3626 | J7: -2211568.9 | K7: Yes | L7: No
A8: 45840 | B8: 44418G | C8: SR151-10 | D8: GV | E8: SupplierInvoice | G8: RICHWOOD HOSPITALITY CO LTD | I8: 2254 | J8: -2213822.9 | K8: Yes | L8: No
A9: 45840 | B9: 44418H | C9: SR151-10 | D9: GV | E9: SupplierInvoice | G9: RICHWOOD HOSPITALITY CO LTD | I9: 57720.97 | J9: -2271543.9 | K9: Yes | L9: No
A10: 45840 | B10: 44698 | C10: SR151-10 | D10: GV | E10: SupplierInvoice | G10: RICHWOOD HOSPITALITY CO LTD | I10: 51958.22 | J10: -2323502.1 | K10: Yes | L10: No
A11: 45840 | B11: 44698C | C11: SR151-10 | D11: GV | E11: SupplierInvoice | G11: RICHWOOD HOSPITALITY CO LTD | I11: 51764.04 | J11: -2375266.1 | K11: Yes | L11: No
A12: 45840 | B12: 44698D | C12: SR151-10 | D12: GV | E12: SupplierInvoice | G12: RICHWOOD HOSPITALITY CO LTD | I12: 51958.22 | J12: -2427224.4 | K12: Yes | L12: No
A13: 45840 | B13: 44698E | C13: SR151-10 | D13: GV | E13: SupplierInvoice | G13: RICHWOOD HOSPITALITY CO LTD | I13: 40716.25 | J13: -2467940.6 | K13: Yes | L13: No
A14: 45840 | B14: W-0702 | D14: GV | E14: Payment | F14: 44776 | G14: WOW USA, Inc. | J14: -2467940.6
A15: 45841 | D15: GV | E15: Payment | G15: Beijing Topli Decorative Materials Co., LTD | J15: -2467940.6
A16: 45841 | D16: GV | E16: Payment | G16: Modular Shower Walls | J16: -2467940.6
A17: 45841 | B17: 43344 | C17: SR173-5PC | D17: GV | E17: SupplierInvoice | G17: HARMONY HOSPITALITY CO LTD | I17: 20234.4 | J17: -2488175 | K17: Yes | L17: No
A18: 45841 | B18: 44504B | C18: 8118121367 | D18: GV | E18: SupplierInvoice | G18: GRES DE ARAGON, S.A. | I18: 15801.36 | J18: -2503976.4 | K18: Yes | L18: No
A19: 45841 | B19: 45813 | C19: SR173-5PM | D19: GV | E19: SupplierInvoice | G19: HARMONY HOSPITALITY CO LTD | I19: 37963.9 | J19: -2541940.3 | K19: Yes | L19: No
A20: 45841 | B20: 45866 | C20: GV2025019-B | D20: GV | E20: SupplierInvoice | G20: XIAMEN DEYUAN PANMIN TRADING CO., LTD. | I20: 50 | J20: -2541990.3 | K20: Yes | L20: No
A21: 45841 | B21: W-0703 | D21: GV | E21: Payment | F21: 46028 | G21: Beijing Topli Decorative Materials Co., LTD | J21: -2541990.3
A22: 45846 | B22: W-0708 | D22: GV | E22: Payment | G22: Fama | J22: -2541990.3
A23: 45846 | B23: W-0708 | D23: GV | E23: Payment | F23: 45890 | G23: Jasfer Industry Co., Limited | J23: -2541990.3
A24: 45846 | B24: W-0708 | D24: GV | E24: Payment | F24: 45979 | G24: Jasfer Industry Co., Limited | J24: -2541990.3
A25: 45846 | B25: W-0708 | D25: GV | E25: Payment | F25: 42296 | G25: Jasfer Industry Co., Limited | J25: -2541990.3
A26: 45846 | B26: W-0708 | D26: GV | E26: Payment | F26: 45797 | G26: Jasfer Industry Co., Limited | J26: -2541990.3
A27: 45846 | B27: W-0708 | D27: GV | E27: Payment | F27: 45798 | G27: Jasfer Industry Co., Limited | J27: -2541990.3
A28: 45846 | B28: W-0708 | D28: GV | E28: Payment | F28: 44575 | G28: Jasfer Industry Co., Limited | J28: -2541990.3
A29: 45846 | B29: W-0708 | D29: GV | E29: Payment | F29: 36502 / 36503 / 36504 - CI copies not received | G29: Pantarei | J29: -2541990.3
A30: 45846 | B30: W-0708 | D30: GV | E30: Payment | G30: Jasfer Industry Co., Limited | J30: -2541990.3
A31: 45847 | B31: 40915B | C31: SR273-41P2 | D31: GV | E31: SupplierInvoice | G31: HARMONY HOSPITALITY CO LTD | I31: 6134.1 | J31: -2548124.4 | K31: Yes | L31: No
A32: 45847 | B32: 40918C | C32: SR273-41 | D32: GV | E32: SupplierInvoice | G32: HARMONY HOSPITALITY CO LTD | I32: 6160 | J32: -2554284.4 | K32: Yes | L32: No
A33: 45847 | B33: 42365B | C33: SR382-4P2 | D33: GV | E33: SupplierInvoice | G33: HARMONY HOSPITALITY CO LTD | I33: 601 | J33: -2554885.4 | K33: Yes | L33: No
A34: 45847 | B34: 42404 | C34: SR382-3 | D34: GV | E34: SupplierInvoice | G34: HARMONY HOSPITALITY CO LTD | I34: 5806.45 | J34: -2560691.8 | K34: Yes | L34: No
A35: 45847 | B35: 42567 | C35: 999187124 | D35: GV | E35: SupplierInvoice | G35: Shaw Integrated Solutions | I35: 112340.84 | J35: -2673032.7 | K35: Yes | L35: Yes | M35: amount difference in SPS & NetSUite
A36: 45847 | B36: 44380 | C36: 999187125 | D36: GV | E36: SupplierInvoice | G36: Shaw Industries Inc. Patcraft | I36: 14947.74 | J36: -2687980.4 | K36: Yes | L36: Yes
A37: 45847 | B37: 44381 | C37: 999187126 | D37: GV | E37: SupplierInvoice | G37: Shaw Industries Inc. Patcraft | I37: 21084.02 | J37: -2709064.4 | K37: Yes | L37: Yes
A38: 45847 | B38: 45049 | C38: SR273-37P2 | D38: GV | E38: SupplierInvoice | G38: HARMONY HOSPITALITY CO LTD | I38: 750.11 | J38: -2709814.5 | K38: Yes | L38: No
A39: 45847 | B39: 45813B | C39: SR173-5PM | D39: GV | E39: SupplierInvoice | G39: HARMONY HOSPITALITY CO LTD | I39: 5869 | J39: -2715683.5 | K39: Yes | L39: No
A40: 45847 | B40: 46025 | C40: SR405-2S | D40: GV | E40: SupplierInvoice | G40: HARMONY HOSPITALITY CO LTD | I40: 1401.2 | J40: -2717084.7 | K40: Yes | L40: Yes
A41: 45847 | B41: 47004 | C41: SR382-3 | D41: GV | E41: SupplierInvoice | G41: HARMONY HOSPITALITY CO LTD | I41: 2610.5 | J41: -2719695.2 | K41: Yes | L41: No
A42: 45848 | D42: GV | E42: Payment | G42: FAP CERAMICHE | J42: -2719695.2
A43: 45849 | B43: 36504 | C43: 16 | D43: GV | E43: SupplierInvoice | G43: Pantarei | I43: 45198 | J43: -2764893.2 | K43: Yes | L43: No
A44: 45852 | D44: GV | E44: Payment | G44: Modular Shower Walls | J44: -2764893.2
A45: 45852 | B45: 36502B | C45: 17 | D45: GV | E45: SupplierInvoice | G45: Pantarei | I45: 13148.19 | J45: -2778041.4 | K45: Yes | L45: No
A46: 45852 | B46: 36504B | C46: 17 | D46: GV | E46: SupplierInvoice | G46: Pantarei | I46: 36191.53 | J46: -2814233 | K46: Yes | L46: No
A47: 45852 | B47: 42017D | C47: 22534659-E | D47: GV | E47: SupplierInvoice | G47: Fama | I47: 28405.63 | J47: -2842638.6 | K47: Yes | L47: Yes
A48: 45852 | B48: W-0714 | D48: GV | E48: Payment | F48: 44501 | G48: Jasfer Industry Co., Limited | J48: -2842638.6
A49: 45852 | B49: W-0714 | D49: GV | E49: Payment | F49: HMMU9050194 | G49: Jasfer Industry Co., Limited | J49: -2842638.6
A50: 45852 | B50: W-0714 | D50: GV | E50: Payment | G50: Cambodian Zulite Stone Co., Ltd. | J50: -2842638.6
A51: 45853 | D51: GV | E51: Payment | G51: Shaw Industries Inc. Patcraft | J51: -2842638.6
A52: 45853 | D52: GV | E52: Payment | G52: HARMONY HOSPITALITY CO LTD | J52: -2842638.6
A53: 45853 | D53: GV | E53: Payment | F53: 45820 | G53: RICHWOOD HOSPITALITY CO LTD | J53: -2842638.6
A54: 45853 | D54: GV | E54: Payment | F54: 45820 | G54: HARMONY HOSPITALITY CO LTD | J54: -2842638.6
A55: 45853 | D55: GV | E55: Payment | F55: 44508 | G55: HARMONY HOSPITALITY CO LTD | J55: -2842638.6
A56: 45853 | D56: GV | E56: Payment | F56: 45830 | G56: HARMONY HOSPITALITY CO LTD | J56: -2842638.6
A57: 45853 | D57: GV | E57: Payment | G57: Shaw Industries Inc. Patcraft | J57: -2842638.6
A58: 45853 | B58: 664 | D58: GV | E58: Payment | G58: Shaw Industries Inc. Patcraft | J58: -2842638.6
A59: 45853 | B59: 664 | D59: GV | E59: Payment | F59: 43226 | G59: Shaw Integrated Solutions | J59: -2842638.6
A60: 45853 | B60: W-0715 | D60: GV | E60: Payment | G60: Fama | J60: -2842638.6
A61: 45853 | B61: W-0715 | D61: GV | E61: Payment | F61: 45808 | G61: MASOMEX GLOBAL | J61: -2842638.6
A62: 45853 | B62: W-0715 | D62: GV | E62: Payment | F62: 45809 | G62: MASOMEX GLOBAL | J62: -2842638.6
A63: 45853 | B63: W-0715 | D63: GV | E63: Payment | F63: 36502 / 36503 / 36504 - CI copies not received | G63: Pantarei | J63: -2842638.6
A64: 45855 | B64: 36503 | C64: 18 | D64: GV | E64: SupplierInvoice | G64: Pantarei | I64: 32084.13 | J64: -2874722.7 | K64: Yes | L64: No
A65: 45855 | B65: 46772C | C65: SR273-58,GV048 | D65: GV | E65: SupplierInvoice | G65: HARMONY HOSPITALITY CO LTD | I65: 209.13 | J65: -2874931.9 | K65: Yes | L65: No
A66: 45856 | B66: 36502C | C66: 19 | D66: GV | E66: SupplierInvoice | G66: Pantarei | I66: 10651.2 | J66: -2885583 | K66: Yes | L66: No
A67: 45856 | B67: 36503B | C67: 19 | D67: GV | E67: SupplierInvoice | G67: Pantarei | I67: 26373 | J67: -2911956 | K67: Yes | L67: No
A68: 45856 | B68: 45908 | C68: ZB202501005USA | D68: GV | E68: SupplierInvoice | G68: ZBOM Cabinets Crop. | I68: 12065.33 | J68: -2924021.4 | K68: Yes | L68: No
A69: 45859 | B69: 44066 | C69: SR350-13 | D69: GV | E69: SupplierInvoice | G69: HARMONY HOSPITALITY CO LTD | I69: 1216.27 | J69: -2925237.6 | K69: Yes | L69: No
A70: 45859 | B70: 44508 | C70: SR350-9 | D70: GV | E70: SupplierInvoice | G70: HARMONY HOSPITALITY CO LTD | I70: 12036 | J70: -2937273.6 | K70: Yes | L70: Yes
A71: 45859 | B71: 45820 | C71: SR350-9PA | D71: GV | E71: SupplierInvoice | G71: HARMONY HOSPITALITY CO LTD | I71: 31354.5 | J71: -2968628.1 | K71: Yes | L71: Yes
A72: 45859 | B72: 45830 | C72: SR350-9S | D72: GV | E72: SupplierInvoice | G72: HARMONY HOSPITALITY CO LTD | I72: 32079.54 | J72: -3000707.7 | K72: Yes | L72: Yes
A73: 45860 | B73: 46023 | C73: ZB202410026USA | D73: GV | E73: SupplierInvoice | G73: ZBOM Cabinets Crop. | I73: 11075.11 | J73: -3011782.8 | K73: Yes | L73: No
A74: 45860 | B74: W-0722 | D74: GV | E74: Payment | G74: Jasfer Industry Co., Limited | J74: -3011782.8
A75: 45860 | B75: W-0722 | D75: GV | E75: Payment | F75: MSKU1358592 | G75: Jasfer Industry Co., Limited | J75: -3011782.8
A76: 45861 | D76: GV | E76: Payment | F76: 46023 | G76: ZBOM Cabinets Crop. | J76: -3011782.8
A77: 45861 | D77: GV | E77: Payment | F77: 45783 | G77: ZBOM Cabinets Crop. | J77: -3011782.8
A78: 45861 | B78: 1416 | D78: GV | E78: Payment | F78: 45906 | G78: Tarkett | J78: -3011782.8
A79: 45861 | B79: 36502D | C79: 21 | D79: GV | E79: SupplierInvoice | G79: Pantarei | I79: 58714.73 | J79: -3070497.5 | K79: Yes | L79: No
A80: 45861 | B80: 43221 | C80: 45839 | D80: GV | E80: SupplierInvoice | G80: Jasfer Industry Co., Limited | I80: 1365743.8 | J80: -4436241.3 | K80: Yes | L80: Yes
A81: 45861 | B81: W-0723 | D81: GV | E81: Payment | F81: 45764 | G81: Fil Doux Textiles | J81: -4436241.3
A82: 45862 | B82: 36502E | C82: 22 | D82: GV | E82: SupplierInvoice | G82: Pantarei | I82: 33567.36 | J82: -4469808.7 | K82: Yes | L82: No
A83: 45862 | B83: 45545B | C83: SR273-52P2 | D83: GV | E83: SupplierInvoice | G83: RICHWOOD HOSPITALITY CO LTD | I83: 675.22 | J83: -4470483.9 | K83: Yes | L83: Yes
A84: 45862 | B84: 45546B | C84: SR273-52P2 | D84: GV | E84: SupplierInvoice | G84: RICHWOOD HOSPITALITY CO LTD | I84: 3183.18 | J84: -4473667.1 | K84: Yes | L84: Yes
A85: 45862 | B85: 45551 | C85: 25JSF03078 | D85: GV | E85: SupplierInvoice | G85: Jasfer Industry Co., Limited | I85: 71566.57 | J85: -4545233.6 | K85: Yes | L85: Yes
A86: 45862 | B86: 45604 | C86: SR273-52P3 | D86: GV | E86: SupplierInvoice | G86: HARMONY HOSPITALITY CO LTD | I86: 1855.26 | J86: -4547088.9 | K86: Yes | L86: Yes | M86: amount difference in SPS & NetSUite
A87: 45862 | B87: 45604B | C87: SR273-52P3 | D87: GV | E87: SupplierInvoice | G87: HARMONY HOSPITALITY CO LTD | I87: 18613.97 | J87: -4565702.9 | K87: Yes | L87: Yes | M87: amount difference in SPS & NetSUite
